Workbook
Name Instalaciones: Adicionales!$S$2:$S$3
Name SegmentaciónDeDatos_Año: #N/A
Name SegmentaciónDeDatos_Cliente: #N/A
Name SegmentaciónDeDatos_Cliente1: #N/A
Name SegmentaciónDeDatos_Cpto_Llamada: #N/A
Name SegmentaciónDeDatos_Detalle_Falla: #N/A
Name SegmentaciónDeDatos_Esp_Por: #N/A
Name SegmentaciónDeDatos_Estado: #N/A
Name SegmentaciónDeDatos_Estado_Asistencia: #N/A
Name SegmentaciónDeDatos_Negocio: #N/A
Name SegmentaciónDeDatos_Red: #N/A
Name SegmentaciónDeDatos_Semana: #N/A
Name SegmentaciónDeDatos_SR: #N/A
Name SegmentaciónDeDatos_Tec_Asignado: #N/A
Name SegmentaciónDeDatos_Tec_Asignado1: #N/A
Name SegmentaciónDeDatos_Tec_Zona: #N/A
Name SegmentaciónDeDatos_Tec_Zona1: #N/A
Name SegmentaciónDeDatos_Tecnico: #N/A
Name SegmentaciónDeDatos_Zona_Local: #N/A
Name SegmentaciónDeDatos_Zona_Local1: #N/A
Name SegmentaciónDeDatos_Zona_Local2: #N/A
Name SegmentaciónDeDatos_Zona_Local3: #N/A
Name SegmentaciónDeDatos_Zona_Local4: #N/A

Sheet Agenda
A2: =Pendientes[[#Totals],[Estado Asistencia]] -> 21 | B2: =TODAY() -> 46086 | C2: 0.39583333 | D2: =B2+C2 -> 46086.396 | E2: =COUNTIF(Adicionales[Semana], WEEKNUM(TODAY())) -> 0 | M2: =_xleta.HOUR -> #VALUE! | Y2: =TODAY()-90 -> 45996 | AD2: =EXACT('Suspendidos Total'!M5531,Agenda!AC9) -> FALSE | AP2: {=COUNTIF(Despachos[Tecnico ],AL25:AL27)} -> 0 | AR2: =COUNTIF(Despachos[Tecnico ],"Deus, Mariano") -> 0 | AT2: =COUNTIFS(#REF!,"SR", Despachos[Destino],"Mar del Plata") -> #REF!
A3: Días desde última atención | B3: R | C3: % SLA | D3: T | E3: Fecha Vto | F3: Hs SLA | G3: Fecha Coor | H3: Ctrl Inicio | I3: Estado Asistencia | J3: Pedido | K3: Stock | L3: Repuestos | M3: Cliente | N3: Luno | O3: MP | P3: Direccion | Q3: Localidad | R3: Provincia | S3: Tec Asignado | T3: Desc Problema | U3: Detalle Falla | V3: Modelo | W3: Cpto Llamada | X3: Prob Encontrado | Y3: Obs Control | Z3: Esp Por | AA3: Notas Internas | AB3: Red | AC3: ID | AD3: Zona Local | AE3: Tec Zona | AP3: 0
A4: {=IFERROR(_xlfn.LET(_xlpm.dias,NETWORKDAYS(MAX(IF((Suspendidos_Total[ID]=Pendientes[[#This Row],[ID]])*(Suspendidos_Total[PEDIDO]<>Pendientes[[#This Row],[Pedido]]), Suspendidos_Total[MARCA FIN])),TODAY(),Feriados[Fecha]),_xlpm.concepto,INDEX(Suspendidos_Total[CONCEPTO LLAMADA],MATCH(MAX(IF((Suspendidos_Total[ID]=Pendientes[[#This Row],[ID]])*(Suspendidos_Total[PEDIDO]<>Pendientes[[#This Row],[Pedido]]),Suspendidos_Total[MARCA FIN])),Suspendidos_Total[MARCA FIN],0)),IF(_xlpm.dias>=20,_xlpm.concepto & CHAR(160)& "-" & CHAR(160)& INT(_xlpm.dias/20)& " " & IF(INT(_xlpm.dias/20)=1,"mes","meses") & IF(MOD(_xlpm.dias,20)>0,CHAR(160)& "," & CHAR(160)& MOD(_xlpm.dias,20)& " " & IF(MOD(_xlpm.dias,20)=1,"día","días"),""), _xlpm.concepto & CHAR(160)& "-" & CHAR(160) & IF(INT(_xlpm.dias/5)>0,INT(_xlpm.dias/5)& " " & IF(INT(_xlpm.dias/5)=1,"semana","semanas") & IF(MOD(_xlpm.dias,5)>0,CHAR(160)& "," & CHAR(160),""),"") & IF(MOD(_xlpm.dias,5)>0,MOD(_xlpm.dias,5)& " " & IF(MOD(_xlpm.dias,5)=1,"día","días"),"")) ),"")} -> SC - 4 días | B4: 2 | C4: 0.62 | E4: 46083.542 | F4: 3 | G4: 46083.417 | H4: 5,2 h | I4: SEG Asistencia | J4: 101162470 | K4: 0 | L4: - | M4: BAPRO | N4: 11369 | O4: 0 | P4: Av. Constitucion 5850 | Q4: Mar Del Plata | R4: Buenos Aires | S4: Buratti, Fabian | T4: ATM-DEPÓSITO | U4: - Falla : presenta falla en la zona de recepción del efectivo. El módulo no está operativo._x000D_ _x000D_ se agrega Falla: esta trabado el módulo de dispensador. | V4: DT-7000H34N | W4: SERVICE CALL | AB4: ATM | AC4: BAPRO 11369 | AD4: Atlántica | AE4: Buratti, Fabian | AP4: 0
A5: {=IFERROR(_xlfn.LET(_xlpm.dias,NETWORKDAYS(MAX(IF((Suspendidos_Total[ID]=Pendientes[[#This Row],[ID]])*(Suspendidos_Total[PEDIDO]<>Pendientes[[#This Row],[Pedido]]), Suspendidos_Total[MARCA FIN])),TODAY(),Feriados[Fecha]),_xlpm.concepto,INDEX(Suspendidos_Total[CONCEPTO LLAMADA],MATCH(MAX(IF((Suspendidos_Total[ID]=Pendientes[[#This Row],[ID]])*(Suspendidos_Total[PEDIDO]<>Pendientes[[#This Row],[Pedido]]),Suspendidos_Total[MARCA FIN])),Suspendidos_Total[MARCA FIN],0)),IF(_xlpm.dias>=20,_xlpm.concepto & CHAR(160)& "-" & CHAR(160)& INT(_xlpm.dias/20)& " " & IF(INT(_xlpm.dias/20)=1,"mes","meses") & IF(MOD(_xlpm.dias,20)>0,CHAR(160)& "," & CHAR(160)& MOD(_xlpm.dias,20)& " " & IF(MOD(_xlpm.dias,20)=1,"día","días"),""), _xlpm.concepto & CHAR(160)& "-" & CHAR(160) & IF(INT(_xlpm.dias/5)>0,INT(_xlpm.dias/5)& " " & IF(INT(_xlpm.dias/5)=1,"semana","semanas") & IF(MOD(_xlpm.dias,5)>0,CHAR(160)& "," & CHAR(160),""),"") & IF(MOD(_xlpm.dias,5)>0,MOD(_xlpm.dias,5)& " " & IF(MOD(_xlpm.dias,5)=1,"día","días"),"")) ),"")} -> SC - 2 semanas , 3 días | C5: 0.62 | E5: 46083.542 | F5: 5 | G5: 46083.333 | H5: 7,2 h | I5: SEG Espera | J5: 101162437 | K5: 200182777 | L5: - | M5: BAPRO | N5: 8729 | O5: 0 | P5: Av. J. Peralta Ramos 1890 | Q5: Mar Del Plata | R5: Buenos Aires | S5: SIN ASIGNAR | T5: ATM-TECLADO DE CLIENTE | U5: falla en teclado de cliente, sistema muy lento, falla en dispensa (retiene billetes), queda funcionando con fallas. | V5: DT-7000H22V | W5: SERVICE CALL | X5: Teclado cliente | Y5: [02/03/2026] se suspende por pedido de repuesto (shutter con falla en motor) | Z5: Repuesto | AB5: ATM | AC5: BAPRO 8729 | AD5: Atlántica | AE5: Buratti, Fabian
A6: {=IFERROR(_xlfn.LET(_xlpm.dias,NETWORKDAYS(MAX(IF((Suspendidos_Total[ID]=Pendientes[[#This Row],[ID]])*(Suspendidos_Total[PEDIDO]<>Pendientes[[#This Row],[Pedido]]), Suspendidos_Total[MARCA FIN])),TODAY(),Feriados[Fecha]),_xlpm.concepto,INDEX(Suspendidos_Total[CONCEPTO LLAMADA],MATCH(MAX(IF((Suspendidos_Total[ID]=Pendientes[[#This Row],[ID]])*(Suspendidos_Total[PEDIDO]<>Pendientes[[#This Row],[Pedido]]),Suspendidos_Total[MARCA FIN])),Suspendidos_Total[MARCA FIN],0)),IF(_xlpm.dias>=20,_xlpm.concepto & CHAR(160)& "-" & CHAR(160)& INT(_xlpm.dias/20)& " " & IF(INT(_xlpm.dias/20)=1,"mes","meses") & IF(MOD(_xlpm.dias,20)>0,CHAR(160)& "," & CHAR(160)& MOD(_xlpm.dias,20)& " " & IF(MOD(_xlpm.dias,20)=1,"día","días"),""), _xlpm.concepto & CHAR(160)& "-" & CHAR(160) & IF(INT(_xlpm.dias/5)>0,INT(_xlpm.dias/5)& " " & IF(INT(_xlpm.dias/5)=1,"semana","semanas") & IF(MOD(_xlpm.dias,5)>0,CHAR(160)& "," & CHAR(160),""),"") & IF(MOD(_xlpm.dias,5)>0,MOD(_xlpm.dias,5)& " " & IF(MOD(_xlpm.dias,5)=1,"día","días"),"")) ),"")} -> SC - 1 semana | B6: 1 | C6: 0.9 | E6: 46083.564 | F6: 3.0422222 | G6: 46083.438 | H6: 4,7 h | I6: SEG Asistencia | J6: 101162414 | K6: 200182749 | L6: Repuesto Enviado | M6: BAPRO | N6: 11214 | O6: 0 | P6: San Martin 1 | Q6: Pellegrini | R6: Buenos Aires | S6: Garcia, Alejandro Javier | T6: ATM-DISPENSADOR | U6: traba billetes | V6: DT-7000H34N | W6: SERVICE CALL | X6: Dispensador | Y6: [27/02/2026] Se suspende por pedido de parte (falla de motor de stacker) | Z6: Repuesto | AB6: ATM | AC6: BAPRO 11214 | AD6: Oeste | AE6: Garcia, Alejandro Javier
A7: {=IFERROR(_xlfn.LET(_xlpm.dias,NETWORKDAYS(MAX(IF((Suspendidos_Total[ID]=Pendientes[[#This Row],[ID]])*(Suspendidos_Total[PEDIDO]<>Pendientes[[#This Row],[Pedido]]), Suspendidos_Total[MARCA FIN])),TODAY(),Feriados[Fecha]),_xlpm.concepto,INDEX(Suspendidos_Total[CONCEPTO LLAMADA],MATCH(MAX(IF((Suspendidos_Total[ID]=Pendientes[[#This Row],[ID]])*(Suspendidos_Total[PEDIDO]<>Pendientes[[#This Row],[Pedido]]),Suspendidos_Total[MARCA FIN])),Suspendidos_Total[MARCA FIN],0)),IF(_xlpm.dias>=20,_xlpm.concepto & CHAR(160)& "-" & CHAR(160)& INT(_xlpm.dias/20)& " " & IF(INT(_xlpm.dias/20)=1,"mes","meses") & IF(MOD(_xlpm.dias,20)>0,CHAR(160)& "," & CHAR(160)& MOD(_xlpm.dias,20)& " " & IF(MOD(_xlpm.dias,20)=1,"día","días"),""), _xlpm.concepto & CHAR(160)& "-" & CHAR(160) & IF(INT(_xlpm.dias/5)>0,INT(_xlpm.dias/5)& " " & IF(INT(_xlpm.dias/5)=1,"semana","semanas") & IF(MOD(_xlpm.dias,5)>0,CHAR(160)& "," & CHAR(160),""),"") & IF(MOD(_xlpm.dias,5)>0,MOD(_xlpm.dias,5)& " " & IF(MOD(_xlpm.dias,5)=1,"día","días"),"")) ),"")} -> AIEC - 3 meses , 12 días | C7: 0.01 | E7: 46084.499 | F7: 25.010833 | G7: 46083.457 | H7: 4,2 h | I7: SEG Registrado | J7: 101163020 | K7: 0 | L7: - | M7: BANCO NACION | N7: 4203 | O7: 1 | P7: Rivadavia 698 | Q7: General Villegas | R7: Buenos Aires | S7: SIN ASIGNAR | T7: ATM-DISPENSADOR | U7: Dispensador con correas salidas de su posición eso genera que el ATM no dispense y quede fuera de servicio_x000D_ SLA Vence 03/03 11:42_x000D_ Prosegur 10 a 18 | V7: DT-7000H34N (FECT) | W7: SERVICE CALL | AB7: ATM | AC7: BANCO NACION 4203 | AD7: Oeste | AE7: Garcia, Alejandro Javier
A8: {=IFERROR(_xlfn.LET(_xlpm.dias,NETWORKDAYS(MAX(IF((Suspendidos_Total[ID]=Pendientes[[#This Row],[ID]])*(Suspendidos_Total[PEDIDO]<>Pendientes[[#This Row],[Pedido]]), Suspendidos_Total[MARCA FIN])),TODAY(),Feriados[Fecha]),_xlpm.concepto,INDEX(Suspendidos_Total[CONCEPTO LLAMADA],MATCH(MAX(IF((Suspendidos_Total[ID]=Pendientes[[#This Row],[ID]])*(Suspendidos_Total[PEDIDO]<>Pendientes[[#This Row],[Pedido]]),Suspendidos_Total[MARCA FIN])),Suspendidos_Total[MARCA FIN],0)),IF(_xlpm.dias>=20,_xlpm.concepto & CHAR(160)& "-" & CHAR(160)& INT(_xlpm.dias/20)& " " & IF(INT(_xlpm.dias/20)=1,"mes","meses") & IF(MOD(_xlpm.dias,20)>0,CHAR(160)& "," & CHAR(160)& MOD(_xlpm.dias,20)& " " & IF(MOD(_xlpm.dias,20)=1,"día","días"),""), _xlpm.concepto & CHAR(160)& "-" & CHAR(160) & IF(INT(_xlpm.dias/5)>0,INT(_xlpm.dias/5)& " " & IF(INT(_xlpm.dias/5)=1,"semana","semanas") & IF(MOD(_xlpm.dias,5)>0,CHAR(160)& "," & CHAR(160),""),"") & IF(MOD(_xlpm.dias,5)>0,MOD(_xlpm.dias,5)& " " & IF(MOD(_xlpm.dias,5)=1,"día","días"),"")) ),"")} -> SC - 1 semana , 3 días | C8: 0.4 | E8: 46083.761 | F8: 6.7644444 | G8: 46083.479 | H8: 3,7 h | I8: Asistencia Demorada | J8: 101162906 | K8: 0 | L8: - | M8: ACA | N8: 002359016370 | O8: 0 | P8: Diagonal F De La Palza 1733 | Q8: Miramar | R8: Buenos Aires | S8: Castaño, Matias | T8: SMC-IMPRESORA | U8: Cliente reporta que no le imprime el dispositivo, se ejecutaron las siguientes pruebas:_x000D_ Simulación de cambio de papel_x000D_ Test Print automático (fallido)_x000D_ Página de prueba de Windows (fallida)_x000D_ Configuración completa en CAOS (correcta)_x000D_ Verificación de coincidencia del nombre_x000D_ Seteo desde modo Supervisor_x000D_ _x000D_ La impresora continúa sin imprimir en ningún escenario._x000D_ Posible falla física del módulo de impresión y no un problema de configuración._x000D_ Se solicita asistencia técnica para su verificación +5492291401747 | V8: CIMA SDM500 | W8: SERVICE CALL | Y8: Cliente reporta que no le imprime el dispositivo, se ejecutaron las siguientes pruebas:_x000D_ Simulación de cambio de papel_x000D_ Test Print automático (fallido)_x000D_ Página de prueba de Windows (fallida)_x000D_ Configuración completa en CAOS (correcta)_x000D_ Verificación de coincidencia del nombre_x000D_ Seteo desde modo Supervisor_x000D_ _x000D_ La impresora continúa sin imprimir en ningún escenario._x000D_ Posible falla física del módulo de impresión y no un problema de configuración._x000D_ Se solicita asistencia técnica para su verificacion _x000D_ +5492291401747 | AB8: Cash Today | AC8: ACA 002359016370 | AD8: Atlántica | AE8: Castaño, Matias
A9: {=IFERROR(_xlfn.LET(_xlpm.dias,NETWORKDAYS(MAX(IF((Suspendidos_Total[ID]=Pendientes[[#This Row],[ID]])*(Suspendidos_Total[PEDIDO]<>Pendientes[[#This Row],[Pedido]]), Suspendidos_Total[MARCA FIN])),TODAY(),Feriados[Fecha]),_xlpm.concepto,INDEX(Suspendidos_Total[CONCEPTO LLAMADA],MATCH(MAX(IF((Suspendidos_Total[ID]=Pendientes[[#This Row],[ID]])*(Suspendidos_Total[PEDIDO]<>Pendientes[[#This Row],[Pedido]]),Suspendidos_Total[MARCA FIN])),Suspendidos_Total[MARCA FIN],0)),IF(_xlpm.dias>=20,_xlpm.concepto & CHAR(160)& "-" & CHAR(160)& INT(_xlpm.dias/20)& " " & IF(INT(_xlpm.dias/20)=1,"mes","meses") & IF(MOD(_xlpm.dias,20)>0,CHAR(160)& "," & CHAR(160)& MOD(_xlpm.dias,20)& " " & IF(MOD(_xlpm.dias,20)=1,"día","días"),""), _xlpm.concepto & CHAR(160)& "-" & CHAR(160) & IF(INT(_xlpm.dias/5)>0,INT(_xlpm.dias/5)& " " & IF(INT(_xlpm.dias/5)=1,"semana","semanas") & IF(MOD(_xlpm.dias,5)>0,CHAR(160)& "," & CHAR(160),""),"") & IF(MOD(_xlpm.dias,5)>0,MOD(_xlpm.dias,5)& " " & IF(MOD(_xlpm.dias,5)=1,"día","días"),"")) ),"")} -> MTM - 1 semana , 2 días | B9: 2 | C9: 0 | E9: 46084.466 | F9: 24.008056 | G9: 46083.466 | H9: 4,0 h | I9: SEG Registrado | J9: 101163028 | K9: 0 | L9: - | M9: BAPRO | N9: 3049 | O9: 0 | P9: Calle 2 Nº 1005 | Q9: Santa Teresita | R9: Buenos Aires | S9: SIN ASIGNAR | T9: ATM-DEPÓSITO | U9: Falla: en el módulo de depósito. Sigue presentando el mismo inconveniente que cuando vino el técnico.- | V9: DT-7000H34N | W9: SERVICE CALL | AB9: ATM | AC9: BAPRO 3049 | AD9: Atlántica | AE9: Montiel, Juan Fernando
A10: {=IFERROR(_xlfn.LET(_xlpm.dias,NETWORKDAYS(MAX(IF((Suspendidos_Total[ID]=Pendientes[[#This Row],[ID]])*(Suspendidos_Total[PEDIDO]<>Pendientes[[#This Row],[Pedido]]), Suspendidos_Total[MARCA FIN])),TODAY(),Feriados[Fecha]),_xlpm.concepto,INDEX(Suspendidos_Total[CONCEPTO LLAMADA],MATCH(MAX(IF((Suspendidos_Total[ID]=Pendientes[[#This Row],[ID]])*(Suspendidos_Total[PEDIDO]<>Pendientes[[#This Row],[Pedido]]),Suspendidos_Total[MARCA FIN])),Suspendidos_Total[MARCA FIN],0)),IF(_xlpm.dias>=20,_xlpm.concepto & CHAR(160)& "-" & CHAR(160)& INT(_xlpm.dias/20)& " " & IF(INT(_xlpm.dias/20)=1,"mes","meses") & IF(MOD(_xlpm.dias,20)>0,CHAR(160)& "," & CHAR(160)& MOD(_xlpm.dias,20)& " " & IF(MOD(_xlpm.dias,20)=1,"día","días"),""), _xlpm.concepto & CHAR(160)& "-" & CHAR(160) & IF(INT(_xlpm.dias/5)>0,INT(_xlpm.dias/5)& " " & IF(INT(_xlpm.dias/5)=1,"semana","semanas") & IF(MOD(_xlpm.dias,5)>0,CHAR(160)& "," & CHAR(160),""),"") & IF(MOD(_xlpm.dias,5)>0,MOD(_xlpm.dias,5)& " " & IF(MOD(_xlpm.dias,5)=1,"día","días"),"")) ),"")} -> SC - 1 mes , 18 días | C10: 0 | E10: 46083.747 | F10: 3.9219444 | G10: 46083.583 | H10: 1,2 h | I10: Asistencia Demorada | J10: 101162952 | K10: 0 | L10: - | M10: BAPRO | N10: 11488 | O10: 0 | P10: Avellaneda 199 | Q10: General Madariaga | R10: Buenos Aires | S10: Aldayturriaga, Martin | T10: ATM-LECTORA DE TARJETA | U10: falla en la lectora de tarjetas | V10: DT-7000H22V | W10: SERVICE CALL | AB10: ATM | AC10: BAPRO 11488 | AD10: Atlántica | AE10: Montiel, Juan Fernando
A11: {=IFERROR(_xlfn.LET(_xlpm.dias,NETWORKDAYS(MAX(IF((Suspendidos_Total[ID]=Pendientes[[#This Row],[ID]])*(Suspendidos_Total[PEDIDO]<>Pendientes[[#This Row],[Pedido]]), Suspendidos_Total[MARCA FIN])),TODAY(),Feriados[Fecha]),_xlpm.concepto,INDEX(Suspendidos_Total[CONCEPTO LLAMADA],MATCH(MAX(IF((Suspendidos_Total[ID]=Pendientes[[#This Row],[ID]])*(Suspendidos_Total[PEDIDO]<>Pendientes[[#This Row],[Pedido]]),Suspendidos_Total[MARCA FIN])),Suspendidos_Total[MARCA FIN],0)),IF(_xlpm.dias>=20,_xlpm.concepto & CHAR(160)& "-" & CHAR(160)& INT(_xlpm.dias/20)& " " & IF(INT(_xlpm.dias/20)=1,"mes","meses") & IF(MOD(_xlpm.dias,20)>0,CHAR(160)& "," & CHAR(160)& MOD(_xlpm.dias,20)& " " & IF(MOD(_xlpm.dias,20)=1,"día","días"),""), _xlpm.concepto & CHAR(160)& "-" & CHAR(160) & IF(INT(_xlpm.dias/5)>0,INT(_xlpm.dias/5)& " " & IF(INT(_xlpm.dias/5)=1,"semana","semanas") & IF(MOD(_xlpm.dias,5)>0,CHAR(160)& "," & CHAR(160),""),"") & IF(MOD(_xlpm.dias,5)>0,MOD(_xlpm.dias,5)& " " & IF(MOD(_xlpm.dias,5)=1,"día","días"),"")) ),"")} -> MTM - 1 semana , 2 días | B11: 1 | C11: 0.05 | E11: 46085.75 | F11: 56.616667 | G11: 46083.391 | H11: 5,8 h | I11: SEG Registrado | J11: 101162971 | K11: 0 | L11: - | M11: BANCO HIPOTECARIO | N11: 035TI0001 | O11: 0 | P11: General Rodriguez 726 | Q11: Tandil | R11: Buenos Aires | S11: SIN ASIGNAR | T11: ATM-DEPÓSITO | U11: Informamos que tras visita técnica el equipo continua con falla en modulo ENA | V11: TAS OPTEVA 720 R/L | W11: SERVICE CALL | AB11: ATM | AC11: BANCO HIPOTECARIO 035TI0001 | AD11: Oeste | AE11: Aldayturriaga, Martin
A12: {=IFERROR(_xlfn.LET(_xlpm.dias,NETWORKDAYS(MAX(IF((Suspendidos_Total[ID]=Pendientes[[#This Row],[ID]])*(Suspendidos_Total[PEDIDO]<>Pendientes[[#This Row],[Pedido]]), Suspendidos_Total[MARCA FIN])),TODAY(),Feriados[Fecha]),_xlpm.concepto,INDEX(Suspendidos_Total[CONCEPTO LLAMADA],MATCH(MAX(IF((Suspendidos_Total[ID]=Pendientes[[#This Row],[ID]])*(Suspendidos_Total[PEDIDO]<>Pendientes[[#This Row],[Pedido]]),Suspendidos_Total[MARCA FIN])),Suspendidos_Total[MARCA FIN],0)),IF(_xlpm.dias>=20,_xlpm.concepto & CHAR(160)& "-" & CHAR(160)& INT(_xlpm.dias/20)& " " & IF(INT(_xlpm.dias/20)=1,"mes","meses") & IF(MOD(_xlpm.dias,20)>0,CHAR(160)& "," & CHAR(160)& MOD(_xlpm.dias,20)& " " & IF(MOD(_xlpm.dias,20)=1,"día","días"),""), _xlpm.concepto & CHAR(160)& "-" & CHAR(160) & IF(INT(_xlpm.dias/5)>0,INT(_xlpm.dias/5)& " " & IF(INT(_xlpm.dias/5)=1,"semana","semanas") & IF(MOD(_xlpm.dias,5)>0,CHAR(160)& "," & CHAR(160),""),"") & IF(MOD(_xlpm.dias,5)>0,MOD(_xlpm.dias,5)& " " & IF(MOD(_xlpm.dias,5)=1,"día","días"),"")) ),"")} -> MTM - 2 semanas , 2 días | B12: 1 | C12: 0.2 | E12: 46084.42 | F12: 20.085556 | G12: 46083.583 | H12: 1,2 h | I12: Asistencia Demorada | J12: 101162995 | K12: 0 | L12: - | M12: BAPRO | N12: 6571 | O12: 0 | P12: Calle 64 3000 | Q12: Necochea | R12: Buenos Aires | S12: Chiriello, Pablo Javier | T12: ATM-IMPRESORA DE RECIBO | U12: - Falla : presenta falla en la impresión de ticket.Es un error constante que deja el atm fuera de servicio. Por el momento se encuentra funcionando , pero son arreglos temporales. | V12: DT-7000H34N | W12: SERVICE CALL | AB12: ATM | AC12: BAPRO 6571 | AD12: Atlántica | AE12: Chiriello, Pablo Javier
A13: {=IFERROR(_xlfn.LET(_xlpm.dias,NETWORKDAYS(MAX(IF((Suspendidos_Total[ID]=Pendientes[[#This Row],[ID]])*(Suspendidos_Total[PEDIDO]<>Pendientes[[#This Row],[Pedido]]), Suspendidos_Total[MARCA FIN])),TODAY(),Feriados[Fecha]),_xlpm.concepto,INDEX(Suspendidos_Total[CONCEPTO LLAMADA],MATCH(MAX(IF((Suspendidos_Total[ID]=Pendientes[[#This Row],[ID]])*(Suspendidos_Total[PEDIDO]<>Pendientes[[#This Row],[Pedido]]),Suspendidos_Total[MARCA FIN])),Suspendidos_Total[MARCA FIN],0)),IF(_xlpm.dias>=20,_xlpm.concepto & CHAR(160)& "-" & CHAR(160)& INT(_xlpm.dias/20)& " " & IF(INT(_xlpm.dias/20)=1,"mes","meses") & IF(MOD(_xlpm.dias,20)>0,CHAR(160)& "," & CHAR(160)& MOD(_xlpm.dias,20)& " " & IF(MOD(_xlpm.dias,20)=1,"día","días"),""), _xlpm.concepto & CHAR(160)& "-" & CHAR(160) & IF(INT(_xlpm.dias/5)>0,INT(_xlpm.dias/5)& " " & IF(INT(_xlpm.dias/5)=1,"semana","semanas") & IF(MOD(_xlpm.dias,5)>0,CHAR(160)& "," & CHAR(160),""),"") & IF(MOD(_xlpm.dias,5)>0,MOD(_xlpm.dias,5)& " " & IF(MOD(_xlpm.dias,5)=1,"día","días"),"")) ),"")} -> MTM - 1 semana , 2 días | B13: 2 | C13: 0.62 | E13: 46083.542 | F13: 5 | G13: 46083.333 | H13: 7,2 h | I13: SEG Asistencia | J13: 101162436 | K13: 200182779 | L13: - | M13: BAPRO | N13: 8728 | O13: 0 | P13: Av. J. Peralta Ramos 1890 | Q13: Mar Del Plata | R13: Buenos Aires | S13: Chiriello, Pablo Javier | T13: ATM-LECTORA DE TARJETA | U13: Falla: falla en lectora de tarjetas, queda en servicio con falla. | V13: DT-7000H22V | W13: SERVICE CALL | AB13: ATM | AC13: BAPRO 8728 | AD13: Atlántica | AE13: Chiriello, Pablo Javier
A14: {=IFERROR(_xlfn.LET(_xlpm.dias,NETWORKDAYS(MAX(IF((Suspendidos_Total[ID]=Pendientes[[#This Row],[ID]])*(Suspendidos_Total[PEDIDO]<>Pendientes[[#This Row],[Pedido]]), Suspendidos_Total[MARCA FIN])),TODAY(),Feriados[Fecha]),_xlpm.concepto,INDEX(Suspendidos_Total[CONCEPTO LLAMADA],MATCH(MAX(IF((Suspendidos_Total[ID]=Pendientes[[#This Row],[ID]])*(Suspendidos_Total[PEDIDO]<>Pendientes[[#This Row],[Pedido]]),Suspendidos_Total[MARCA FIN])),Suspendidos_Total[MARCA FIN],0)),IF(_xlpm.dias>=20,_xlpm.concepto & CHAR(160)& "-" & CHAR(160)& INT(_xlpm.dias/20)& " " & IF(INT(_xlpm.dias/20)=1,"mes","meses") & IF(MOD(_xlpm.dias,20)>0,CHAR(160)& "," & CHAR(160)& MOD(_xlpm.dias,20)& " " & IF(MOD(_xlpm.dias,20)=1,"día","días"),""), _xlpm.concepto & CHAR(160)& "-" & CHAR(160) & IF(INT(_xlpm.dias/5)>0,INT(_xlpm.dias/5)& " " & IF(INT(_xlpm.dias/5)=1,"semana","semanas") & IF(MOD(_xlpm.dias,5)>0,CHAR(160)& "," & CHAR(160),""),"") & IF(MOD(_xlpm.dias,5)>0,MOD(_xlpm.dias,5)& " " & IF(MOD(_xlpm.dias,5)=1,"día","días"),"")) ),"")} -> SC - 2 semanas | B14: 3 | C14: 0.12 | E14: 46084.583 | F14: 25 | G14: 46083.542 | H14: 2,2 h | I14: Asistencia Demorada | J14: 101162508 | K14: 200182770 | L14: - | M14: BANCO CREDICOOP | N14: 812051 | O14: 0 | P14: Sarmiento 2200 | Q14: Bahia Blanca | R14: Buenos Aires | S14: Pavon, Diego Emanuel | T14: ATM-ACEPTADOR DE BILLETES | U14: Falla en Depósitos de Acreditación Inmediata:_x000D_ El ATM no muestra errores pero rechaza casi todos los billetes, tomando apenas 2 o 3 billetes por transacción de depósito. | V14: ATM FULL OPTEVA 720 R/L ENA/ 5 GAV EDC R | W14: SERVICE CALL | AB14: ATM | AC14: BANCO CREDICOOP 812051 | AD14: Centro | AE14: Pavon, Diego Emanuel
A15: {=IFERROR(_xlfn.LET(_xlpm.dias,NETWORKDAYS(MAX(IF((Suspendidos_Total[ID]=Pendientes[[#This Row],[ID]])*(Suspendidos_Total[PEDIDO]<>Pendientes[[#This Row],[Pedido]]), Suspendidos_Total[MARCA FIN])),TODAY(),Feriados[Fecha]),_xlpm.concepto,INDEX(Suspendidos_Total[CONCEPTO LLAMADA],MATCH(MAX(IF((Suspendidos_Total[ID]=Pendientes[[#This Row],[ID]])*(Suspendidos_Total[PEDIDO]<>Pendientes[[#This Row],[Pedido]]),Suspendidos_Total[MARCA FIN])),Suspendidos_Total[MARCA FIN],0)),IF(_xlpm.dias>=20,_xlpm.concepto & CHAR(160)& "-" & CHAR(160)& INT(_xlpm.dias/20)& " " & IF(INT(_xlpm.dias/20)=1,"mes","meses") & IF(MOD(_xlpm.dias,20)>0,CHAR(160)& "," & CHAR(160)& MOD(_xlpm.dias,20)& " " & IF(MOD(_xlpm.dias,20)=1,"día","días"),""), _xlpm.concepto & CHAR(160)& "-" & CHAR(160) & IF(INT(_xlpm.dias/5)>0,INT(_xlpm.dias/5)& " " & IF(INT(_xlpm.dias/5)=1,"semana","semanas") & IF(MOD(_xlpm.dias,5)>0,CHAR(160)& "," & CHAR(160),""),"") & IF(MOD(_xlpm.dias,5)>0,MOD(_xlpm.dias,5)& " " & IF(MOD(_xlpm.dias,5)=1,"día","días"),"")) ),"")} -> SC - 1 mes | B15: 2 | C15: 0.34 | E15: 46084.5 | F15: 26.993611 | G15: 46083.375 | H15: 6,2 h | I15: SEG Asistencia | J15: 101162427 | K15: 0 | L15: - | M15: BANCO CREDICOOP | N15: 812961 | O15: 0 | P15: Garibaldi 360 | Q15: Bahia Blanca | R15: Buenos Aires | S15: Pavon, Diego Emanuel | T15: ATM-DISPENSADOR | U15: Descripción: Fallas aleatorias de dispensador. Revisión de módulo y gavetas. | V15: ATM FULL OPTEVA 720 R/L ENA | W15: SERVICE CALL | AB15: ATM | AC15: BANCO CREDICOOP 812961 | AD15: Centro | AE15: Pavon, Diego Emanuel
A16: {=IFERROR(_xlfn.LET(_xlpm.dias,NETWORKDAYS(MAX(IF((Suspendidos_Total[ID]=Pendientes[[#This Row],[ID]])*(Suspendidos_Total[PEDIDO]<>Pendientes[[#This Row],[Pedido]]), Suspendidos_Total[MARCA FIN])),TODAY(),Feriados[Fecha]),_xlpm.concepto,INDEX(Suspendidos_Total[CONCEPTO LLAMADA],MATCH(MAX(IF((Suspendidos_Total[ID]=Pendientes[[#This Row],[ID]])*(Suspendidos_Total[PEDIDO]<>Pendientes[[#This Row],[Pedido]]),Suspendidos_Total[MARCA FIN])),Suspendidos_Total[MARCA FIN],0)),IF(_xlpm.dias>=20,_xlpm.concepto & CHAR(160)& "-" & CHAR(160)& INT(_xlpm.dias/20)& " " & IF(INT(_xlpm.dias/20)=1,"mes","meses") & IF(MOD(_xlpm.dias,20)>0,CHAR(160)& "," & CHAR(160)& MOD(_xlpm.dias,20)& " " & IF(MOD(_xlpm.dias,20)=1,"día","días"),""), _xlpm.concepto & CHAR(160)& "-" & CHAR(160) & IF(INT(_xlpm.dias/5)>0,INT(_xlpm.dias/5)& " " & IF(INT(_xlpm.dias/5)=1,"semana","semanas") & IF(MOD(_xlpm.dias,5)>0,CHAR(160)& "," & CHAR(160),""),"") & IF(MOD(_xlpm.dias,5)>0,MOD(_xlpm.dias,5)& " " & IF(MOD(_xlpm.dias,5)=1,"día","días"),"")) ),"")} -> SC - 5 meses , 10 días | C16: 0.35 | E16: 46084.498 | F16: 26.961111 | G16: 46083.375 | H16: 6,2 h | I16: SEG Asistencia | J16: 101162426 | K16: 0 | L16: - | M16: BANCO CREDICOOP | N16: 812951 | O16: 1 | P16: Garibaldi 360 | Q16: Bahia Blanca | R16: Buenos Aires | S16: Pavon, Diego Emanuel | T16: ATM-DISPENSADOR | U16: Descripción: Fallas aleatorias de dispensador. Revisión de módulo y gavetas. | V16: ATM FULL OPTEVA 720 R/L 5ºGAV | W16: SERVICE CALL | AB16: ATM | AC16: BANCO CREDICOOP 812951 | AD16: Centro | AE16: Pavon, Diego Emanuel
A17: {=IFERROR(_xlfn.LET(_xlpm.dias,NETWORKDAYS(MAX(IF((Suspendidos_Total[ID]=Pendientes[[#This Row],[ID]])*(Suspendidos_Total[PEDIDO]<>Pendientes[[#This Row],[Pedido]]), Suspendidos_Total[MARCA FIN])),TODAY(),Feriados[Fecha]),_xlpm.concepto,INDEX(Suspendidos_Total[CONCEPTO LLAMADA],MATCH(MAX(IF((Suspendidos_Total[ID]=Pendientes[[#This Row],[ID]])*(Suspendidos_Total[PEDIDO]<>Pendientes[[#This Row],[Pedido]]),Suspendidos_Total[MARCA FIN])),Suspendidos_Total[MARCA FIN],0)),IF(_xlpm.dias>=20,_xlpm.concepto & CHAR(160)& "-" & CHAR(160)& INT(_xlpm.dias/20)& " " & IF(INT(_xlpm.dias/20)=1,"mes","meses") & IF(MOD(_xlpm.dias,20)>0,CHAR(160)& "," & CHAR(160)& MOD(_xlpm.dias,20)& " " & IF(MOD(_xlpm.dias,20)=1,"día","días"),""), _xlpm.concepto & CHAR(160)& "-" & CHAR(160) & IF(INT(_xlpm.dias/5)>0,INT(_xlpm.dias/5)& " " & IF(INT(_xlpm.dias/5)=1,"semana","semanas") & IF(MOD(_xlpm.dias,5)>0,CHAR(160)& "," & CHAR(160),""),"") & IF(MOD(_xlpm.dias,5)>0,MOD(_xlpm.dias,5)& " " & IF(MOD(_xlpm.dias,5)=1,"día","días"),"")) ),"")} -> SC - 7 meses , 12 días | C17: 0.35 | E17: 46084.498 | F17: 26.951944 | G17: 46083.375 | H17: 6,2 h | I17: SEG Asistencia | J17: 101162424 | K17: 0 | L17: - | M17: BANCO CREDICOOP | N17: 812931 | O17: 1 | P17: Garibaldi 360 | Q17: Bahia Blanca | R17: Buenos Aires | S17: Pavon, Diego Emanuel | T17: ATM-DISPENSADOR | U17: Descripción: Fallas aleatorias de dispensador. Revisión de módulo y gavetas. | V17: ATM FULL OPTEVA 720 R/L | W17: SERVICE CALL | AB17: ATM | AC17: BANCO CREDICOOP 812931 | AD17: Centro | AE17: Pavon, Diego Emanuel
A18: {=IFERROR(_xlfn.LET(_xlpm.dias,NETWORKDAYS(MAX(IF((Suspendidos_Total[ID]=Pendientes[[#This Row],[ID]])*(Suspendidos_Total[PEDIDO]<>Pendientes[[#This Row],[Pedido]]), Suspendidos_Total[MARCA FIN])),TODAY(),Feriados[Fecha]),_xlpm.concepto,INDEX(Suspendidos_Total[CONCEPTO LLAMADA],MATCH(MAX(IF((Suspendidos_Total[ID]=Pendientes[[#This Row],[ID]])*(Suspendidos_Total[PEDIDO]<>Pendientes[[#This Row],[Pedido]]),Suspendidos_Total[MARCA FIN])),Suspendidos_Total[MARCA FIN],0)),IF(_xlpm.dias>=20,_xlpm.concepto & CHAR(160)& "-" & CHAR(160)& INT(_xlpm.dias/20)& " " & IF(INT(_xlpm.dias/20)=1,"mes","meses") & IF(MOD(_xlpm.dias,20)>0,CHAR(160)& "," & CHAR(160)& MOD(_xlpm.dias,20)& " " & IF(MOD(_xlpm.dias,20)=1,"día","días"),""), _xlpm.concepto & CHAR(160)& "-" & CHAR(160) & IF(INT(_xlpm.dias/5)>0,INT(_xlpm.dias/5)& " " & IF(INT(_xlpm.dias/5)=1,"semana","semanas") & IF(MOD(_xlpm.dias,5)>0,CHAR(160)& "," & CHAR(160),""),"") & IF(MOD(_xlpm.dias,5)>0,MOD(_xlpm.dias,5)& " " & IF(MOD(_xlpm.dias,5)=1,"día","días"),"")) ),"")} -> MTM - 5 meses , 1 día | C18: 0 | E18: 46085.424 | F18: 45.676111 | G18: 46083.521 | H18: 2,7 h | I18: Asistencia Demorada | J18: 101163027 | K18: 0 | L18: - | M18: BANCO CREDICOOP | N18: 823031 | O18: 1 | P18: Vicente Lopez 3045 | Q18: Olavarria | R18: Buenos Aires | S18: Martos, Jose Angel | T18: ATM-DEPÓSITO | U18: Descripción: hace la apertura del buzón pero no toma el efectivo y hace ruido en los engranajes | V18: ATM FULL OPTEVA 720 R/L ENA/ 5 GAV | W18: SERVICE CALL | AB18: ATM | AC18: BANCO CREDICOOP 823031 | AD18: Oeste | AE18: Martos, Jose Angel
A19: {=IFERROR(_xlfn.LET(_xlpm.dias,NETWORKDAYS(MAX(IF((Suspendidos_Total[ID]=Pendientes[[#This Row],[ID]])*(Suspendidos_Total[PEDIDO]<>Pendientes[[#This Row],[Pedido]]), Suspendidos_Total[MARCA FIN])),TODAY(),Feriados[Fecha]),_xlpm.concepto,INDEX(Suspendidos_Total[CONCEPTO LLAMADA],MATCH(MAX(IF((Suspendidos_Total[ID]=Pendientes[[#This Row],[ID]])*(Suspendidos_Total[PEDIDO]<>Pendientes[[#This Row],[Pedido]]),Suspendidos_Total[MARCA FIN])),Suspendidos_Total[MARCA FIN],0)),IF(_xlpm.dias>=20,_xlpm.concepto & CHAR(160)& "-" & CHAR(160)& INT(_xlpm.dias/20)& " " & IF(INT(_xlpm.dias/20)=1,"mes","meses") & IF(MOD(_xlpm.dias,20)>0,CHAR(160)& "," & CHAR(160)& MOD(_xlpm.dias,20)& " " & IF(MOD(_xlpm.dias,20)=1,"día","días"),""), _xlpm.concepto & CHAR(160)& "-" & CHAR(160) & IF(INT(_xlpm.dias/5)>0,INT(_xlpm.dias/5)& " " & IF(INT(_xlpm.dias/5)=1,"semana","semanas") & IF(MOD(_xlpm.dias,5)>0,CHAR(160)& "," & CHAR(160),""),"") & IF(MOD(_xlpm.dias,5)>0,MOD(_xlpm.dias,5)& " " & IF(MOD(_xlpm.dias,5)=1,"día","días"),"")) ),"")} -> MTM - 1 semana , 1 día | B19: 5 | C19: 0.95 | E19: 46083.482 | F19: -1.4305556 | G19: 46083.542 | H19: 2,2 h | I19: Asistencia Demorada | J19: 101162157 | K19: 200182737 | L19: Repuesto Enviado | M19: BANCO CREDICOOP | N19: 814621 | O19: 0 | P19: 9 de Julio 270 | Q19: Trelew | R19: Chubut | S19: Godoy, Diego | T19: ATM-DISPENSADOR | U19: REITERA FALLA EN DISPENSADOR | V19: DT-7000H22V | W19: SERVICE CALL | X19: Dispensador | Y19: [27/02/2026] Se suspende por pedido de repuesto. Por recomendación de sector Especialista se solicita Shutter. | Z19: Repuesto | AA19: Se realizaron pruebas en dispensador con soporte de Especialista Walter Formaggio. Se reviso sensor y resorte de presenter. se realizaron pruebas de apertura y cierre en Shutter. Pruebas OK. se extrajeron LOGS de errores. Se realizaron pruebas de extracción ($14.0000, $25.000 y $40.000) con funcionario bancario. Pruebas OK. el equipo quedó operativo y en servicio. | AB19: ATM | AC19: BANCO CREDICOOP 814621 | AD19: Sur | AE19: Godoy, Diego
A20: {=IFERROR(_xlfn.LET(_xlpm.dias,NETWORKDAYS(MAX(IF((Suspendidos_Total[ID]=Pendientes[[#This Row],[ID]])*(Suspendidos_Total[PEDIDO]<>Pendientes[[#This Row],[Pedido]]), Suspendidos_Total[MARCA FIN])),TODAY(),Feriados[Fecha]),_xlpm.concepto,INDEX(Suspendidos_Total[CONCEPTO LLAMADA],MATCH(MAX(IF((Suspendidos_Total[ID]=Pendientes[[#This Row],[ID]])*(Suspendidos_Total[PEDIDO]<>Pendientes[[#This Row],[Pedido]]),Suspendidos_Total[MARCA FIN])),Suspendidos_Total[MARCA FIN],0)),IF(_xlpm.dias>=20,_xlpm.concepto & CHAR(160)& "-" & CHAR(160)& INT(_xlpm.dias/20)& " " & IF(INT(_xlpm.dias/20)=1,"mes","meses") & IF(MOD(_xlpm.dias,20)>0,CHAR(160)& "," & CHAR(160)& MOD(_xlpm.dias,20)& " " & IF(MOD(_xlpm.dias,20)=1,"día","días"),""), _xlpm.concepto & CHAR(160)& "-" & CHAR(160) & IF(INT(_xlpm.dias/5)>0,INT(_xlpm.dias/5)& " " & IF(INT(_xlpm.dias/5)=1,"semana","semanas") & IF(MOD(_xlpm.dias,5)>0,CHAR(160)& "," & CHAR(160),""),"") & IF(MOD(_xlpm.dias,5)>0,MOD(_xlpm.dias,5)& " " & IF(MOD(_xlpm.dias,5)=1,"día","días"),"")) ),"")} -> SC - 2 semanas , 4 días | B20: 2 | C20: 1 | E20: 46080.621 | F20: -67.088889 | G20: 46083.417 | H20: 5,2 h | I20: SEG Asistencia | J20: 101162329 | K20: 200182755 | L20: Repuesto Enviado | M20: BANCO NACION | N20: 5060 | O20: 0 | P20: 9 de Julio 127 | Q20: Puerto Madryn | R20: Chubut | S20: Godoy, Diego | T20: ATM-MONITOR DE CLIENTE | U20: Pantalla de clientes y teclado no funcionan_x000D_ SLA Vence 27/02 14:52_x000D_ Prosegur 08 a 16 | V20: ATM OPTEVA 522 | W20: SERVICE CALL | X20: Monitor cliente | Y20: [27/02/2026] Tecla de función en monitor en mal estado y trabada. Se realizan pruebas. Falla persiste. Se suspende por repuesto | Z20: Repuesto | AB20: ATM | AC20: BANCO NACION 5060 | AD20: Sur | AE20: Godoy, Diego
A21: {=IFERROR(_xlfn.LET(_xlpm.dias,NETWORKDAYS(MAX(IF((Suspendidos_Total[ID]=Pendientes[[#This Row],[ID]])*(Suspendidos_Total[PEDIDO]<>Pendientes[[#This Row],[Pedido]]), Suspendidos_Total[MARCA FIN])),TODAY(),Feriados[Fecha]),_xlpm.concepto,INDEX(Suspendidos_Total[CONCEPTO LLAMADA],MATCH(MAX(IF((Suspendidos_Total[ID]=Pendientes[[#This Row],[ID]])*(Suspendidos_Total[PEDIDO]<>Pendientes[[#This Row],[Pedido]]),Suspendidos_Total[MARCA FIN])),Suspendidos_Total[MARCA FIN],0)),IF(_xlpm.dias>=20,_xlpm.concepto & CHAR(160)& "-" & CHAR(160)& INT(_xlpm.dias/20)& " " & IF(INT(_xlpm.dias/20)=1,"mes","meses") & IF(MOD(_xlpm.dias,20)>0,CHAR(160)& "," & CHAR(160)& MOD(_xlpm.dias,20)& " " & IF(MOD(_xlpm.dias,20)=1,"día","días"),""), _xlpm.concepto & CHAR(160)& "-" & CHAR(160) & IF(INT(_xlpm.dias/5)>0,INT(_xlpm.dias/5)& " " & IF(INT(_xlpm.dias/5)=1,"semana","semanas") & IF(MOD(_xlpm.dias,5)>0,CHAR(160)& "," & CHAR(160),""),"") & IF(MOD(_xlpm.dias,5)>0,MOD(_xlpm.dias,5)& " " & IF(MOD(_xlpm.dias,5)=1,"día","días"),"")) ),"")} -> SC - 1 mes , 18 días | C21: 0.51 | E21: 46083.705 | F21: 4.9227778 | G21: 46083.5 | H21: 3,2 h | I21: Asistencia Demorada | J21: 101162889 | K21: 0 | L21: - | M21: CENCOSUD S.A | N21: 008681061970 | O21: 0 | P21: Manuel Belgrano 372 | Q21: Puerto Madryn | R21: Chubut | S21: Godoy, Diego | T21: SMC-CPU | U21: cte reclama que la PC no inicia, aparece error en disco. se solicita asistencia | V21: GLORY P500 | W21: SERVICE CALL | Y21: cte reclama que la PC no inicia, aparece error en disco. se solicita asistencia_x000D_ Horarios: de 8.30 a 21 hs_x000D_ Contacto:2804205750 Carla | AB21: Cash Today | AC21: CENCOSUD S.A 008681061970 | AD21: Sur | AE21: Godoy, Diego
A22: {=IFERROR(_xlfn.LET(_xlpm.dias,NETWORKDAYS(MAX(IF((Suspendidos_Total[ID]=Pendientes[[#This Row],[ID]])*(Suspendidos_Total[PEDIDO]<>Pendientes[[#This Row],[Pedido]]), Suspendidos_Total[MARCA FIN])),TODAY(),Feriados[Fecha]),_xlpm.concepto,INDEX(Suspendidos_Total[CONCEPTO LLAMADA],MATCH(MAX(IF((Suspendidos_Total[ID]=Pendientes[[#This Row],[ID]])*(Suspendidos_Total[PEDIDO]<>Pendientes[[#This Row],[Pedido]]),Suspendidos_Total[MARCA FIN])),Suspendidos_Total[MARCA FIN],0)),IF(_xlpm.dias>=20,_xlpm.concepto & CHAR(160)& "-" & CHAR(160)& INT(_xlpm.dias/20)& " " & IF(INT(_xlpm.dias/20)=1,"mes","meses") & IF(MOD(_xlpm.dias,20)>0,CHAR(160)& "," & CHAR(160)& MOD(_xlpm.dias,20)& " " & IF(MOD(_xlpm.dias,20)=1,"día","días"),""), _xlpm.concepto & CHAR(160)& "-" & CHAR(160) & IF(INT(_xlpm.dias/5)>0,INT(_xlpm.dias/5)& " " & IF(INT(_xlpm.dias/5)=1,"semana","semanas") & IF(MOD(_xlpm.dias,5)>0,CHAR(160)& "," & CHAR(160),""),"") & IF(MOD(_xlpm.dias,5)>0,MOD(_xlpm.dias,5)& " " & IF(MOD(_xlpm.dias,5)=1,"día","días"),"")) ),"")} -> MTM - 4 meses , 3 días | C22: 0.13 | E22: 46084.456 | F22: 25.006944 | G22: 46083.414 | H22: 5,3 h | I22: SEG Registrado | J22: 101162985 | K22: 0 | L22: - | M22: BANCO NACION | N22: 5031 | O22: 0 | P22: Av. San Martin 2598 | Q22: El Bolson | R22: Rio Negro | S22: SIN ASIGNAR | T22: ATM-DISPENSADOR | U22: Modulo 1 con error. No ingresa carro con gavetas, no traba y no entra en servicio. Lector de huella caido y eso imposibilita que el carro con gavetas trabe y pueda dispensar dinero_x000D_ _x000D_ SLA Vence 03/03 10:50hs_x000D_ TELLEX 8 a 16hs | V22: ATM OPTEVA 522 | W22: SERVICE CALL | AB22: ATM | AC22: BANCO NACION 5031 | AD22: Suroeste | AE22: Ibañez, Pablo Fernando
A23: {=IFERROR(_xlfn.LET(_xlpm.dias,NETWORKDAYS(MAX(IF((Suspendidos_Total[ID]=Pendientes[[#This Row],[ID]])*(Suspendidos_Total[PEDIDO]<>Pendientes[[#This Row],[Pedido]]), Suspendidos_Total[MARCA FIN])),TODAY(),Feriados[Fecha]),_xlpm.concepto,INDEX(Suspendidos_Total[CONCEPTO LLAMADA],MATCH(MAX(IF((Suspendidos_Total[ID]=Pendientes[[#This Row],[ID]])*(Suspendidos_Total[PEDIDO]<>Pendientes[[#This Row],[Pedido]]),Suspendidos_Total[MARCA FIN])),Suspendidos_Total[MARCA FIN],0)),IF(_xlpm.dias>=20,_xlpm.concepto & CHAR(160)& "-" & CHAR(160)& INT(_xlpm.dias/20)& " " & IF(INT(_xlpm.dias/20)=1,"mes","meses") & IF(MOD(_xlpm.dias,20)>0,CHAR(160)& "," & CHAR(160)& MOD(_xlpm.dias,20)& " " & IF(MOD(_xlpm.dias,20)=1,"día","días"),""), _xlpm.concepto & CHAR(160)& "-" & CHAR(160) & IF(INT(_xlpm.dias/5)>0,INT(_xlpm.dias/5)& " " & IF(INT(_xlpm.dias/5)=1,"semana","semanas") & IF(MOD(_xlpm.dias,5)>0,CHAR(160)& "," & CHAR(160),""),"") & IF(MOD(_xlpm.dias,5)>0,MOD(_xlpm.dias,5)& " " & IF(MOD(_xlpm.dias,5)=1,"día","días"),"")) ),"")} -> SC - 4 días | C23: 0.14 | E23: 46083.893 | F23: 11.92 | G23: 46083.396 | H23: 5,7 h | I23: SEG Asistencia | J23: 101162732 | K23: 0 | L23: - | M23: CARREFOUR | N23: 006624021970 | O23: 0 | P23: Av. Olascoaga 350 | Q23: Neuquen | R23: Neuquen | S23: Ibañez, Pablo Fernando | T23: SMC-ERROR RECONTADORA | U23: El cliente se comunica por la misma falla anterior, no lee billetes de mil de San Martin. | V23: GLORY P500 | W23: SERVICE CALL | Y23: a confirmar ope ///Se pide asistencia tecnica para chequear el tema de lectura de los billetes de mil de San Martin, favor de hacer varias pruebas ya que el error persiste. Horario de 8 a 22. | Z23: Cliente | AB23: Cash Today | AC23: CARREFOUR 006624021970 | AD23: Suroeste | AE23: Ibañez, Pablo Fernando
A24: {=IFERROR(_xlfn.LET(_xlpm.dias,NETWORKDAYS(MAX(IF((Suspendidos_Total[ID]=Pendientes[[#This Row],[ID]])*(Suspendidos_Total[PEDIDO]<>Pendientes[[#This Row],[Pedido]]), Suspendidos_Total[MARCA FIN])),TODAY(),Feriados[Fecha]),_xlpm.concepto,INDEX(Suspendidos_Total[CONCEPTO LLAMADA],MATCH(MAX(IF((Suspendidos_Total[ID]=Pendientes[[#This Row],[ID]])*(Suspendidos_Total[PEDIDO]<>Pendientes[[#This Row],[Pedido]]),Suspendidos_Total[MARCA FIN])),Suspendidos_Total[MARCA FIN],0)),IF(_xlpm.dias>=20,_xlpm.concepto & CHAR(160)& "-" & CHAR(160)& INT(_xlpm.dias/20)& " " & IF(INT(_xlpm.dias/20)=1,"mes","meses") & IF(MOD(_xlpm.dias,20)>0,CHAR(160)& "," & CHAR(160)& MOD(_xlpm.dias,20)& " " & IF(MOD(_xlpm.dias,20)=1,"día","días"),""), _xlpm.concepto & CHAR(160)& "-" & CHAR(160) & IF(INT(_xlpm.dias/5)>0,INT(_xlpm.dias/5)& " " & IF(INT(_xlpm.dias/5)=1,"semana","semanas") & IF(MOD(_xlpm.dias,5)>0,CHAR(160)& "," & CHAR(160),""),"") & IF(MOD(_xlpm.dias,5)>0,MOD(_xlpm.dias,5)& " " & IF(MOD(_xlpm.dias,5)=1,"día","días"),"")) ),"")} -> AIEC - 3 meses , 12 días | C24: 1 | E24: 46080.875 | F24: -73.366667 | G24: 46083.932 | I24: SEG Espera Llegada | J24: 101162319 | K24: 0 | L24: - | M24: SAIEP | N24: 004677006870 | O24: 0 | P24: Av. Ángel Gallardo 801 | Q24: San Carlos De Bariloche | R24: Rio Negro | S24: SIN ASIGNAR | T24: SMC-FALLA EN TRANSPORTE | U24: en ocasiones queda algún billete que no es tomado en el deposito de un cajero pero tampoco indica error ni informa billete trabado y luego es considerado en el deposito siguiente ( estimamos que queda en algún lado intermedio entre donde se puede observar por nosotros y antes de pasar por el sensor y bolsa de deposito) | V24: CIMA SDM500 | W24: SERVICE CALL | Y24: en ocasiones queda algún billete que no es tomado en el deposito de un cajero pero tampoco indica error ni informa billete trabado y luego es considerado en el deposito siguiente ( estimamos que queda en algún lado intermedio entre donde se puede observar por nosotros y antes de pasar por el sensor y bolsa de deposito) | AB24: Cash Today | AC24: SAIEP 004677006870 | AD24: Suroeste | AE24: Ibañez, Pablo Fernando
C25: Total | I25: =SUBTOTAL(103,Pendientes[Estado Asistencia]) -> 21 | AB25: =SUBTOTAL(103,Pendientes[Red]) -> 21

Sheet Zonas
B1: Técnico | C1: B | D1: c
B2: Aldayturriaga, Martin | C2: 3 | D2: 1
B3: Allende, Martin Leandro | C3: 4 | D3: 1 | E3: Mail a Rossi reclamando
B4: Buratti, Fabian | C4: 1
B5: Castaño, Matias | C5: 20 | D5: 1
B6: Christiansen, Patricio | C6: 4
B7: Corti Victor | C7: 3
B8: Foschi, Alejandro | C8: 14 | D8: 1
B9: Garcia, Alejandro Javier | C9: 2 | D9: 1
B10: Godoy, Diego | C10: 11 | D10: 1
B11: Gonzalez Cabrera, Antonio | C11: 5 | D11: 1
B12: Hernandez, Marcos Alberto | C12: 2 | D12: 1
B13: Lemos, Daniel | C13: 5
B14: Liscio, Leonardo Gastón | C14: 6 | D14: 1
B15: Martos, Jose Angel | C15: 2 | D15: 1
B16: Miranda, Matias | C16: 9
B17: Osorio, Gabriel | C17: 4
B18: Vicente, Francisco Ariel | C18: 3 | D18: 1
A21: Zona Local | B21: TECNICO | C21: Zona | E21: Zona Local | F21: TECNICO | G21: Zona
A22: Atlántica | B22: Buratti, Fabian | C22: IN MDP 2 | E22: Atlántica | F22: Buratti, Fabian | G22: IN MDP 2
A23: Atlántica | B23: Castaño, Matias | C23: IN MDP3 | E23: Atlántica | F23: Castaño, Matias | G23: IN MDP3 | K23: García | L23: 7
A24: Atlántica | B24: Montiel, Juan Fernando | C24: IN COS | E24: Atlántica | F24: Montiel, Juan Fernando | G24: IN COS | K24: Mateo | L24: 4
A25: Atlántica | B25: Chiriello, Pablo Javier | C25: IN MDP 1 | E25: Atlántica | F25: Chiriello, Pablo Javier | G25: IN MDP 1 | K25: Godoy | L25: 7
A26: Centro | B26: Christiansen, Patricio | C26: IN BB1 | E26: Centro | F26: Christiansen, Patricio | G26: IN BB1 | I26: {=_xlfn.UNIQUE(DetalleZonasTécnicas[Zona Local])} -> Atlántica
A27: Centro | B27: Pavon, Diego Emanuel | C27: IN BB2 | E27: Centro | F27: Pavon, Diego Emanuel | G27: IN BB2 | I27: Centro
A28: Centro | B28: Rodriguez, Mateo Joaquin | C28: IN CSZ | E28: Centro | F28: Rodriguez, Mateo Joaquin | G28: IN CSZ | I28: Contratistas
A29: Centro | B29: Vicente, Francisco Ariel | C29: IN VIE | E29: Centro | F29: Vicente, Francisco Ariel | G29: IN VIE | I29: La Pampa
A30: Contratistas | B30: Barrera, Fernando Andrés | C30: IN RIT | E30: Contratistas | F30: Barrera, Fernando Andrés | G30: IN RIT | I30: Oeste
A31: Contratistas | B31: Corti Victor | C31: IN RGR | E31: Contratistas | F31: Corti Victor | G31: IN RGR | I31: Sur
A32: Contratistas | B32: Foschi, Alejandro | C32: IN RGA | E32: Contratistas | F32: Foschi, Alejandro | G32: IN RGA | I32: Suroeste
A33: Contratistas | B33: Lemos, Daniel | C33: IN USH | E33: Contratistas | F33: Lemos, Daniel | G33: IN USH
A34: La Pampa | B34: Allende, Martin Leandro | C34: IN SRO1 | E34: La Pampa | F34: Allende, Martin Leandro | G34: IN SRO1
A35: La Pampa | B35: Heinz, Carlos | C35: IN PCO1 | E35: La Pampa | F35: Heinz, Carlos | G35: IN PCO1
A36: La Pampa | B36: Hernandez, Marcos Alberto | C36: IN PCO | E36: La Pampa | F36: Hernandez, Marcos Alberto | G36: IN PCO
A37: La Pampa | B37: Sanchez, Claudio | C37: IN SRO | E37: La Pampa | F37: Sanchez, Claudio | G37: IN SRO
A38: Oeste | B38: Aldayturriaga, Martin | C38: IN TDL | E38: Oeste | F38: Aldayturriaga, Martin | G38: IN TDL
A39: Oeste | B39: Garcia, Alejandro Javier | C39: IN TRQ | E39: Oeste | F39: Garcia, Alejandro Javier | G39: IN TRQ
A40: Oeste | B40: Martos, Jose Angel | C40: IN OLA | E40: Oeste | F40: Martos, Jose Angel | G40: IN OLA
A41: Sur | B41: Godoy, Diego | C41: IN TRE | E41: Sur | F41: Godoy, Diego | G41: IN TRE
A42: Sur | B42: Gonzalez Cabrera, Antonio | C42: IN COM1 | E42: Sur | F42: Gonzalez Cabrera, Antonio | G42: IN COM1
A43: Sur | B43: Osorio, Gabriel | C43: IN COM | E43: Sur | F43: Osorio, Gabriel | G43: IN COM
A44: Sur | B44: Diez, Jonatan | C44: IN TRE1 | E44: Sur | F44: Diez, Jonatan | G44: IN TRE1
... A47: Suroeste | B47: Lazzaro, Leonardo | C47: IN NQN | E47: Suroeste | F47: Lazzaro, Leonardo | G47: IN NQN

Sheet Control Inicio
A1: Técnico | B1: Zona Local | C1: TECNICO | D1: Estado | E1: Cliente | F1: Luno | G1: Direccion | H1: Localidad | I1: Hora Coordinada | J1: Fecha Vto | L1: =NOW() -> 46086.392
A2: =_xlfn.XLOOKUP(Control_Inicio[[#This Row],[TECNICO]],Tabla8[Nombre Flow], Tabla8[Foto],"",0) -> #VALUE! | B2: Atlántica | C2: Buratti, Fabian | D2: SEG Asistencia | E2: BAPRO | F2: 11369 | G2: Av. Constitucion 5850 | H2: Mar Del Plata | I2: 0.41666667 | J2: Hasta 02/03/2026 13:00:00
A3: =_xlfn.XLOOKUP(Control_Inicio[[#This Row],[TECNICO]],Tabla8[Nombre Flow], Tabla8[Foto],"",0) -> #VALUE! | B3: Atlántica | C3: Castaño, Matias | D3: SEG Registrado | E3: ACA | F3: 002359016370 | G3: Diagonal F De La Palza 1733 | H3: Miramar | I3: 0.47916667 | J3: Hasta 02/03/2026 18:15:52
A4: =_xlfn.XLOOKUP(Control_Inicio[[#This Row],[TECNICO]],Tabla8[Nombre Flow], Tabla8[Foto],"",0) -> #VALUE! | B4: Atlántica | C4: Chiriello, Pablo Javier | D4: SEG Asistencia | E4: BAPRO | F4: 8728 | G4: Av. J. Peralta Ramos 1890 | H4: Mar Del Plata | I4: 0.33333333 | J4: Hasta 02/03/2026 13:00:00
A5: =_xlfn.XLOOKUP(Control_Inicio[[#This Row],[TECNICO]],Tabla8[Nombre Flow], Tabla8[Foto],"",0) -> #VALUE! | B5: Atlántica | C5: Chiriello, Pablo Javier | D5: SEG Control Final | E5: BAPRO | F5: 11347 | G5: Av. Mario Bravo 3650 | H5: Mar Del Plata | I5: 0.4375 | J5: Hasta 27/02/2026 11:22:48
A6: =_xlfn.XLOOKUP(Control_Inicio[[#This Row],[TECNICO]],Tabla8[Nombre Flow], Tabla8[Foto],"",0) -> #VALUE! | B6: Atlántica | C6: Chiriello, Pablo Javier | D6: SEG Asistencia | E6: BAPRO | F6: 11347 | G6: Av. Mario Bravo 3650 | H6: Mar Del Plata | I6: 0.45833333 | J6: Hasta 05/01/2026 16:48:41
A7: =_xlfn.XLOOKUP(Control_Inicio[[#This Row],[TECNICO]],Tabla8[Nombre Flow], Tabla8[Foto],"",0) -> #VALUE! | B7: Atlántica | C7: Chiriello, Pablo Javier | D7: SEG Registrado | E7: BAPRO | F7: 6571 | G7: Calle 64 3000 | H7: Necochea | I7: 0.58333333 | J7: Hasta 03/03/2026 10:05:08
A8: =_xlfn.XLOOKUP(Control_Inicio[[#This Row],[TECNICO]],Tabla8[Nombre Flow], Tabla8[Foto],"",0) -> #VALUE! | B8: Atlántica | C8: Montiel, Juan Fernando | D8: Sin pedidos asignados
A9: =_xlfn.XLOOKUP(Control_Inicio[[#This Row],[TECNICO]],Tabla8[Nombre Flow], Tabla8[Foto],"",0) -> #VALUE! | B9: Centro | C9: Pavon, Diego Emanuel | D9: SEG Asistencia | E9: BANCO CREDICOOP | F9: 812961 | G9: Garibaldi 360 | H9: Bahia Blanca | I9: 0.375 | J9: Hasta 03/03/2026 11:59:37
A10: =_xlfn.XLOOKUP(Control_Inicio[[#This Row],[TECNICO]],Tabla8[Nombre Flow], Tabla8[Foto],"",0) -> #VALUE! | B10: Centro | C10: Pavon, Diego Emanuel | D10: SEG Asistencia | E10: BANCO CREDICOOP | F10: 812931 | G10: Garibaldi 360 | H10: Bahia Blanca | I10: 0.375 | J10: Hasta 03/03/2026 11:57:07
A11: =_xlfn.XLOOKUP(Control_Inicio[[#This Row],[TECNICO]],Tabla8[Nombre Flow], Tabla8[Foto],"",0) -> #VALUE! | B11: Centro | C11: Pavon, Diego Emanuel | D11: SEG Asistencia | E11: BANCO CREDICOOP | F11: 812951 | G11: Garibaldi 360 | H11: Bahia Blanca | I11: 0.375 | J11: Hasta 07/01/2026 14:00:00
A12: =_xlfn.XLOOKUP(Control_Inicio[[#This Row],[TECNICO]],Tabla8[Nombre Flow], Tabla8[Foto],"",0) -> #VALUE! | B12: Centro | C12: Pavon, Diego Emanuel | D12: SEG Asistencia | E12: BANCO CREDICOOP | F12: 812931 | G12: Garibaldi 360 | H12: Bahia Blanca | I12: 0.375 | J12: Hasta 07/01/2026 14:00:00
A13: =_xlfn.XLOOKUP(Control_Inicio[[#This Row],[TECNICO]],Tabla8[Nombre Flow], Tabla8[Foto],"",0) -> #VALUE! | B13: Centro | C13: Pavon, Diego Emanuel | D13: SEG Asistencia | E13: BANCO CREDICOOP | F13: 812951 | G13: Garibaldi 360 | H13: Bahia Blanca | I13: 0.375 | J13: Hasta 03/03/2026 11:57:40
A14: =_xlfn.XLOOKUP(Control_Inicio[[#This Row],[TECNICO]],Tabla8[Nombre Flow], Tabla8[Foto],"",0) -> #VALUE! | B14: Centro | C14: Pavon, Diego Emanuel | D14: SEG Registrado | E14: BANCO CREDICOOP | F14: 812051 | G14: Sarmiento 2200 | H14: Bahia Blanca | I14: 0.54166667 | J14: Hasta 03/03/2026 14:00:00
A15: =_xlfn.XLOOKUP(Control_Inicio[[#This Row],[TECNICO]],Tabla8[Nombre Flow], Tabla8[Foto],"",0) -> #VALUE! | B15: Centro | C15: Rodriguez, Mateo Joaquin | D15: Sin pedidos asignados
A16: =_xlfn.XLOOKUP(Control_Inicio[[#This Row],[TECNICO]],Tabla8[Nombre Flow], Tabla8[Foto],"",0) -> #VALUE! | B16: Centro | C16: Vicente, Francisco Ariel | D16: Sin pedidos asignados
A17: =_xlfn.XLOOKUP(Control_Inicio[[#This Row],[TECNICO]],Tabla8[Nombre Flow], Tabla8[Foto],"",0) -> #VALUE! | B17: Contratistas | C17: Barrera, Fernando Andrés | D17: Sin pedidos asignados
A18: =_xlfn.XLOOKUP(Control_Inicio[[#This Row],[TECNICO]],Tabla8[Nombre Flow], Tabla8[Foto],"",0) -> #VALUE! | B18: Contratistas | C18: Corti Victor | D18: Sin pedidos asignados
A19: =_xlfn.XLOOKUP(Control_Inicio[[#This Row],[TECNICO]],Tabla8[Nombre Flow], Tabla8[Foto],"",0) -> #VALUE! | B19: Contratistas | C19: Foschi, Alejandro | D19: Sin pedidos asignados
A20: =_xlfn.XLOOKUP(Control_Inicio[[#This Row],[TECNICO]],Tabla8[Nombre Flow], Tabla8[Foto],"",0) -> #VALUE! | B20: La Pampa | C20: Allende, Martin Leandro | D20: SEG Control Final | E20: BANCO NACION | F20: 4136 | G20: Avda. General San Martín Oeste 1 | H20: Santa Rosa | I20: 0.33333333 | J20: Hasta 05/01/2026 14:00:00
A21: =_xlfn.XLOOKUP(Control_Inicio[[#This Row],[TECNICO]],Tabla8[Nombre Flow], Tabla8[Foto],"",0) -> #VALUE! | B21: La Pampa | C21: Hernandez, Marcos Alberto | D21: SEG Asistencia | E21: CLIENTE INTERNO | F21: SRO | G21: Fiorucci 45 | H21: Santa Rosa | I21: 0.38888889 | J21: Hasta 02/03/2026 09:18:00
A22: =_xlfn.XLOOKUP(Control_Inicio[[#This Row],[TECNICO]],Tabla8[Nombre Flow], Tabla8[Foto],"",0) -> #VALUE! | B22: Oeste | C22: Aldayturriaga, Martin | D22: SEG Registrado | E22: BAPRO | F22: 11488 | G22: Avellaneda 199 | H22: General Madariaga | I22: 0.58333333 | J22: SLA 02/03/2026 17:55:19
A23: =_xlfn.XLOOKUP(Control_Inicio[[#This Row],[TECNICO]],Tabla8[Nombre Flow], Tabla8[Foto],"",0) -> #VALUE! | B23: Oeste | C23: Aldayturriaga, Martin | D23: SEG Registrado | E23: ARCOS DORADOS | F23: 005091015170 | G23: Av. Bunge 682 | H23: Pinamar | I23: 0.58333333 | J23: Hasta 25/02/2026 18:01:12
A24: =_xlfn.XLOOKUP(Control_Inicio[[#This Row],[TECNICO]],Tabla8[Nombre Flow], Tabla8[Foto],"",0) -> #VALUE! | B24: Oeste | C24: Garcia, Alejandro Javier | D24: SEG Asistencia | E24: BAPRO | F24: 11214 | G24: San Martin 1 | H24: Pellegrini | I24: 0.4375 | J24: Hasta 02/03/2026 13:32:32
A25: =_xlfn.XLOOKUP(Control_Inicio[[#This Row],[TECNICO]],Tabla8[Nombre Flow], Tabla8[Foto],"",0) -> #VALUE! | B25: Oeste | C25: Martos, Jose Angel | D25: SEG Asistencia | E25: BAPRO | F25: 11203 | G25: Los Ligustros S/N | H25: Olavarria | I25: 0.375 | J25: Hasta 06/01/2026 17:00:00
A26: =_xlfn.XLOOKUP(Control_Inicio[[#This Row],[TECNICO]],Tabla8[Nombre Flow], Tabla8[Foto],"",0) -> #VALUE! | B26: Oeste | C26: Martos, Jose Angel | D26: SEG Asistencia | E26: BAPRO | F26: 11202 | G26: Los Ligustros S/N | H26: Olavarria | I26: 0.375 | J26: Hasta 06/01/2026 17:00:00
A27: =_xlfn.XLOOKUP(Control_Inicio[[#This Row],[TECNICO]],Tabla8[Nombre Flow], Tabla8[Foto],"",0) -> #VALUE! | B27: Oeste | C27: Martos, Jose Angel | D27: SEG Registrado | E27: BANCO CREDICOOP | F27: 823031 | G27: Vicente Lopez 3045 | H27: Olavarria | I27: 0.52083333 | J27: Hasta 07/01/2026 14:00:00
A28: =_xlfn.XLOOKUP(Control_Inicio[[#This Row],[TECNICO]],Tabla8[Nombre Flow], Tabla8[Foto],"",0) -> #VALUE! | B28: Oeste | C28: Martos, Jose Angel | D28: SEG Registrado | E28: BANCO CREDICOOP | F28: 823031 | G28: Vicente Lopez 3045 | H28: Olavarria | I28: 0.52083333 | J28: Hasta 04/03/2026 10:10:34
A29: =_xlfn.XLOOKUP(Control_Inicio[[#This Row],[TECNICO]],Tabla8[Nombre Flow], Tabla8[Foto],"",0) -> #VALUE! | B29: Sur | C29: Godoy, Diego | D29: SEG Asistencia | E29: BANCO NACION | F29: 5060 | G29: 9 de Julio 127 | H29: Puerto Madryn | I29: 0.41666667 | J29: Hasta 27/02/2026 14:54:40
A30: =_xlfn.XLOOKUP(Control_Inicio[[#This Row],[TECNICO]],Tabla8[Nombre Flow], Tabla8[Foto],"",0) -> #VALUE! | B30: Sur | C30: Godoy, Diego | D30: SEG Registrado | E30: CENCOSUD S.A | F30: 008681061970 | G30: Manuel Belgrano 372 | H30: Puerto Madryn | I30: 0.5 | J30: Hasta 02/03/2026 16:55:22
A31: =_xlfn.XLOOKUP(Control_Inicio[[#This Row],[TECNICO]],Tabla8[Nombre Flow], Tabla8[Foto],"",0) -> #VALUE! | B31: Sur | C31: Godoy, Diego | D31: SEG Espera Llegada | E31: BANCO CREDICOOP | F31: 814621 | G31: 9 de Julio 270 | H31: Trelew | I31: 0.54166667 | J31: Hasta 02/03/2026 11:34:10
... A34: =_xlfn.XLOOKUP(Control_Inicio[[#This Row],[TECNICO]],Tabla8[Nombre Flow], Tabla8[Foto],"",0) -> #VALUE! | B34: Sur | C34: Gonzalez Cabrera, Antonio | D34: SEG Asistencia | E34: BANCO CREDICOOP | F34: 808251 | G34: Pellegrini 851 | H34: Comodoro Rivadavia | I34: 0.35416667 | J34: Hasta 08/01/2026 08:52:27
A35: =_xlfn.XLOOKUP(Control_Inicio[[#This Row],[TECNICO]],Tabla8[Nombre Flow], Tabla8[Foto],"",0) -> #VALUE! | B35: Suroeste | C35: Ibañez, Pablo Fernando | D35: Sin pedidos asignados
A36: =_xlfn.XLOOKUP(Control_Inicio[[#This Row],[TECNICO]],Tabla8[Nombre Flow], Tabla8[Foto],"",0) -> #VALUE! | B36: Suroeste | C36: Lazzaro, Leonardo | D36: Sin pedidos asignados
A37: =_xlfn.XLOOKUP(Control_Inicio[[#This Row],[TECNICO]],Tabla8[Nombre Flow], Tabla8[Foto],"",0) -> #VALUE! | B37: Suroeste | C37: Meneses, Cristian | D37: Sin pedidos asignados

Sheet Asignados
A1: =Asignados[[#Totals],[Cliente]] -> 37
A2: Pedido | B2: Estado | C2: Cpto Llamada | D2: Cliente | E2: Luno | F2: Direccion | G2: Localidad | H2: LATITUD | I2: LONGITUD | J2: Stock | K2: Despachos | L2: Tec Asignado | M2: F Alta | N2: Marca Coordinación | O2: Fecha Vto | P2: Desc Problema | Q2: Detalle Falla | R2: Modelo | S2: Tec Zona | T2: Zona Local | U2: Provincia | V2: País
A3: 101162952 | B3: SEG Registrado | C3: SERVICE CALL | D3: BAPRO | E3: 11488 | F3: Avellaneda 199 | G3: General Madariaga | H3: -36.541359 | I3: -56.689995 | L3: Aldayturriaga, Martin | M3: 46083 | N3: 2/3/2026 14:00 | O3: SLA 02/03/2026 17:55:19 | P3: ATM-LECTORA DE TARJETA | Q3: falla en la lectora de tarjetas | R3: DT-7000H22V | S3: Montiel, Juan Fernando | T3: Atlántica | U3: Buenos Aires | V3: Argentina
A4: 101161452 | B4: SEG Registrado | C4: SERVICE CALL | D4: ARCOS DORADOS | E4: 005091015170 | F4: Av. Bunge 682 | G4: Pinamar | H4: -37.11108 | I4: -56.86523 | J4: 200182605 | K4: Repuesto Enviado | L4: Aldayturriaga, Martin | M4: 46076 | N4: 2/3/2026 14:00 | O4: Hasta 25/02/2026 18:01:12 | P4: SMC-ASISTENCIA POR FALLA | Q4: Se solicita asistencia para el cliente de referencia ya que tiene error en sensor de bolsa. Equipo con valores 2% | R4: CTE2 SNBC -C | S4: Montiel, Juan Fernando | T4: Atlántica | U4: Buenos Aires | V4: Argentina
A5: 101144122 | B5: SEG Control Final | C5: MTM | D5: BANCO NACION | E5: 4136 | F5: Avda. General San Martín Oeste 1 | G5: Santa Rosa | H5: -36.618133 | I5: -64.299688 | L5: Allende, Martin Leandro | M5: 46025 | N5: 2/3/2026 08:00 | O5: Hasta 05/01/2026 14:00:00 | P5: ATM-Mantenimiento preventivo | Q5: MANTENIMIENTO PREVENTIVO 1er. SEMESTRE 2026. Anexar foto del ATM antes y después de la actividad. | R5: DT-7000H34N (FECT) | S5: Allende, Martin Leandro | T5: La Pampa | U5: La Pampa | V5: Argentina
A6: 101145353 | B6: SEG Registrado | C6: MTM | D6: BANCO NACION | E6: 10298 | F6: Avda. De Los Mineros 550 | G6: Rio Turbio | H6: -51.53911 | I6: -72.338294 | L6: Barrera, Fernando Andrés | M6: 46025 | N6: 13/1/2026 08:00 | O6: Hasta 06/01/2026 13:00:00 | P6: ATM-Mantenimiento preventivo | Q6: MANTENIMIENTO PREVENTIVO 1er. SEMESTRE 2026. Anexar foto del ATM antes y después de la actividad. | R6: ATM OPTEVA 522 | S6: Barrera, Fernando Andrés | T6: Contratistas | U6: Santa Cruz | V6: Argentina
A7: 101144492 | B7: SEG Registrado | C7: MTM | D7: BANCO NACION | E7: 7947 | F7: Calle 15 N° 551 | G7: Balcarce | H7: -37.84638 | I7: -58.25549 | L7: Buratti, Fabian | M7: 46025 | N7: 24/2/2026 12:15 | O7: Hasta 05/01/2026 16:00:00 | P7: ATM-Mantenimiento preventivo | Q7: MANTENIMIENTO PREVENTIVO 1er. SEMESTRE 2026. Anexar foto del ATM antes y después de la actividad. | R7: DT-7000H22V | S7: Buratti, Fabian | T7: Atlántica | U7: Buenos Aires | V7: Argentina
A8: 101145114 | B8: SEG Registrado | C8: MTM | D8: BANCO NACION | E8: 10478 | F8: Gral. San Martín 2594 | G8: Mar Del Plata | H8: -37.999208 | I8: -57.559081 | L8: Buratti, Fabian | M8: 46025 | N8: 27/2/2026 09:00 | O8: Hasta 05/01/2026 15:00:00 | P8: ATM-Mantenimiento preventivo | Q8: MANTENIMIENTO PREVENTIVO 1er. SEMESTRE 2026. Anexar foto del ATM antes y después de la actividad. | R8: ATM OPTEVA 522 | S8: Buratti, Fabian | T8: Atlántica | U8: Buenos Aires | V8: Argentina
A9: 101162470 | B9: SEG Asistencia | C9: SERVICE CALL | D9: BAPRO | E9: 11369 | F9: Av. Constitucion 5850 | G9: Mar Del Plata | H9: -37.999208 | I9: -57.559081 | L9: Buratti, Fabian | M9: 46080 | N9: 2/3/2026 10:00 | O9: Hasta 02/03/2026 13:00:00 | P9: ATM-DEPÓSITO | Q9: - Falla : presenta falla en la zona de recepción del efectivo. El módulo no está operativo._x000D_ _x000D_ se agrega Falla: esta trabado el módulo de dispensador. | R9: DT-7000H34N | S9: Buratti, Fabian | T9: Atlántica | U9: Buenos Aires | V9: Argentina
A10: 101162906 | B10: SEG Registrado | C10: SERVICE CALL | D10: ACA | E10: 002359016370 | F10: Diagonal F De La Palza 1733 | G10: Miramar | H10: -38.26655 | I10: -57.834387 | L10: Castaño, Matias | M10: 46082 | N10: 2/3/2026 11:30 | O10: Hasta 02/03/2026 18:15:52 | P10: SMC-IMPRESORA | Q10: Cliente reporta que no le imprime el dispositivo, se ejecutaron las siguientes pruebas:_x000D_ Simulación de cambio de papel_x000D_ Test Print automático (fallido)_x000D_ Página de prueba de Windows (fallida)_x000D_ Configuración completa en CAOS (correcta)_x000D_ Verificación de coincidencia del nombre_x000D_ Seteo desde modo Supervisor_x000D_ _x000D_ La impresora continúa sin imprimir en ningún escenario._x000D_ Posible falla física del módulo de impresión y no un problema de configuración._x000D_ Se solicita asistencia técnica para su verificación +5492291401747 | R10: CIMA SDM500 | S10: Castaño, Matias | T10: Atlántica | U10: Buenos Aires | V10: Argentina
A11: 101162995 | B11: SEG Registrado | C11: SERVICE CALL | D11: BAPRO | E11: 6571 | F11: Calle 64 3000 | G11: Necochea | H11: -38.359431 | I11: -59.613727 | L11: Chiriello, Pablo Javier | M11: 46083 | N11: 2/3/2026 14:00 | O11: Hasta 03/03/2026 10:05:08 | P11: ATM-IMPRESORA DE RECIBO | Q11: - Falla : presenta falla en la impresión de ticket.Es un error constante que deja el atm fuera de servicio. Por el momento se encuentra funcionando , pero son arreglos temporales. | R11: DT-7000H34N | S11: Chiriello, Pablo Javier | T11: Atlántica | U11: Buenos Aires | V11: Argentina
A12: 101162436 | B12: SEG Asistencia | C12: SERVICE CALL | D12: BAPRO | E12: 8728 | F12: Av. J. Peralta Ramos 1890 | G12: Mar Del Plata | H12: -37.999208 | I12: -57.559081 | J12: 200182779 | K12: Repuesto Pendiente | L12: Chiriello, Pablo Javier | M12: 46080 | N12: 2/3/2026 08:00 | O12: Hasta 02/03/2026 13:00:00 | P12: ATM-LECTORA DE TARJETA | Q12: Falla: falla en lectora de tarjetas, queda en servicio con falla. | R12: DT-7000H22V | S12: Chiriello, Pablo Javier | T12: Atlántica | U12: Buenos Aires | V12: Argentina
A13: 101161660 | B13: SEG Control Final | C13: SERVICE CALL | D13: BAPRO | E13: 11347 | F13: Av. Mario Bravo 3650 | G13: Mar Del Plata | H13: -37.999208 | I13: -57.559081 | J13: 200182716 | K13: Repuesto Enviado | L13: Chiriello, Pablo Javier | M13: 46077 | N13: 2/3/2026 10:30 | O13: Hasta 27/02/2026 11:22:48 | P13: ATM-VERIFICACIÓN DE FALLA | Q13: Falla: Pantalla cliente poco brillo. por favor revisar/ajustar/reemplaza | R13: DT-7000H22V | S13: Chiriello, Pablo Javier | T13: Atlántica | U13: Buenos Aires | V13: Argentina
A14: 101146210 | B14: SEG Asistencia | C14: MTM | D14: BAPRO | E14: 11347 | F14: Av. Mario Bravo 3650 | G14: Mar Del Plata | H14: -37.999208 | I14: -57.559081 | L14: Chiriello, Pablo Javier | M14: 46027 | N14: 2/3/2026 11:00 | O14: Hasta 05/01/2026 16:48:41 | P14: ATM-Mantenimiento preventivo | Q14: Mantenimiento Preventivo Primer Semestre 2026 | R14: DT-7000H22V | S14: Chiriello, Pablo Javier | T14: Atlántica | U14: Buenos Aires | V14: Argentina
A15: 101160721 | B15: SEG Asistencia | C15: AIEC | D15: CLIENTE INTERNO | E15: MDP | F15: Alvear 4862 | G15: Mar Del Plata | H15: -37.999208 | I15: -57.559081 | L15: Deus, Mariano | M15: 46073 | N15: 20/2/2026 10:15 | O15: Hasta 20/02/2026 09:51:58 | P15: GI-TAREAS GENERALES | Q15: Tareas en planta/ generales | R15: ATM | S15: Buratti, Fabian | T15: Atlántica | U15: Buenos Aires | V15: Argentina
A16: 101160324 | B16: SEG Asistencia | C16: TAD | D16: CLIENTE INTERNO | E16: MDP | F16: Alvear 4862 | G16: Mar Del Plata | H16: -37.999208 | I16: -57.559081 | L16: Deus, Mariano | M16: 46071 | N16: 18/2/2026 15:23 | O16: Hasta 18/02/2026 15:20:50 | P16: GI-CONTROL DE STOCK | Q16: Entrega de Repuesto Stock Regional MDP | R16: ATM | S16: Buratti, Fabian | T16: Atlántica | U16: Buenos Aires | V16: Argentina
A17: 101161411 | B17: SEG Asistencia | C17: TAD | D17: BAPRO | E17: 11090 | F17: General Paz 299 | G17: Coronel Vidal | H17: -37.44652 | I17: -57.72939 | L17: Deus, Mariano | M17: 46076 | N17: 24/2/2026 09:00 | O17: Hasta 24/02/2026 13:00:00 | P17: ATM-AUDITORIA | Q17: Auditoría ATM | R17: DT-7000H34N | S17: Buratti, Fabian | T17: Atlántica | U17: Buenos Aires | V17: Argentina
A18: 101162414 | B18: SEG Asistencia | C18: SERVICE CALL | D18: BAPRO | E18: 11214 | F18: San Martin 1 | G18: Pellegrini | H18: -36.26785 | I18: -63.164671 | J18: 200182749 | K18: Repuesto Enviado | L18: Garcia, Alejandro Javier | M18: 46080 | N18: 2/3/2026 10:30 | O18: Hasta 02/03/2026 13:32:32 | P18: ATM-DISPENSADOR | Q18: traba billetes | R18: DT-7000H34N | S18: Garcia, Alejandro Javier | T18: Oeste | U18: Buenos Aires | V18: Argentina
A19: 101144432 | B19: SEG Registrado | C19: MTM | D19: BANCO NACION | E19: 4203 | F19: Rivadavia 698 | G19: General Villegas | H19: -35.3261 | I19: -63.1477 | L19: Garcia, Alejandro Javier | M19: 46025 | N19: 27/2/2026 12:30 | O19: Hasta 06/01/2026 09:00:00 | P19: ATM-Mantenimiento preventivo | Q19: MANTENIMIENTO PREVENTIVO 1er. SEMESTRE 2026. Anexar foto del ATM antes y después de la actividad. | R19: DT-7000H34N (FECT) | S19: Garcia, Alejandro Javier | T19: Oeste | U19: Buenos Aires | V19: Argentina
A20: 101146930 | B20: SEG Registrado | C20: MTM | D20: BAPRO | E20: 5586 | F20: Alberto Almiron 201 | G20: Carlos Tejedor | H20: -35.39852 | I20: -62.4226 | L20: Garcia, Alejandro Javier | M20: 46027 | N20: 25/2/2026 09:30 | O20: Hasta 06/01/2026 17:00:00 | P20: ATM-Mantenimiento preventivo | Q20: Mantenimiento Preventivo Primer Semestre 2026 | R20: DT-7000H34N | S20: Garcia, Alejandro Javier | T20: Oeste | U20: Buenos Aires | V20: Argentina
A21: 101162329 | B21: SEG Asistencia | C21: SERVICE CALL | D21: BANCO NACION | E21: 5060 | F21: 9 de Julio 127 | G21: Puerto Madryn | H21: -42.766396 | I21: -65.354612 | J21: 200182755 | K21: Repuesto Enviado | L21: Godoy, Diego | M21: 46080 | N21: 2/3/2026 10:00 | O21: Hasta 27/02/2026 14:54:40 | P21: ATM-MONITOR DE CLIENTE | Q21: Pantalla de clientes y teclado no funcionan_x000D_ SLA Vence 27/02 14:52_x000D_ Prosegur 08 a 16 | R21: ATM OPTEVA 522 | S21: Godoy, Diego | T21: Sur | U21: Chubut | V21: Argentina
A22: 101162889 | B22: SEG Registrado | C22: SERVICE CALL | D22: CENCOSUD S.A | E22: 008681061970 | F22: Manuel Belgrano 372 | G22: Puerto Madryn | H22: -42.766396 | I22: -65.354612 | L22: Godoy, Diego | M22: 46082 | N22: 2/3/2026 12:00 | O22: Hasta 02/03/2026 16:55:22 | P22: SMC-CPU | Q22: cte reclama que la PC no inicia, aparece error en disco. se solicita asistencia | R22: GLORY P500 | S22: Godoy, Diego | T22: Sur | U22: Chubut | V22: Argentina
A23: 101162157 | B23: SEG Espera Llegada | C23: SERVICE CALL | D23: BANCO CREDICOOP | E23: 814621 | F23: 9 de Julio 270 | G23: Trelew | H23: -43.251626 | I23: -65.36983 | J23: 200182737 | K23: Repuesto Enviado | L23: Godoy, Diego | M23: 46079 | N23: 2/3/2026 13:00 | O23: Hasta 02/03/2026 11:34:10 | P23: ATM-DISPENSADOR | Q23: REITERA FALLA EN DISPENSADOR | R23: DT-7000H22V | S23: Godoy, Diego | T23: Sur | U23: Chubut | V23: Argentina
A24: 101147891 | B24: SEG Asistencia | C24: MTM | D24: BANCO CREDICOOP | E24: 808231 | F24: Pellegrini 851 | G24: Comodoro Rivadavia | H24: -45.867823 | I24: -67.479235 | L24: Gonzalez Cabrera, Antonio | M24: 46028 | N24: 2/3/2026 08:30 | O24: Hasta 08/01/2026 08:51:10 | P24: ATM-Mantenimiento preventivo | Q24: Mantenimiento Preventivo Primer Semestre 2026 | R24: ATM FULL OPTEVA 720 R/L ENA | S24: Gonzalez Cabrera, Antonio | T24: Sur | U24: Chubut | V24: Argentina
A25: 101147981 | B25: SEG Asistencia | C25: MTM | D25: BANCO CREDICOOP | E25: 808251 | F25: Pellegrini 851 | G25: Comodoro Rivadavia | H25: -45.867823 | I25: -67.479235 | L25: Gonzalez Cabrera, Antonio | M25: 46028 | N25: 2/3/2026 08:30 | O25: Hasta 08/01/2026 08:52:27 | P25: ATM-Mantenimiento preventivo | Q25: Mantenimiento Preventivo Primer Semestre 2026 | R25: ATM FULL OPTEVA 720 R/L 5ºGAV/G VOZ | S25: Gonzalez Cabrera, Antonio | T25: Sur | U25: Chubut | V25: Argentina
A26: 101148074 | B26: SEG Registrado | C26: MTM | D26: BANCO CREDICOOP | E26: 808221 | F26: Pellegrini 851 | G26: Comodoro Rivadavia | H26: -45.867823 | I26: -67.479235 | L26: Gonzalez Cabrera, Antonio | M26: 46028 | N26: 2/3/2026 08:30 | O26: Hasta 08/01/2026 08:54:38 | P26: ATM-Mantenimiento preventivo | Q26: Mantenimiento Preventivo Primer Semestre 2026 | R26: ATM FULL OPTEVA 720 R/L 5ºGAV/G VOZ | S26: Gonzalez Cabrera, Antonio | T26: Sur | U26: Chubut | V26: Argentina
A27: 101162965 | B27: SEG Asistencia | C27: TAD | D27: CLIENTE INTERNO | E27: SRO | F27: Fiorucci 45 | G27: Santa Rosa | H27: -36.618133 | I27: -64.299688 | L27: Hernandez, Marcos Alberto | M27: 46083 | N27: 2/3/2026 09:20 | O27: Hasta 02/03/2026 09:18:00 | P27: GI- AUDITORIA A TECNICO | Q27: Auditoría Martín Allende | R27: ATM | S27: Hernandez, Marcos Alberto | T27: La Pampa | U27: La Pampa | V27: Argentina
A28: 101146540 | B28: SEG Asistencia | C28: MTM | D28: BAPRO | E28: 11202 | F28: Los Ligustros S/N | G28: Olavarria | H28: -36.98147 | I28: -63.14138 | L28: Martos, Jose Angel | M28: 46027 | N28: 2/3/2026 09:00 | O28: Hasta 06/01/2026 17:00:00 | P28: ATM-Mantenimiento preventivo | Q28: Mantenimiento Preventivo Primer Semestre 2026 | R28: DT-7000H34N | S28: Martos, Jose Angel | T28: Oeste | U28: Buenos Aires | V28: Argentina
A29: 101146120 | B29: SEG Asistencia | C29: MTM | D29: BAPRO | E29: 11314 | F29: Bartolome Mitre 925 | G29: Coronel Pringles | L29: Martos, Jose Angel | M29: 46027 | N29: 25/2/2026 09:30 | O29: Hasta 06/01/2026 17:00:00 | P29: ATM-Mantenimiento preventivo | Q29: Mantenimiento Preventivo Primer Semestre 2026 | R29: DT-7000H34N | S29: Rodriguez, Mateo Joaquin | T29: Centro | U29: Buenos Aires | V29: Argentina
A30: 101147896 | B30: SEG Registrado | C30: MTM | D30: BANCO CREDICOOP | E30: 823031 | F30: Vicente Lopez 3045 | G30: Olavarria | H30: -36.98147 | I30: -63.14138 | L30: Martos, Jose Angel | M30: 46028 | N30: 2/3/2026 12:30 | O30: Hasta 07/01/2026 14:00:00 | P30: ATM-Mantenimiento preventivo | Q30: Mantenimiento Preventivo Primer Semestre 2026 | R30: ATM FULL OPTEVA 720 R/L ENA/ 5 GAV | S30: Martos, Jose Angel | T30: Oeste | U30: Buenos Aires | V30: Argentina
A31: 101163027 | B31: SEG Registrado | C31: SERVICE CALL | D31: BANCO CREDICOOP | E31: 823031 | F31: Vicente Lopez 3045 | G31: Olavarria | H31: -36.98147 | I31: -63.14138 | L31: Martos, Jose Angel | M31: 46083 | N31: 2/3/2026 12:30 | O31: Hasta 04/03/2026 10:10:34 | P31: ATM-DEPÓSITO | Q31: Descripción: hace la apertura del buzón pero no toma el efectivo y hace ruido en los engranajes | R31: ATM FULL OPTEVA 720 R/L ENA/ 5 GAV | S31: Martos, Jose Angel | T31: Oeste | U31: Buenos Aires | V31: Argentina
A32: 101146515 | B32: SEG Registrado | C32: MTM | D32: BAPRO | E32: 11125 | F32: San Martin 899 | G32: Carhue | L32: Martos, Jose Angel | M32: 46027 | N32: 26/2/2026 12:30 | O32: Hasta 06/01/2026 17:00:00 | P32: ATM-Mantenimiento preventivo | Q32: Mantenimiento Preventivo Primer Semestre 2026 | R32: DT-7000H34N | S32: Rodriguez, Mateo Joaquin | T32: Centro | U32: Buenos Aires | V32: Argentina
A33: 101146586 | B33: SEG Asistencia | C33: MTM | D33: BAPRO | E33: 11203 | F33: Los Ligustros S/N | G33: Olavarria | H33: -36.98147 | I33: -63.14138 | L33: Martos, Jose Angel | M33: 46027 | N33: 2/3/2026 09:00 | O33: Hasta 06/01/2026 17:00:00 | P33: ATM-Mantenimiento preventivo | Q33: Mantenimiento Preventivo Primer Semestre 2026 | R33: DT-7000H34N | S33: Martos, Jose Angel | T33: Oeste | U33: Buenos Aires | V33: Argentina
A34: 101162508 | B34: SEG Registrado | C34: SERVICE CALL | D34: BANCO CREDICOOP | E34: 812051 | F34: Sarmiento 2200 | G34: Bahia Blanca | H34: -38.736789 | I34: -62.333135 | J34: 200182770 | K34: Repuesto Pendiente | L34: Pavon, Diego Emanuel | M34: 46080 | N34: 2/3/2026 13:00 | O34: Hasta 03/03/2026 14:00:00 | P34: ATM-ACEPTADOR DE BILLETES | Q34: Falla en Depósitos de Acreditación Inmediata:_x000D_ El ATM no muestra errores pero rechaza casi todos los billetes, tomando apenas 2 o 3 billetes por transacción de depósito. | R34: ATM FULL OPTEVA 720 R/L ENA/ 5 GAV EDC R | S34: Pavon, Diego Emanuel | T34: Centro | U34: Buenos Aires | V34: Argentina
A35: 101148005 | B35: SEG Asistencia | C35: MTM | D35: BANCO CREDICOOP | E35: 812931 | F35: Garibaldi 360 | G35: Bahia Blanca | H35: -38.736789 | I35: -62.333135 | L35: Pavon, Diego Emanuel | M35: 46028 | N35: 2/3/2026 09:00 | O35: Hasta 07/01/2026 14:00:00 | P35: ATM-Mantenimiento preventivo | Q35: Mantenimiento Preventivo Primer Semestre 2026 | R35: ATM FULL OPTEVA 720 R/L | S35: Pavon, Diego Emanuel | T35: Centro | U35: Buenos Aires | V35: Argentina
A36: 101148006 | B36: SEG Asistencia | C36: MTM | D36: BANCO CREDICOOP | E36: 812951 | F36: Garibaldi 360 | G36: Bahia Blanca | H36: -38.736789 | I36: -62.333135 | L36: Pavon, Diego Emanuel | M36: 46028 | N36: 2/3/2026 09:00 | O36: Hasta 07/01/2026 14:00:00 | P36: ATM-Mantenimiento preventivo | Q36: Mantenimiento Preventivo Primer Semestre 2026 | R36: ATM FULL OPTEVA 720 R/L 5ºGAV | S36: Pavon, Diego Emanuel | T36: Centro | U36: Buenos Aires | V36: Argentina
A37: 101162424 | B37: SEG Asistencia | C37: SERVICE CALL | D37: BANCO CREDICOOP | E37: 812931 | F37: Garibaldi 360 | G37: Bahia Blanca | H37: -38.736789 | I37: -62.333135 | L37: Pavon, Diego Emanuel | M37: 46080 | N37: 2/3/2026 09:00 | O37: Hasta 03/03/2026 11:57:07 | P37: ATM-DISPENSADOR | Q37: Descripción: Fallas aleatorias de dispensador. Revisión de módulo y gavetas. | R37: ATM FULL OPTEVA 720 R/L | S37: Pavon, Diego Emanuel | T37: Centro | U37: Buenos Aires | V37: Argentina
A38: 101162426 | B38: SEG Asistencia | C38: SERVICE CALL | D38: BANCO CREDICOOP | E38: 812951 | F38: Garibaldi 360 | G38: Bahia Blanca | H38: -38.736789 | I38: -62.333135 | L38: Pavon, Diego Emanuel | M38: 46080 | N38: 2/3/2026 09:00 | O38: Hasta 03/03/2026 11:57:40 | P38: ATM-DISPENSADOR | Q38: Descripción: Fallas aleatorias de dispensador. Revisión de módulo y gavetas. | R38: ATM FULL OPTEVA 720 R/L 5ºGAV | S38: Pavon, Diego Emanuel | T38: Centro | U38: Buenos Aires | V38: Argentina
A39: 101162427 | B39: SEG Asistencia | C39: SERVICE CALL | D39: BANCO CREDICOOP | E39: 812961 | F39: Garibaldi 360 | G39: Bahia Blanca | H39: -38.736789 | I39: -62.333135 | L39: Pavon, Diego Emanuel | M39: 46080 | N39: 2/3/2026 09:00 | O39: Hasta 03/03/2026 11:59:37 | P39: ATM-DISPENSADOR | Q39: Descripción: Fallas aleatorias de dispensador. Revisión de módulo y gavetas. | R39: ATM FULL OPTEVA 720 R/L ENA | S39: Pavon, Diego Emanuel | T39: Centro | U39: Buenos Aires | V39: Argentina
A40: Total | D40: =SUBTOTAL(103,Asignados[Cliente]) -> 37 | V40: =SUBTOTAL(103,Asignados[País]) -> 37

Sheet Adicionales
S1: =TODAY() -> 46086 | T1: =WEEKNUM(TODAY(),2) -> 10
A2: Cliente | B2: Obra | C2: ATM | D2: Sucursal | E2: Direccion | F2: Localidad | G2: Provincia | H2: Fecha | I2: Hora | J2: Serie | K2: Modelo | L2: Actividad | M2: Pedido COT | N2: Semana | Q2: =WEEKNUM(TODAY()) -> 10 | S2: {=IFERROR(_xlfn._xlws.SORT(_xlfn._xlws.FILTER(TEXT((Adicionales[Fecha]),"dd/mm")&" "&(Adicionales[Cliente])&" "&(Adicionales[ATM])&" "&(Adicionales[Localidad])&" "&(Adicionales[Actividad]), Adicionales[Fecha]=$S$1)),"Sin adicionales")} -> Sin adicionales
A3: Cooperativa Obrera | B3: 15472 | C3: SNBC02CTE00341 | D3: SUC 05 - BAHIA BLANCA (CENTRO) | E3: Belgrano 45 | F3: Bahia Blanca | G3: Buenos Aires | H3: 45664 | I3: 09:00 | J3: SNBC02CTE00341 | K3: SNBC 2 CTE | L3: Recambio | M3: 101011773 | N3: =WEEKNUM(Adicionales[[#This Row],[Fecha]],2) -> 2
A4: Cooperativa Obrera | B4: 15472 | C4: SNBC02CTE00342 | D4: SUC 42 - Hiper del Shopping (Bahia Blanca) | E4: AV. Sarmiento 2153 | F4: Bahia Blanca | G4: Buenos Aires | H4: 45664 | I4: 0.41666667 | J4: SNBC02CTE00342 | K4: SNBC 2 CTE | L4: Recambio | M4: 101011738 | N4: =WEEKNUM(Adicionales[[#This Row],[Fecha]],2) -> 2
A5: Cooperativa Obrera | B5: 15472 | C5: SNBC02CTE00340 | D5: SUC 18 - BAHIA BLANCA (ROCA) | E5: Roca 34 | F5: BAHIA BLANCA | G5: Buenos Aires | H5: 45665 | I5: 0.41666667 | J5: SNBC02CTE00340 | K5: SNBC 2 CTE | L5: Recambio | N5: =WEEKNUM(Adicionales[[#This Row],[Fecha]],2) -> 2
A6: Cooperativa Obrera | B6: 15472 | C6: SNBC02CTE00329 | D6: SUC 68 - Punta Alta | E6: Av. La Estación s/n | F6: Punta Alta | G6: Buenos Aires | H6: 45666 | I6: 0.41666667 | J6: SNBC02CTE00329 | K6: SNBC 2 CTE | L6: Recambio | M6: 101011750 | N6: =WEEKNUM(Adicionales[[#This Row],[Fecha]],2) -> 2
A7: Sepsa | B7: 15480 | C7: 2201153770 | D7: LUGAR SOÑADO BUZON | E7: AV. BUZON 494 | F7: TANDIL | G7: Buenos Aires | H7: 45678 | I7: 10:00 | J7: SNBCULCTI01163 | K7: SNBC UL CTI CON CAMARA | L7: Instalación | M7: 101018719 | N7: =WEEKNUM(Adicionales[[#This Row],[Fecha]],2) -> 4
A8: Nacion | B8: 14916 | C8: 4998 | D8: 2320 MACACHIN | E8: FRATINI 301 | F8: MACACHIN | G8: La Pampa | H8: 45700 | I8: 0.45833333 | J8: 603014 | K8: DT-7000H34N (FECT) | L8: Instalación | N8: =WEEKNUM(Adicionales[[#This Row],[Fecha]],2) -> 7
A9: La Pampa | B9: 15013 | C9: 14104 | D9: Plaza Independencia | E9: Belgrano y Malvinas Argentinas | F9: Relmo | G9: La Pampa | H9: 45707 | J9: 634138 | K9: DT-7000H22VLR | L9: Instalación | M9: 101026886 | N9: =WEEKNUM(Adicionales[[#This Row],[Fecha]],2) -> 8
A10: La Pampa | B10: 15013 | C10: 14105 | D10: Shelter Neutral Perú | E10: Planta Urbana s/n – Ruta 35 Km 206 | F10: Peru | G10: La Pampa | H10: 45701 | J10: 634139 | K10: DT-7000H22VLR | L10: Instalación | N10: =WEEKNUM(Adicionales[[#This Row],[Fecha]],2) -> 7
A11: La Pampa | B11: 15013 | C11: 14102 | D11: Shelter Parque Infantil | E11: Roque Saenz Peña 2045 | F11: Toay | G11: La Pampa | H11: 45728 | J11: 634140 | K11: DT-7000H22VLR | L11: Instalación | N11: =WEEKNUM(Adicionales[[#This Row],[Fecha]],2) -> 11
A12: La Pampa | B12: 15013 | C12: 14102 | D12: Shelter Parque Infantil | E12: Roque Saenz Peña 2045 | F12: Toay | G12: La Pampa | H12: 45728 | J12: 639685 | K12: DT-7000H22VLR | L12: Instalación | N12: =WEEKNUM(Adicionales[[#This Row],[Fecha]],2) -> 11
A13: La Pampa | B13: 15013 | C13: 14106 | D13: Shelter | E13: Sarah | F13: Sarah | G13: La Pampa | H13: 45733 | J13: 634137 | K13: DT-7000H22VLR | L13: Instalación | N13: =WEEKNUM(Adicionales[[#This Row],[Fecha]],2) -> 12
A14: Nación | B14: 14916 | C14: 6080 | D14: 3790 VILLA HUIDOBRO | E14: AVDA. MANUEL A. ESPINOSA 301 | F14: VILLA HUIDOBRO | G14: Cordoba | H14: 45743 | I14: 0.45833333 | J14: 603026 | K14: DT-7000H34N (FECT) | L14: Instalación | M14: 101044310 | N14: =WEEKNUM(Adicionales[[#This Row],[Fecha]],2) -> 13
A15: Nacion | B15: 14916 | C15: 6053 | D15: 3836 WINIFREDA | E15: PRESIDENTE RAÚL RICARDO ALFONSÍN 348 | F15: WINIFREDA | G15: La Pampa | H15: 45742 | I15: 0.45833333 | J15: 730719 | K15: DT-7000H34N (FECT) | L15: Instalación | M15: 101044306 | N15: =WEEKNUM(Adicionales[[#This Row],[Fecha]],2) -> 13
A16: Favanet SA | B16: A definir | C16: 004925003170 | D16: Bahia Blanca | E16: Chiclana 501 | F16: Bahia Blanca | G16: Buenos Aires | H16: 45758 | I16: 0.45833333 | J16: SNBCULCTI01221 | K16: SNBC UL CTI CON CAMARA | L16: Instalación | N16: =WEEKNUM(Adicionales[[#This Row],[Fecha]],2) -> 15
A17: FRAVEGA SACIEI | B17: 15567 | D17: SUC 152 - SANTA ROSA | E17: Cnel. Gil 267 - SANTA ROSA | F17: SANTA ROSA | G17: La Pampa | H17: 45755 | I17: 0.33333333 | K17: SNBC UL CTI | L17: Relevamiento | M17: 101049354 | N17: =WEEKNUM(Adicionales[[#This Row],[Fecha]],2) -> 15
A18: FRAVEGA SACIEI | B18: 15567 | D18: SUC 162 - RIO GRANDE | E18: Av. San Martin 170 - RIO GRANDE | F18: RIO GRANDE | G18: Tierra del Fuego | H18: 45757 | K18: SNBC UL CTI | L18: Relevamiento | N18: =WEEKNUM(Adicionales[[#This Row],[Fecha]],2) -> 15
A19: Nacion | B19: 14916 | C19: 4291 | D19: 2992 RIVERA | E19: AVDA. S. MARTÍN ESQ.DE LOS COLONIZADORES | F19: RIVERA | G19: Buenos Aires | H19: 45776 | I19: 0.54166667 | J19: 603108 | K19: DT-7000H34N (FECT) | L19: Instalación | M19: 101055714 | N19: =WEEKNUM(Adicionales[[#This Row],[Fecha]],2) -> 18
A20: BAPRO | B20: 14810 | C20: 11471 | D20: AEROPUERTO BAHIA BLANCA | E20: Ex Ruta 3 Norte KM 675 | F20: BAHIA BLANCA | G20: Buenos Aires | H20: 45803 | I20: 0.41666667 | J20: 578002 | K20: DT-7000H22V | L20: Instalación | N20: =WEEKNUM(Adicionales[[#This Row],[Fecha]],2) -> 22
A21: Nacion | B21: 14916 | C21: 6208 | D21: 1360 CASBAS | E21: H. YRIGOYEN 400 | F21: CASBAS | G21: Buenos Aires | H21: 45798 | I21: 0.54166667 | J21: 738912 | K21: DT-7000H34N (FECT) | L21: Instalación | N21: =WEEKNUM(Adicionales[[#This Row],[Fecha]],2) -> 21
A22: BAPRO | B22: 14810 | C22: 11487 | D22: GRAL MADARIAGA 6952 | E22: Avellaneda 199 | F22: GRAL MADARIAGA | G22: Buenos Aires | H22: 45803 | I22: 0.41666667 | L22: Instalación | N22: =WEEKNUM(Adicionales[[#This Row],[Fecha]],2) -> 22
A23: BAPRO | B23: 14810 | C23: 11488 | D23: GRAL MADARIAGA 6952 | E23: Avellaneda 199 | F23: GRAL MADARIAGA | G23: Buenos Aires | H23: 45803 | I23: 0.41666667 | L23: Instalación | N23: =WEEKNUM(Adicionales[[#This Row],[Fecha]],2) -> 22
A24: BAPRO | B24: 14810 | C24: 11495 | D24: SAN BERNARDO | E24: CHIOZZA 2351 | F24: SAN BERNARDO | G24: Buenos Aires | H24: 45863 | I24: 0.41666667 | J24: 578318 | K24: DT-7000H22V | L24: Instalación | M24: 101085431 | N24: =WEEKNUM(Adicionales[[#This Row],[Fecha]],2) -> 30
A25: Nacion | B25: 14916 | C25: 10004 | D25: 2030 INGENIERO LUIGGI | E25: BELGRANO 327 | F25: INGENIERO LUIGGI | G25: La Pampa | H25: 45846 | I25: 0.45833333 | J25: 738612 | K25: DT-7000H22V | L25: Instalación | M25: 101085013 | N25: =WEEKNUM(Adicionales[[#This Row],[Fecha]],2) -> 28
A26: Nacion | B26: 14916 | C26: 4428 | D26: 2030 INGENIERO LUIGGI | E26: BELGRANO 327 | F26: INGENIERO LUIGGI | G26: La Pampa | H26: 45846 | I26: 0.45833333 | J26: 603074 | K26: DT-7000H34N (FECT) | L26: Instalación | M26: 101085016 | N26: =WEEKNUM(Adicionales[[#This Row],[Fecha]],2) -> 28
A27: UNTS S.A | B27: 15688 | C27: 10286000270 | D27: Bahia Blanca | E27: Av Sarmiento 2153 | F27: Bahia Blanca | G27: Buenos Aires | H27: 45881 | I27: 0.5625 | J27: SNBCULCTI01299 | K27: SNBC UL CTI | L27: Instalación | N27: =WEEKNUM(Adicionales[[#This Row],[Fecha]],2) -> 33
A28: Nacion | B28: 1614 | C28: 4364 | D28: 1653 DAIREAUX | E28: AVDA. JULIO A. ROCA 199 | F28: DAIREAUX | G28: Buenos Aires | H28: 45888 | I28: 0.54166667 | J28: 602940 | K28: DT-7000H34N (FECT) | L28: Instalación | N28: =WEEKNUM(Adicionales[[#This Row],[Fecha]],2) -> 34
A29: Nacion | B29: 1614 | C29: 5907 | D29: 9245 BARRIO LA PERLA | E29: AVDA. LIBERTAD 3802 | F29: Mar del Plata | G29: Buenos Aires | H29: 45888 | I29: 0.54166667 | J29: 728566 | K29: DT-7000H22V | L29: Instalación | N29: =WEEKNUM(Adicionales[[#This Row],[Fecha]],2) -> 34
A30: Nacion | B30: 1614 | C30: 10071 | D30: 9245 BARRIO LA PERLA | E30: AVDA. LIBERTAD 3802 | F30: Mar del Plata | G30: Buenos Aires | H30: 45888 | I30: 0.54166667 | J30: 728571 | K30: DT-7000H22V | L30: Instalación | N30: =WEEKNUM(Adicionales[[#This Row],[Fecha]],2) -> 34
A31: Nacion | B31: 1614 | C31: 10138 | D31: 9245 BARRIO LA PERLA | E31: AVDA. LIBERTAD 3802 | F31: Mar del Plata | G31: Buenos Aires | H31: 45888 | I31: 0.54166667 | J31: 728553 | K31: DT-7000H22V | L31: Instalación | N31: =WEEKNUM(Adicionales[[#This Row],[Fecha]],2) -> 34
A32: Nacion | B32: 1614 | C32: 10072 | D32: 1190 BARRIO PUERTO | E32: AVDA. EDISON 302 | F32: Mar del Plata | G32: Buenos Aires | H32: 45889 | I32: 0.54166667 | J32: 728555 | K32: DT-7000H22V | L32: Instalación | N32: =WEEKNUM(Adicionales[[#This Row],[Fecha]],2) -> 34
A33: Nacion | B33: 1614 | C33: 10073 | D33: 1190 BARRIO PUERTO | E33: AVDA. EDISON 302 | F33: Mar del Plata | G33: Buenos Aires | H33: 45889 | I33: 0.54166667 | J33: 728557 | K33: DT-7000H22V | L33: Instalación | N33: =WEEKNUM(Adicionales[[#This Row],[Fecha]],2) -> 34
A34: Nacion | B34: 1614 | C34: 20203 | D34: 2530 NICANOR OLIVERA | E34: CALLE 22 N° 1001 | F34: Nicanor Olivera | G34: Buenos Aires | H34: 45890 | I34: 0.54166667 | J34: 728520 | K34: DT-7000H22V | L34: Instalación | N34: =WEEKNUM(Adicionales[[#This Row],[Fecha]],2) -> 34
A35: AUTOMOVIL CLUB ARGENTINO | B35: 15816 | C35: 113757 | D35: Ruta 5 y 33 (CP 6400) | F35: Trenque Lauquen | G35: Buenos Aires | H35: 45953 | I35: 0.5 | J35: SNBCULCTI01356 | K35: SNBC UL CTI CON CAMARA | L35: Instalación | N35: =WEEKNUM(Adicionales[[#This Row],[Fecha]],2) -> 43
A36: CUMELCAN SRL | B36: 15826 | C36: - | E36: Avda Juan B. Justo 4885 | F36: Mar del Plata | G36: Buenos Aires | H36: 45953 | I36: 0.47916667 | J36: SNBCULCTI01329 | K36: SNBC UL CTI CON CAMARA | L36: Instalación | N36: =WEEKNUM(Adicionales[[#This Row],[Fecha]],2) -> 43
A37: ACERCAR DISTRIBUCIONES SAS. | B37: 15819 | D37: Plaza Huincul | E37: AV. CORDOBA 1591 - LOTE A31 | F37: PZA. HUINCUL | G37: Neuquen | H37: 45950 | K37: SNBC 90 CTI | L37: Instalación | N37: =WEEKNUM(Adicionales[[#This Row],[Fecha]],2) -> 43
A38: S.A. IMPORTADORA Y EXPORTADORA DE LA PATAGONIA (SAIEP) | B38: 15506 | D38: 234 | E38: Buenos Aires 179 | F38: Plottier | G38: Neuquen | H38: 45952 | K38: SNBC 90 CTI | L38: Instalación | N38: =WEEKNUM(Adicionales[[#This Row],[Fecha]],2) -> 43
A39: GMRA S.A. | B39: 15810 | D39: Samsung Alto Comahue | E39: Av. Dr. Ramón 355 | F39: Neuquén | G39: Neuquen | H39: 45953 | K39: SNBC UL CTI | L39: Instalación | N39: =WEEKNUM(Adicionales[[#This Row],[Fecha]],2) -> 43
A40: S.A. IMPORTADORA Y EXPORTADORA DE LA PATAGONIA (SAIEP) | B40: 15506 | D40: 230 | E40: Avellaneda 99 | F40: Zapala | G40: Neuquen | H40: 45951 | K40: SNBC 90 CTI | L40: Instalación | N40: =WEEKNUM(Adicionales[[#This Row],[Fecha]],2) -> 43
A41: S.A. IMPORTADORA Y EXPORTADORA DE LA PATAGONIA (SAIEP) | B41: 15254 | D41: 208 | E41: Ruta 2, entre Caleta Falsa y Punta Villarino - Las Grutas | F41: Las Grutas | G41: Rio Negro | H41: 45951 | K41: SNBC UL CTI | L41: Instalación | N41: =WEEKNUM(Adicionales[[#This Row],[Fecha]],2) -> 43
A42: Total | C42: =SUBTOTAL(103,Adicionales[ATM]) -> 32

Sheet Datos
A3: Etiquetas de fila | B3: Pedidos
A4: Atlántica | B4: 3
A5: Buratti, Fabian | B5: 2
A6: SIN ASIGNAR | B6: 1
A7: Centro | B7: 5
A8: SIN ASIGNAR | B8: 3
A9: Vicente, Francisco Ariel | B9: 1
A10: Pavon, Diego Emanuel | B10: 1
A11: La Pampa | B11: 1
A12: Allende, Martin Leandro | B12: 1
A13: Oeste | B13: 3
A14: SIN ASIGNAR | B14: 3
A15: Sur | B15: 1
... A17: Total general | B17: 13

Sheet Master LP
A1: PN | B1: DESCRIPCION
A2: 00-000000-0000 | B2: Parte RET TEST
A3: 00-000000-RJ11 | B3: PINZA RJ11 *44-000293-000A*
A4: 00-000000-Y220 | B4: REEMPLAZO TEMPORAL DE ZAPATILLA OPTEVA SPI 220 V
A5: 00-000000-ZZZZ | B5: FUERA DE SISTEMA
A6: 00-000001-000A | B6: DISCO CON IMÁGENES DE WINDOWS Y OS2 SIN IMAGEN 00-1-B
A7: 00-000001-000B | B7: DISCO RIGIDO PARA BTP
A8: 00-000001-000C | B8: DISCO RIGIDO PARA CTP *00-000003-000S*
A9: 00-000001-000G | B9: EXPIRED
A10: 00-000001-000H | B10: EXPIRED
A11: 00-000001-000I | B11: DISCONTINUADO *00-000002-000I*
A12: 00-000001-000K | B12: DISCONTINUADO *00-000002-000K*
... A2405: DR-0MULTI-BOOT | B2405: DISCO MULTI IMAGEN ANEXO GPT

Sheet Despachos
A1: N° Pedido | B1: F Alta | C1: N° Reclamo | D1: Destino | E1: Tecnico | F1: Nro de Guia | G1: Transporte | H1: Datos | I1: Fecha | J1: Column10 | K1: 27/2/2026 | L1: Zona Local | M1: SR | N1: Nación | S1: Pedido | T1: Cliente | U1: Luno | V1: Direccion | W1: Localidad | X1: Ubicacion
A2: 200182735 | B2: 46080 | C2: 101161803 | D2: Jujuy | E2: Albornoz, Claudio | F2: 044-32212854 | G2: Jet-Paq | I2: 46080 | L2: Interior | M2: =IF(Despachos[[#This Row],[N° Reclamo]]=3, "SR","") | N2: =COUNTIF($S$2:$S$12, Despachos[[#This Row],[N° Reclamo]]) -> 0 | S2: 100951785 | T2: BANCO NACION | U2: 7886 | V2: Colectora y Emilio Larraya | W2: Batan | X2: 1204 BATAN
A3: 200182723 | B3: 46080 | C3: 2 | D3: Jujuy | E3: Avila, Julio | F3: 044-32212832 | G3: Jet-Paq | I3: 46080 | L3: Interior | M3: =IF(Despachos[[#This Row],[N° Reclamo]]=3, "SR","") | N3: =COUNTIF($S$2:$S$12, Despachos[[#This Row],[N° Reclamo]]) -> 0 | Q3: =Despachos[[#Totals],[Destino]] -> 5 | S3: 100951682 | T3: BANCO NACION | U3: 7861 | V3: Calle 15 N° 1100 | W3: General Pico
A4: 200182760 | B4: 46080 | C4: 101162439 | D4: Jujuy | E4: Avila, Julio | F4: 044-32212832 | G4: Jet-Paq | I4: 46080 | L4: Interior | M4: =IF(Despachos[[#This Row],[N° Reclamo]]=3, "SR","") | N4: =COUNTIF($S$2:$S$12, Despachos[[#This Row],[N° Reclamo]]) -> 0 | S4: 100951648 | T4: BANCO NACION | U4: 7913 | V4: Av. San Martín 202 | W4: Loberia
A5: 200182746 | B5: 46080 | C5: 101157792 | D5: Posadas | E5: Batocletti, Segundo Domingo | F5: 044-32212876 | G5: Jet-Paq | I5: 46080 | L5: Interior | M5: =IF(Despachos[[#This Row],[N° Reclamo]]=3, "SR","") | N5: =COUNTIF($S$2:$S$12, Despachos[[#This Row],[N° Reclamo]]) -> 0 | S5: 100951796 | T5: BANCO NACION | U5: 4333 | V5: Av. Juan B Justo 6600 | W5: Mar Del Plata | X5: 2350 TOLEDO MAR DEL PLATA
A6: 200182744 | B6: 46080 | C6: 101162326 | D6: cordoba | E6: Cano, Simon Eduardo | F6: 9007-00259555 | G6: Chevallier | I6: 46080 | L6: Interior | M6: =IF(Despachos[[#This Row],[N° Reclamo]]=3, "SR","") | N6: =COUNTIF($S$2:$S$12, Despachos[[#This Row],[N° Reclamo]]) -> 0 | S6: 100951795 | T6: BANCO NACION | U6: 4980 | V6: Ruta 2 KM. 398,50 | W6: Mar Del Plata | X6: 2350 AEROPUERTO MAR DEL PLATA
A7: 200182748 | B7: 46080 | C7: 101162375 | D7: Salta | E7: Chavez, Rodrigo | F7: 044-32212821 | G7: Jet-Paq | I7: 46080 | L7: Interior | M7: =IF(Despachos[[#This Row],[N° Reclamo]]=3, "SR","") | N7: =COUNTIF($S$2:$S$12, Despachos[[#This Row],[N° Reclamo]]) -> 0 | S7: 100951794 | T7: BANCO NACION | U7: 4305 | V7: Av. Constitucion 7598 | W7: Mar Del Plata | X7: 2350 CARREFOUR MAR DEL PLATA
A8: 200182745 | B8: 46080 | C8: 101161864 | D8: Salta | E8: Chavez, Rodrigo | F8: 044-32212821 | G8: Jet-Paq | I8: 46080 | L8: Interior | M8: =IF(Despachos[[#This Row],[N° Reclamo]]=3, "SR","") | N8: =COUNTIF($S$2:$S$12, Despachos[[#This Row],[N° Reclamo]]) -> 0 | S8: 100951784 | T8: BANCO NACION | U8: 7881 | V8: Avda. Edison 302 | W8: Mar Del Plata
A9: 200182716 | B9: 46080 | C9: 101161660 | D9: Mar del Plata | E9: Chiriello, Pablo Javier | F9: rto-00125572 | G9: Rabbione | I9: 46080 | L9: Atlántica | M9: =IF(Despachos[[#This Row],[N° Reclamo]]=3, "SR","") | N9: =COUNTIF($S$2:$S$12, Despachos[[#This Row],[N° Reclamo]]) -> 0 | S9: 100951697 | T9: BANCO NACION | U9: 19646 | V9: Av. Juan B. Justo 2035 | W9: Mar Del Plata | X9: 2350 YPF BASSO - entre las calles Buenos Aires y Tucuman
A10: 200182734 | B10: 46080 | C10: 0 | D10: Roque Sáenz Peña | E10: Dubina, Facundo Nicolas | F10: 6935P00132096 | G10: Flecha Bus | I10: 46080 | L10: Interior | M10: =IF(Despachos[[#This Row],[N° Reclamo]]=3, "SR","") | N10: =COUNTIF($S$2:$S$12, Despachos[[#This Row],[N° Reclamo]]) -> 0 | S10: 100951650 | T10: BANCO NACION | U10: 7876 | V10: Av. Libertad 3802 | W10: Mar Del Plata | X10: 9245 BARRIO LA PERLA
A11: 200182759 | B11: 46080 | C11: 0 | D11: San Nicolas | E11: Escanda, Benjamin | F11: 6935P00132100 | G11: Flecha Bus | I11: 46080 | L11: Interior | M11: =IF(Despachos[[#This Row],[N° Reclamo]]=3, "SR","") | N11: =COUNTIF($S$2:$S$12, Despachos[[#This Row],[N° Reclamo]]) -> 0 | S11: 100951646 | T11: BANCO NACION | U11: 9009 | V11: Av. Independencia 3617 | W11: Mar Del Plata
A12: 200182761 | B12: 46080 | C12: 0 | D12: La Rioja | E12: Flores, Rodrigo | F12: 6935P00132097 | G12: Flecha Bus | I12: 46080 | L12: Interior | M12: =IF(Despachos[[#This Row],[N° Reclamo]]=3, "SR","") | N12: =COUNTIF($S$2:$S$12, Despachos[[#This Row],[N° Reclamo]]) -> 0 | S12: 100951649 | T12: BANCO NACION | U12: 7946 | V12: Los Angeles 197 | W12: Santa Clara Del Mar | X12: 3325 SANTA CLARA DEL MAR
A13: 200182749 | B13: 46080 | C13: 101162414 | D13: Trenque Lauquen | E13: Garcia, Alejandro Javier | F13: 9007-00259556 | G13: Chevallier | I13: 46080 | L13: Oeste | M13: =IF(Despachos[[#This Row],[N° Reclamo]]=3, "SR","") | N13: =COUNTIF($S$2:$S$12, Despachos[[#This Row],[N° Reclamo]]) -> 0
A14: 200182738 | B14: 46080 | C14: 101162384 | D14: Santiago del Estero | E14: Gerez, Gabriel Omar | F14: 044-32212902 | G14: Jet-Paq | I14: 46080 | L14: Interior | M14: =IF(Despachos[[#This Row],[N° Reclamo]]=3, "SR","") | N14: =COUNTIF($S$2:$S$12, Despachos[[#This Row],[N° Reclamo]]) -> 0
A15: 200182737 | B15: 46080 | C15: 101162157 | D15: Trelew | E15: Godoy, Diego | F15: 044-32212880 | G15: Jet-Paq | I15: 46080 | L15: Sur | M15: =IF(Despachos[[#This Row],[N° Reclamo]]=3, "SR","") | N15: =COUNTIF($S$2:$S$12, Despachos[[#This Row],[N° Reclamo]]) -> 0 | P15: =COUNTIF($S$2:$S$12, C2) -> 0
A16: 200182755 | B16: 46080 | C16: 101162329 | D16: Trelew | E16: Godoy, Diego | F16: 044-32212880 | G16: Jet-Paq | I16: 46080 | L16: Sur | M16: =IF(Despachos[[#This Row],[N° Reclamo]]=3, "SR","") | N16: =COUNTIF($S$2:$S$12, Despachos[[#This Row],[N° Reclamo]]) -> 0
A17: 200182717 | B17: 46080 | C17: 0 | D17: Mendoza | E17: Gonzalez, Leonardo | F17: 044-32212891 | G17: Jet-Paq | I17: 46080 | L17: Interior | M17: =IF(Despachos[[#This Row],[N° Reclamo]]=3, "SR","") | N17: =COUNTIF($S$2:$S$12, Despachos[[#This Row],[N° Reclamo]]) -> 0
A18: 200182742 | B18: 46080 | C18: 101161687 | D18: Rosario | E18: Gorini, Carlos + Ramírez-Pérez-Bravo | F18: 6935P00132102 | G18: Flecha Bus | I18: 46080 | L18: Interior | M18: =IF(Despachos[[#This Row],[N° Reclamo]]=3, "SR","") | N18: =COUNTIF($S$2:$S$12, Despachos[[#This Row],[N° Reclamo]]) -> 0
A19: 200182741 | B19: 46080 | C19: 101143996 | D19: Rosario | E19: Gorini, Carlos + Ramírez-Pérez-Bravo | F19: 6935P00132102 | G19: Flecha Bus | I19: 46080 | L19: Interior | M19: =IF(Despachos[[#This Row],[N° Reclamo]]=3, "SR","") | N19: =COUNTIF($S$2:$S$12, Despachos[[#This Row],[N° Reclamo]]) -> 0
A20: 200182765 | B20: 46080 | C20: 0 | D20: Concordia | E20: Kolln, David | F20: 9007-00259554 | G20: Chevallier | I20: 46080 | L20: Interior | M20: =IF(Despachos[[#This Row],[N° Reclamo]]=3, "SR","") | N20: =COUNTIF($S$2:$S$12, Despachos[[#This Row],[N° Reclamo]]) -> 0
A21: 200182743 | B21: 46080 | C21: 101162230 | D21: Concordia | E21: Kolln, David | F21: 9007-00259554 | G21: Chevallier | I21: 46080 | L21: Interior | M21: =IF(Despachos[[#This Row],[N° Reclamo]]=3, "SR","") | N21: =COUNTIF($S$2:$S$12, Despachos[[#This Row],[N° Reclamo]]) -> 0
A22: 200182726 | B22: 46080 | C22: 2 | D22: S. M. Tucumán | E22: Lizardo, Ezequiel Rodolfo Jesús - Narvaja Hugo | F22: 044-32212913 | G22: Jet-Paq | I22: 46080 | L22: Interior | M22: =IF(Despachos[[#This Row],[N° Reclamo]]=3, "SR","") | N22: =COUNTIF($S$2:$S$12, Despachos[[#This Row],[N° Reclamo]]) -> 0
A23: 200182724 | B23: 46080 | C23: 2 | D23: S. M. Tucumán | E23: Lizardo, Ezequiel Rodolfo Jesús - Narvaja Hugo | F23: 044-32212913 | G23: Jet-Paq | I23: 46080 | L23: Interior | M23: =IF(Despachos[[#This Row],[N° Reclamo]]=3, "SR","") | N23: =COUNTIF($S$2:$S$12, Despachos[[#This Row],[N° Reclamo]]) -> 0
A24: 200182767 | B24: 46080 | C24: 2 | D24: La Rioja | E24: Loiza, Luis Rodolfo | F24: 6935P00132104 | G24: Flecha Bus | I24: 46080 | L24: Interior | M24: =IF(Despachos[[#This Row],[N° Reclamo]]=3, "SR","") | N24: =COUNTIF($S$2:$S$12, Despachos[[#This Row],[N° Reclamo]]) -> 0
A25: 200182766 | B25: 46080 | C25: 101160833 | D25: La Rioja | E25: Loiza, Luis Rodolfo | F25: 6935P00132104 | G25: Flecha Bus | I25: 46080 | L25: Interior | M25: =IF(Despachos[[#This Row],[N° Reclamo]]=3, "SR","") | N25: =COUNTIF($S$2:$S$12, Despachos[[#This Row],[N° Reclamo]]) -> 0
A26: 200182758 | B26: 46080 | C26: 0 | D26: Rosario | E26: Perez, Juan Manuel | F26: 6935P00132099 | G26: Flecha Bus | I26: 46080 | L26: Interior | M26: =IF(Despachos[[#This Row],[N° Reclamo]]=3, "SR","") | N26: =COUNTIF($S$2:$S$12, Despachos[[#This Row],[N° Reclamo]]) -> 0
A27: 200182740 | B27: 46080 | C27: 101162391 | D27: Chivilcoy | E27: Serrano, Damian Alejandro | F27: rto- 45-00125584 | G27: CHIVILCOY | I27: 46080 | L27: Interior | M27: =IF(Despachos[[#This Row],[N° Reclamo]]=3, "SR","") | N27: =COUNTIF($S$2:$S$12, Despachos[[#This Row],[N° Reclamo]]) -> 0
... A63: 200182688 | B63: 46079 | C63: 101162041 | D63: Mendoza | E63: Xavier, Hernan - lorca-Gonzalez-Bastias | F63: 044-32212434 | G63: Jet-Paq | I63: 46079 | L63: Interior | M63: =IF(Despachos[[#This Row],[N° Reclamo]]=3, "SR","") | N63: =COUNTIF($S$2:$S$12, Despachos[[#This Row],[N° Reclamo]]) -> 0
A64: 200182639 | B64: 46078 | C64: 101161708 | D64: Jujuy | E64: Albornoz, Claudio | G64: Jet-Paq | I64: 46078 | L64: Interior | M64: =IF(Despachos[[#This Row],[N° Reclamo]]=3, "SR","") | N64: =COUNTIF($S$2:$S$12, Despachos[[#This Row],[N° Reclamo]]) -> 0
A65: 200182650 | B65: 46078 | C65: 101161947 | D65: Jujuy | E65: Albornoz, Claudio | G65: Jet-Paq | I65: 46078 | L65: Interior | M65: =IF(Despachos[[#This Row],[N° Reclamo]]=3, "SR","") | N65: =COUNTIF($S$2:$S$12, Despachos[[#This Row],[N° Reclamo]]) -> 0
A66: 200182565 | B66: 46077 | C66: 101161279 | D66: Jujuy | E66: Avila, Julio | G66: Jet-Paq | I66: 46078 | L66: Interior | M66: =IF(Despachos[[#This Row],[N° Reclamo]]=3, "SR","") | N66: =COUNTIF($S$2:$S$12, Despachos[[#This Row],[N° Reclamo]]) -> 0
A67: 200182615 | B67: 46078 | C67: 2 | D67: Mendoza | E67: Bastias, Carlos Ignacio | G67: Jet-Paq | I67: 46078 | L67: Interior | M67: =IF(Despachos[[#This Row],[N° Reclamo]]=3, "SR","") | N67: =COUNTIF($S$2:$S$12, Despachos[[#This Row],[N° Reclamo]]) -> 0
A68: 200182640 | B68: 46078 | C68: 101157792 | D68: Posadas | E68: Batocletti, Segundo Domingo | G68: Jet-Paq | I68: 46078 | L68: Interior | M68: =IF(Despachos[[#This Row],[N° Reclamo]]=3, "SR","") | N68: =COUNTIF($S$2:$S$12, Despachos[[#This Row],[N° Reclamo]]) -> 0
A69: 200182608 | B69: 46078 | C69: 101157792 | D69: Posadas | E69: Batocletti, Segundo Domingo | G69: Jet-Paq | I69: 46078 | L69: Interior | M69: =IF(Despachos[[#This Row],[N° Reclamo]]=3, "SR","") | N69: =COUNTIF($S$2:$S$12, Despachos[[#This Row],[N° Reclamo]]) -> 0
A70: 200182646 | B70: 46078 | C70: 101161942 | D70: Gualeguaychú | E70: Boloque, Facundo Nicolas | G70: Chevallier | I70: 46078 | L70: Interior | M70: =IF(Despachos[[#This Row],[N° Reclamo]]=3, "SR","") | N70: =COUNTIF($S$2:$S$12, Despachos[[#This Row],[N° Reclamo]]) -> 0
A71: 200182593 | B71: 46078 | C71: 101161353 | D71: Córdoba | E71: Cano, Simon Eduardo | G71: Chevallier | I71: 46078 | L71: Interior | M71: =IF(Despachos[[#This Row],[N° Reclamo]]=3, "SR","") | N71: =COUNTIF($S$2:$S$12, Despachos[[#This Row],[N° Reclamo]]) -> 0
A72: 200182591 | B72: 46078 | C72: 1 | D72: Cordoba | E72: Cano, Simon Eduardo | G72: Chevallier | I72: 46078 | L72: Interior | M72: =IF(Despachos[[#This Row],[N° Reclamo]]=3, "SR","") | N72: =COUNTIF($S$2:$S$12, Despachos[[#This Row],[N° Reclamo]]) -> 0
A73: 200182614 | B73: 46078 | C73: 0 | D73: Roque Sáenz Peña | E73: Dubina, Facundo Nicolas | G73: Nuevo Expreso | I73: 46078 | L73: Interior | M73: =IF(Despachos[[#This Row],[N° Reclamo]]=3, "SR","") | N73: =COUNTIF($S$2:$S$12, Despachos[[#This Row],[N° Reclamo]]) -> 0
A74: 200182628 | B74: 46078 | C74: 0 | D74: Comodoro Rivadavia | E74: Gonzalez Cabrera, Antonio | G74: Jet-Paq | I74: 46078 | L74: Sur | M74: =IF(Despachos[[#This Row],[N° Reclamo]]=3, "SR","") | N74: =COUNTIF($S$2:$S$12, Despachos[[#This Row],[N° Reclamo]]) -> 0
A75: 200182594 | B75: 46078 | C75: 101161354 | D75: Córdoba | E75: Gonzalez Lopez, Raul Lionel | G75: Chevallier | I75: 46078 | L75: Interior | M75: =IF(Despachos[[#This Row],[N° Reclamo]]=3, "SR","") | N75: =COUNTIF($S$2:$S$12, Despachos[[#This Row],[N° Reclamo]]) -> 0
A76: 200182625 | B76: 46078 | C76: 2 | D76: S. M. Tucumán | E76: Lizardo, Ezequiel Rodolfo Jesús | G76: Jet-Paq | H76: Tarjeta YPF | I76: 46078 | L76: Interior | M76: =IF(Despachos[[#This Row],[N° Reclamo]]=3, "SR","") | N76: =COUNTIF($S$2:$S$12, Despachos[[#This Row],[N° Reclamo]]) -> 0
A77: 200182649 | B77: 46078 | C77: 101160833 | D77: La Rioja | E77: Loiza, Luis Rodolfo | G77: Flecha Bus | I77: 46078 | L77: Interior | M77: =IF(Despachos[[#This Row],[N° Reclamo]]=3, "SR","") | N77: =COUNTIF($S$2:$S$12, Despachos[[#This Row],[N° Reclamo]]) -> 0
A78: 200182630 | B78: 46078 | C78: 2 | D78: La Rioja | E78: Loiza, Luis Rodolfo | G78: Flecha Bus | I78: 46078 | L78: Interior | M78: =IF(Despachos[[#This Row],[N° Reclamo]]=3, "SR","") | N78: =COUNTIF($S$2:$S$12, Despachos[[#This Row],[N° Reclamo]]) -> 0
A79: 200182651 | B79: 46078 | C79: 101161956 | D79: Tartagal | E79: Lopez, Miguel Angel | G79: Via Bariloche | I79: 46078 | L79: Interior | M79: =IF(Despachos[[#This Row],[N° Reclamo]]=3, "SR","") | N79: =COUNTIF($S$2:$S$12, Despachos[[#This Row],[N° Reclamo]]) -> 0
A80: 200182596 | B80: 46078 | C80: 0 | D80: Goya | E80: Lopez, Sebastian | G80: Via Bariloche | I80: 46078 | L80: Interior | M80: =IF(Despachos[[#This Row],[N° Reclamo]]=3, "SR","") | N80: =COUNTIF($S$2:$S$12, Despachos[[#This Row],[N° Reclamo]]) -> 0
A81: 200182638 | B81: 46078 | C81: 101161401 | D81: Rio Cuarto | E81: Marin, Leandro Alexis | G81: Flecha Bus | I81: 46078 | L81: Interior | M81: =IF(Despachos[[#This Row],[N° Reclamo]]=3, "SR","") | N81: =COUNTIF($S$2:$S$12, Despachos[[#This Row],[N° Reclamo]]) -> 0
A82: 200182626 | B82: 46078 | C82: 0 | D82: Olavarría | E82: Martos, Jose Angel | G82: Plusmar | I82: 46078 | L82: Oeste | M82: =IF(Despachos[[#This Row],[N° Reclamo]]=3, "SR","") | N82: =COUNTIF($S$2:$S$12, Despachos[[#This Row],[N° Reclamo]]) -> 0
A83: 200182605 | B83: 46078 | C83: 101161452 | D83: Pinamar. | E83: Montiel, Juan Fernando | G83: Via Bariloche | H83: Tarjeta YPF | I83: 46078 | L83: Atlántica | M83: =IF(Despachos[[#This Row],[N° Reclamo]]=3, "SR","") | N83: =COUNTIF($S$2:$S$12, Despachos[[#This Row],[N° Reclamo]]) -> 0
A84: 200182647 | B84: 46078 | C84: 101161331 | D84: Córdoba | E84: Nicolai, Gustavo | G84: Chevallier | I84: 46078 | L84: Interior | M84: =IF(Despachos[[#This Row],[N° Reclamo]]=3, "SR","") | N84: =COUNTIF($S$2:$S$12, Despachos[[#This Row],[N° Reclamo]]) -> 0
A85: 200182611 | B85: 46078 | C85: 0 | D85: Junín | E85: Pagella, Emmanuel | G85: Chevallier | I85: 46078 | L85: Interior | M85: =IF(Despachos[[#This Row],[N° Reclamo]]=3, "SR","") | N85: =COUNTIF($S$2:$S$12, Despachos[[#This Row],[N° Reclamo]]) -> 0
A86: 200182606 | B86: 46078 | C86: 101161811 | D86: Chilvicoy | E86: Serrano, Damian Alejandro | G86: Chevallier | I86: 46078 | L86: Interior | M86: =IF(Despachos[[#This Row],[N° Reclamo]]=3, "SR","") | N86: =COUNTIF($S$2:$S$12, Despachos[[#This Row],[N° Reclamo]]) -> 0
A87: 200182621 | B87: 46078 | C87: 101161880 | D87: Chivilcoy | E87: Serrano, Damian Alejandro | G87: Chevallier | I87: 46078 | L87: Interior | M87: =IF(Despachos[[#This Row],[N° Reclamo]]=3, "SR","") | N87: =COUNTIF($S$2:$S$12, Despachos[[#This Row],[N° Reclamo]]) -> 0
A88: 200182595 | B88: 46078 | C88: 101161560 | D88: Resistencia | E88: Sikora, Gabriel Agustin | G88: Jet-Paq | I88: 46078 | L88: Interior | M88: =IF(Despachos[[#This Row],[N° Reclamo]]=3, "SR","") | N88: =COUNTIF($S$2:$S$12, Despachos[[#This Row],[N° Reclamo]]) -> 0
A89: 200182612 | B89: 46078 | C89: 101160154 | D89: Resistencia | E89: Traghetti, Axel Nahuel | G89: Jet-Paq | I89: 46078 | L89: Interior | M89: =IF(Despachos[[#This Row],[N° Reclamo]]=3, "SR","") | N89: =COUNTIF($S$2:$S$12, Despachos[[#This Row],[N° Reclamo]]) -> 0
A90: 200182623 | B90: 46078 | C90: 101160839 | D90: Resistencia | E90: Traghetti-Persoglia-Sikora | G90: Jet-Paq | I90: 46078 | L90: Interior | M90: =IF(Despachos[[#This Row],[N° Reclamo]]=3, "SR","") | N90: =COUNTIF($S$2:$S$12, Despachos[[#This Row],[N° Reclamo]]) -> 0
A91: 200182357 | B91: 46072 | C91: 0 | D91: Tandil | E91: Aldayturriaga, Martin | F91: 0489-00002430 | G91: La Estrella | I91: 46073 | L91: Oeste | M91: =IF(Despachos[[#This Row],[N° Reclamo]]=3, "SR","") | N91: =COUNTIF($S$2:$S$12, Despachos[[#This Row],[N° Reclamo]]) -> 0
A92: 200182415 | B92: 46073 | C92: 101160293 | D92: Santa Rosa | E92: Allende, Martin Leandro | F92: 9007-00259000/84 | G92: Chevallier | I92: 46073 | L92: La Pampa | M92: =IF(Despachos[[#This Row],[N° Reclamo]]=3, "SR","") | N92: =COUNTIF($S$2:$S$12, Despachos[[#This Row],[N° Reclamo]]) -> 0
A93: 200182414 | B93: 46073 | C93: 0 | D93: Santa Rosa | E93: Allende, Martin Leandro | F93: 9007-00259000/84 | G93: Chevallier | I93: 46073 | L93: La Pampa | M93: =IF(Despachos[[#This Row],[N° Reclamo]]=3, "SR","") | N93: =COUNTIF($S$2:$S$12, Despachos[[#This Row],[N° Reclamo]]) -> 0
A94: 200182363 | B94: 46072 | C94: 101160302 | D94: Santa Rosa | E94: Allende, Martin Leandro | F94: 9007-00259000/84 | G94: Chevallier | I94: 46073 | L94: La Pampa | M94: =IF(Despachos[[#This Row],[N° Reclamo]]=3, "SR","") | N94: =COUNTIF($S$2:$S$12, Despachos[[#This Row],[N° Reclamo]]) -> 0
A95: 200165487 | B95: 45706 | C95: 2 | D95: Rio Turbio. | E95: Barrera, Fernando Andrés | F95: 615210310 | G95: Cruz del Sur | I95: 46073 | L95: Contratistas | M95: =IF(Despachos[[#This Row],[N° Reclamo]]=3, "SR","") | N95: =COUNTIF($S$2:$S$12, Despachos[[#This Row],[N° Reclamo]]) -> 0
A96: 200182384 | B96: 46072 | C96: 1 | D96: Rio Turbio | E96: Barrera, Fernando Andrés | F96: 615210310 | G96: Cruz del Sur | I96: 46073 | L96: Contratistas | M96: =IF(Despachos[[#This Row],[N° Reclamo]]=3, "SR","") | N96: =COUNTIF($S$2:$S$12, Despachos[[#This Row],[N° Reclamo]]) -> 0
A97: 200182391 | B97: 46072 | C97: 101160548 | D97: Posadas | E97: Bastias, Carlos Ignacio | F97: 044-32210603 | G97: Jet-Paq | I97: 46073 | L97: Interior | M97: =IF(Despachos[[#This Row],[N° Reclamo]]=3, "SR","") | N97: =COUNTIF($S$2:$S$12, Despachos[[#This Row],[N° Reclamo]]) -> 0
A98: 200182450 | B98: 46073 | C98: 101157792 | D98: Posadas | E98: Batocletti, Segundo Domingo | F98: 044-32210570 | G98: Jet-Paq | I98: 46073 | L98: Interior | M98: =IF(Despachos[[#This Row],[N° Reclamo]]=3, "SR","") | N98: =COUNTIF($S$2:$S$12, Despachos[[#This Row],[N° Reclamo]]) -> 0
A99: 200182456 | B99: 46073 | C99: 1 | D99: Posadas. | E99: Batocletti, Segundo Domingo | F99: 044-32210570 | G99: Jet-Paq | I99: 46073 | L99: Interior | M99: =IF(Despachos[[#This Row],[N° Reclamo]]=3, "SR","") | N99: =COUNTIF($S$2:$S$12, Despachos[[#This Row],[N° Reclamo]]) -> 0 | R99: =Despachos[[#Totals],[27/2/2026]] -> 0
A100: 200182366 | B100: 46072 | C100: 101160485 | D100: San Rafael | E100: Benetti, Norman | F100: 1216287 | G100: Camionera Mendocina | I100: 46073 | L100: Interior | M100: =IF(Despachos[[#This Row],[N° Reclamo]]=3, "SR","") | N100: =COUNTIF($S$2:$S$12, Despachos[[#This Row],[N° Reclamo]]) -> 0
A101: 200182449 | B101: 46073 | C101: 101160827 | D101: San Rafael | E101: Benetti, Norman | F101: AS170125639 | G101: Andesmar | I101: 46073 | L101: Interior | M101: =IF(Despachos[[#This Row],[N° Reclamo]]=3, "SR","") | N101: =COUNTIF($S$2:$S$12, Despachos[[#This Row],[N° Reclamo]]) -> 0
A102: 200182389 | B102: 46072 | C102: 101160126 | D102: Gualeguaychú | E102: Boloque, Facundo Nicolas | F102: 9007-00259086 | G102: Chevallier | I102: 46073 | L102: Interior | M102: =IF(Despachos[[#This Row],[N° Reclamo]]=3, "SR","") | N102: =COUNTIF($S$2:$S$12, Despachos[[#This Row],[N° Reclamo]]) -> 0
A103: 200182435 | B103: 46073 | C103: 3 | D103: SR Mar del Plata | E103: Buratti-Chiriello-Deus-Castaño | F103: 6935P00131385 | G103: Flecha Bus | I103: 46073 | L103: Interior | M103: =IF(Despachos[[#This Row],[N° Reclamo]]=3, "SR","") -> SR | N103: =COUNTIF($S$2:$S$12, Despachos[[#This Row],[N° Reclamo]]) -> 0
A104: 200182349 | B104: 46071 | C104: 101156558 | D104: Córdoba | E104: Cano, Simon Eduardo | F104: 9007-00259001 | G104: Chevallier | I104: 46073 | L104: Interior | M104: =IF(Despachos[[#This Row],[N° Reclamo]]=3, "SR","") | N104: =COUNTIF($S$2:$S$12, Despachos[[#This Row],[N° Reclamo]]) -> 0
A105: 200182387 | B105: 46072 | C105: 101160493 | D105: Mar del Plata | E105: Castaño, Matias | F105: 6935P00131279 | G105: Flecha Bus | I105: 46073 | L105: Atlántica | M105: =IF(Despachos[[#This Row],[N° Reclamo]]=3, "SR","") | N105: =COUNTIF($S$2:$S$12, Despachos[[#This Row],[N° Reclamo]]) -> 0
A106: 200182352 | B106: 46071 | C106: 3 | D106: SR santa fe | E106: Cedermaz / Toro | F106: 6935P00131278 | G106: Flecha Bus | I106: 46073 | L106: Interior | M106: =IF(Despachos[[#This Row],[N° Reclamo]]=3, "SR","") -> SR | N106: =COUNTIF($S$2:$S$12, Despachos[[#This Row],[N° Reclamo]]) -> 0
A107: 200182408 | B107: 46072 | C107: 1 | D107: Mar del Plata. | E107: Chiriello, Pablo Javier | F107: 6935P00131387 | G107: Flecha Bus | I107: 46073 | L107: Atlántica | M107: =IF(Despachos[[#This Row],[N° Reclamo]]=3, "SR","") | N107: =COUNTIF($S$2:$S$12, Despachos[[#This Row],[N° Reclamo]]) -> 0
A108: 200182383 | B108: 46072 | C108: 1 | D108: Rio Grande | E108: Corti Victor | F108: 044-32210533 | G108: Jet-Paq | I108: 46073 | L108: Contratistas | M108: =IF(Despachos[[#This Row],[N° Reclamo]]=3, "SR","") | N108: =COUNTIF($S$2:$S$12, Despachos[[#This Row],[N° Reclamo]]) -> 0
A109: 200182370 | B109: 46072 | C109: 101160219 | D109: Roque S. Peña | E109: Dubina, Facundo Nicolas | F109: 9122-00002817 | G109: Nuevo Expreso | I109: 46073 | L109: Interior | M109: =IF(Despachos[[#This Row],[N° Reclamo]]=3, "SR","") | N109: =COUNTIF($S$2:$S$12, Despachos[[#This Row],[N° Reclamo]]) -> 0
A110: 200182359 | B110: 46072 | C110: 101144050 | D110: Roque Sáenz Peña | E110: Dubina, Facundo Nicolas | F110: 9122-00002817 | G110: Nuevo Expreso | I110: 46073 | L110: Interior | M110: =IF(Despachos[[#This Row],[N° Reclamo]]=3, "SR","") | N110: =COUNTIF($S$2:$S$12, Despachos[[#This Row],[N° Reclamo]]) -> 0
A111: 200182354 | B111: 46072 | C111: 0 | D111: Roque Sáenz Peña | E111: Dubina, Facundo Nicolas | F111: 6935P00131280 | G111: Flecha Bus | I111: 46073 | L111: Interior | M111: =IF(Despachos[[#This Row],[N° Reclamo]]=3, "SR","") | N111: =COUNTIF($S$2:$S$12, Despachos[[#This Row],[N° Reclamo]]) -> 0
A112: 200182413 | B112: 46073 | C112: 101146601 | D112: San Nicolas | E112: Escanda, Benjamin | F112: Rto.45-00125277 | G112: Magabo | I112: 46073 | L112: Interior | M112: =IF(Despachos[[#This Row],[N° Reclamo]]=3, "SR","") | N112: =COUNTIF($S$2:$S$12, Despachos[[#This Row],[N° Reclamo]]) -> 0
... A252: 200181875 | B252: 46057 | C252: 0 | D252: Viedma | E252: Vicente, Francisco Ariel | F252: FAB001200004621 | G252: Ceferino | I252: 46057 | L252: Centro | M252: =IF(Despachos[[#This Row],[N° Reclamo]]=3, "SR","") | N252: =COUNTIF($S$2:$S$12, Despachos[[#This Row],[N° Reclamo]]) -> 0
A253: 200181808 | B253: 46056 | C253: 101156509 | D253: Tandil | E253: Aldayturriaga, Martin | G253: La Estrella | I253: 46056 | L253: Oeste | M253: =IF(Despachos[[#This Row],[N° Reclamo]]=3, "SR","") | N253: =COUNTIF($S$2:$S$12, Despachos[[#This Row],[N° Reclamo]]) -> 0
A254: 200181820 | B254: 46056 | C254: 101155493 | D254: Posadas | E254: Batocletti, Segundo Domingo | G254: Jet-Paq | I254: 46056 | L254: Interior | M254: =IF(Despachos[[#This Row],[N° Reclamo]]=3, "SR","") | N254: =COUNTIF($S$2:$S$12, Despachos[[#This Row],[N° Reclamo]]) -> 0
A255: 200181811 | B255: 46056 | C255: 101156611 | D255: Rosario | E255: Bravo/Pérez/Gorini/Ramírez | G255: Flecha Bus | I255: 46056 | L255: Interior | M255: =IF(Despachos[[#This Row],[N° Reclamo]]=3, "SR","") | N255: =COUNTIF($S$2:$S$12, Despachos[[#This Row],[N° Reclamo]]) -> 0
A256: 200181797 | B256: 46056 | C256: 101156332 | D256: Santiago del Estero | E256: Caceres, Rodrigo | G256: Jet-Paq | I256: 46056 | L256: Interior | M256: =IF(Despachos[[#This Row],[N° Reclamo]]=3, "SR","") | N256: =COUNTIF($S$2:$S$12, Despachos[[#This Row],[N° Reclamo]]) -> 0
A257: 200181484 | B257: 46046 | C257: 0 | D257: Presidencia Roque Sáenz Peña | E257: Dubina, Facundo Nicolas | G257: Nuevo Expreso | I257: 46056 | L257: Interior | M257: =IF(Despachos[[#This Row],[N° Reclamo]]=3, "SR","") | N257: =COUNTIF($S$2:$S$12, Despachos[[#This Row],[N° Reclamo]]) -> 0
A258: 200181525 | B258: 46048 | C258: 0 | D258: La Rioja | E258: Flores, Rodrigo | G258: Flecha Bus | I258: 46056 | L258: Interior | M258: =IF(Despachos[[#This Row],[N° Reclamo]]=3, "SR","") | N258: =COUNTIF($S$2:$S$12, Despachos[[#This Row],[N° Reclamo]]) -> 0
A259: 200181819 | B259: 46056 | C259: 0 | D259: Comodoro Rivadavia | E259: Gonzalez Cabrera, Antonio | G259: Jet-Paq | I259: 46056 | L259: Sur | M259: =IF(Despachos[[#This Row],[N° Reclamo]]=3, "SR","") | N259: =COUNTIF($S$2:$S$12, Despachos[[#This Row],[N° Reclamo]]) -> 0
A260: 200181800 | B260: 46056 | C260: 0 | D260: Paraná | E260: Gonzalez, Ariel/Javier Toro | G260: Chevallier | I260: 46056 | L260: Interior | M260: =IF(Despachos[[#This Row],[N° Reclamo]]=3, "SR","") | N260: =COUNTIF($S$2:$S$12, Despachos[[#This Row],[N° Reclamo]]) -> 0
A261: 200179745 | B261: 46002 | C261: 1 | D261: Rosario | E261: Gorini, Carlos | G261: Flecha Bus | I261: 46056 | L261: Interior | M261: =IF(Despachos[[#This Row],[N° Reclamo]]=3, "SR","") | N261: =COUNTIF($S$2:$S$12, Despachos[[#This Row],[N° Reclamo]]) -> 0
A262: 200181794 | B262: 46056 | C262: 101156112 | D262: Rosario | E262: Gorini/Ramírez/Bravo/Pérez/ | G262: Flecha Bus | I262: 46056 | L262: Interior | M262: =IF(Despachos[[#This Row],[N° Reclamo]]=3, "SR","") | N262: =COUNTIF($S$2:$S$12, Despachos[[#This Row],[N° Reclamo]]) -> 0
A263: 200181687 | B263: 46052 | C263: 0 | D263: General Pico | E263: Hernandez, Marcos Alberto | G263: Chevallier | I263: 46056 | L263: La Pampa | M263: =IF(Despachos[[#This Row],[N° Reclamo]]=3, "SR","") | N263: =COUNTIF($S$2:$S$12, Despachos[[#This Row],[N° Reclamo]]) -> 0
A264: 200181823 | B264: 46056 | C264: 101156131 | D264: Córdoba | E264: Moralez, Pablo | G264: Chevallier | I264: 46056 | L264: Interior | M264: =IF(Despachos[[#This Row],[N° Reclamo]]=3, "SR","") | N264: =COUNTIF($S$2:$S$12, Despachos[[#This Row],[N° Reclamo]]) -> 0
... A270: 200181802 | B270: 46056 | C270: 101156426 | D270: Bahía Blanca | E270: Vicente, Francisco Ariel | G270: Plusmar | I270: 46056 | L270: Centro | M270: =IF(Despachos[[#This Row],[N° Reclamo]]=3, "SR","") | N270: =COUNTIF($S$2:$S$12, Despachos[[#This Row],[N° Reclamo]]) -> 0
A271: 200181777 | B271: 46055 | C271: 101143352 | D271: Santa Rosa | E271: Allende, Martin Leandro | F271: 9007-00258229 | G271: Chevallier | I271: 46055 | L271: La Pampa | M271: =IF(Despachos[[#This Row],[N° Reclamo]]=3, "SR","") | N271: =COUNTIF($S$2:$S$12, Despachos[[#This Row],[N° Reclamo]]) -> 0
A272: 200181782 | B272: 46055 | C272: 101154918 | D272: Posadas | E272: Batocletti, Segundo Domingo | F272: 044-32205913 | G272: Jet-Paq | I272: 46055 | L272: Interior | M272: =IF(Despachos[[#This Row],[N° Reclamo]]=3, "SR","") | N272: =COUNTIF($S$2:$S$12, Despachos[[#This Row],[N° Reclamo]]) -> 0
A273: 200181756 | B273: 46055 | C273: 101154939 | D273: Posadas | E273: Batocletti, Segundo Domingo | F273: 044-32205913 | G273: Jet-Paq | I273: 46055 | L273: Interior | M273: =IF(Despachos[[#This Row],[N° Reclamo]]=3, "SR","") | N273: =COUNTIF($S$2:$S$12, Despachos[[#This Row],[N° Reclamo]]) -> 0
A274: 200181781 | B274: 46055 | C274: 101155578 | D274: Gualeguaychú | E274: Boloque, Facundo Nicolas | F274: 9007-00258226 | G274: Chevallier | I274: 46055 | L274: Interior | M274: =IF(Despachos[[#This Row],[N° Reclamo]]=3, "SR","") | N274: =COUNTIF($S$2:$S$12, Despachos[[#This Row],[N° Reclamo]]) -> 0
A275: 200181730 | B275: 46052 | C275: 101154871 | D275: Salta | E275: Chavez, Rodrigo | F275: 044-32205961 | G275: Jet-Paq | I275: 46055 | L275: Interior | M275: =IF(Despachos[[#This Row],[N° Reclamo]]=3, "SR","") | N275: =COUNTIF($S$2:$S$12, Despachos[[#This Row],[N° Reclamo]]) -> 0
A276: 200181770 | B276: 46055 | C276: 101143364 | D276: Trenque Lauquen | E276: Garcia, Alejandro Javier | F276: 9007-00258230 | G276: Chevallier | I276: 46055 | L276: Oeste | M276: =IF(Despachos[[#This Row],[N° Reclamo]]=3, "SR","") | N276: =COUNTIF($S$2:$S$12, Despachos[[#This Row],[N° Reclamo]]) -> 0
A277: 200181745 | B277: 46055 | C277: 101148171 | D277: Comodoro Rivadavia | E277: Gonzalez Cabrera, Antonio | F277: 044-32205935 | G277: Jet-Paq | I277: 46055 | L277: Sur | M277: =IF(Despachos[[#This Row],[N° Reclamo]]=3, "SR","") | N277: =COUNTIF($S$2:$S$12, Despachos[[#This Row],[N° Reclamo]]) -> 0
A278: 200181742 | B278: 46055 | C278: 101155088 | D278: Neuquén | E278: Lazzaro, Leonardo | F278: 044-32205924 | G278: Jet-Paq | I278: 46055 | L278: Suroeste | M278: =IF(Despachos[[#This Row],[N° Reclamo]]=3, "SR","") | N278: =COUNTIF($S$2:$S$12, Despachos[[#This Row],[N° Reclamo]]) -> 0
A279: 200181729 | B279: 46052 | C279: 101155115 | D279: Neuquén | E279: Lazzaro, Leonardo | F279: 044-32205924 | G279: Jet-Paq | I279: 46055 | L279: Suroeste | M279: =IF(Despachos[[#This Row],[N° Reclamo]]=3, "SR","") | N279: =COUNTIF($S$2:$S$12, Despachos[[#This Row],[N° Reclamo]]) -> 0
...

Sheet Pendientes
A1: =Adicionales_2[[#Totals],[Luno]] -> 0 | T1: 30
A2: Pedido | B2: Cliente | C2: Luno | D2: Direccion | E2: Localidad | F2: Provincia | G2: Tec Zona | H2: F Alta | I2: Desc Problema | J2: Detalle Falla | K2: Modelo | L2: Año | M2: Antigüedad | N2: Zona Local | P2: No registra Asistencia | Q2: CTD | R2: Columna15 | T2: =COUNTIF(#REF!, Pendientes!#REF!) -> #REF!
O3: =CONCATENATE(Adicionales_2[[#This Row],[Cliente]]," ",Adicionales_2[[#This Row],[Luno]]) | P3: =IF(_xlfn.MAXIFS(Suspendidos[MARCA FIN], Suspendidos[ATM],Adicionales_2[[#This Row],[Luno]])=0, "No registra Asistencia",_xlfn.MAXIFS(Suspendidos[MARCA FIN], Suspendidos[ATM],Adicionales_2[[#This Row],[Luno]])) -> No registra Asistencia | Q3: =IF(ISNUMBER(FIND("BANCO", Adicionales_2[[#This Row],[Cliente]])), "ATM", IF(ISNUMBER(FIND("BAPRO", Adicionales_2[[#This Row],[Cliente]])), "ATM", "CTD")) -> CTD | R3: {=IF(IFERROR(_xlfn.IFS(Adicionales_2[[#This Row],[No registra Asistencia]]>Adicionales_2[[#This Row],[F Alta]],Adicionales_2[[#This Row],[No registra Asistencia]]-Adicionales_2[[#This Row],[F Alta]],Adicionales_2[[#This Row],[No registra Asistencia]]<Adicionales_2[[#This Row],[F Alta]],""),"")<$T$1,Adicionales_2[[#This Row],[No registra Asistencia]]-Adicionales_2[[#This Row],[F Alta]],"")}
A4: Total | C4: =SUBTOTAL(103,Adicionales_2[Luno]) -> 0

Sheet Resúmen técnicos
A1: Atlántica | F1: =(A4+C4+E4+G4) -> 5 | G1: SC | H1: =(A4+C4+E4+G4)/$A$22 -> 0.3125 | J1: Oeste | P1: SC | Q1: =(J4+L4+N4+P4)/$A$22 -> 0.25
A2: #VALUE! | C2: #VALUE! | E2: #VALUE! | G2: #VALUE! | J2: #VALUE! | L2: #VALUE! | N2: #VALUE! | S2: Preventivos totales
A3: SC | B3: MP | C3: SC | D3: MP | E3: SC | F3: MP | G3: SC | H3: MP | J3: SC | K3: MP | L3: SC | M3: MP | N3: SC | O3: MP | S3: % en cada caso: cerrados y abiertos
A4: =COUNTIFS(Asignados[Tec Asignado], Técnicos!$B$6, Asignados[Cpto Llamada], "SERVICE CALL") -> 1 | B4: =COUNTIFS(Asignados[Tec Asignado], Técnicos!$B$6, Asignados[Cpto Llamada], "<>SERVICE CALL") -> 2 | C4: =COUNTIFS(Asignados[Tec Asignado],Técnicos!$B$14, Asignados[Cpto Llamada], "SERVICE CALL") -> 1 | D4: =COUNTIFS(Asignados[Tec Asignado], Técnicos!$B$14, Asignados[Cpto Llamada], "<>SERVICE CALL") -> 0 | E4: =COUNTIFS(Asignados[Tec Asignado], Técnicos!$B$15, Asignados[Cpto Llamada], "SERVICE CALL") -> 3 | F4: =COUNTIFS(Asignados[Tec Asignado], Técnicos!$B$15, Asignados[Cpto Llamada], "<>SERVICE CALL") -> 1 | G4: =COUNTIFS(Asignados[Tec Asignado], Técnicos!$B$9, Asignados[Cpto Llamada], "SERVICE CALL") -> 0 | H4: =COUNTIFS(Asignados[Tec Asignado], Técnicos!$B$9, Asignados[Cpto Llamada], "<>SERVICE CALL") -> 0 | J4: =COUNTIFS(Asignados[Tec Asignado], Técnicos!$B$2, Asignados[Cpto Llamada], "SERVICE CALL") -> 1 | K4: =COUNTIFS(Asignados[Tec Asignado], Técnicos!$B$2, Asignados[Cpto Llamada], "<>SERVICE CALL") -> 2 | L4: =COUNTIFS(Asignados[Tec Asignado],Técnicos!$B$11, Asignados[Cpto Llamada], "SERVICE CALL") -> 2 | M4: =COUNTIFS(Asignados[Tec Asignado], Técnicos!$B$11, Asignados[Cpto Llamada], "<>SERVICE CALL") -> 0 | N4: =COUNTIFS(Asignados[Tec Asignado], Técnicos!$B$8, Asignados[Cpto Llamada], "SERVICE CALL") -> 1 | O4: =COUNTIFS(Asignados[Tec Asignado], Técnicos!$B$8, Asignados[Cpto Llamada], "<>SERVICE CALL") -> 5 | S4: SLA x vencer
A5: =SUM(A4:B4) -> 3 | C5: =SUM(C4:D4) -> 1 | E5: =SUM(E4:F4) -> 4 | G5: =SUM(G4:H4) -> 0 | J5: =SUM(J4:K4) -> 3 | L5: =SUM(L4:M4) -> 2 | N5: =SUM(N4:O4) -> 6
A7: Centro | G7: SC | H7: =(A10+C10+E10+G10)/$A$22 -> 0.25 | J7: La Pampa | P7: SC | Q7: =(J10+L10+N10+P10)/$A$22 -> 0
C8: #VALUE! | E8: #VALUE! | G8: #VALUE! | L8: #VALUE! | N8: #VALUE!
C9: SC | D9: MP | E9: SC | F9: MP | G9: SC | H9: MP | L9: SC | M9: MP | N9: SC | O9: MP
C10: =COUNTIFS(Asignados[Tec Asignado],Técnicos!$B$4, Asignados[Cpto Llamada], "SERVICE CALL") -> 4 | D10: =COUNTIFS(Asignados[Tec Asignado], Técnicos!$B$4, Asignados[Cpto Llamada], "<>SERVICE CALL") -> 2 | E10: =COUNTIFS(Asignados[Tec Asignado], Técnicos!$B$7, Asignados[Cpto Llamada], "SERVICE CALL") -> 0 | F10: =COUNTIFS(Asignados[Tec Asignado], Técnicos!$B$7, Asignados[Cpto Llamada], "<>SERVICE CALL") -> 0 | G10: =COUNTIFS(Asignados[Tec Asignado], Técnicos!$B$13, Asignados[Cpto Llamada], "SERVICE CALL") -> 0 | H10: =COUNTIFS(Asignados[Tec Asignado], Técnicos!$B$13, Asignados[Cpto Llamada], "<>SERVICE CALL") -> 0 | L10: =COUNTIFS(Asignados[Tec Asignado],Técnicos!$B$10, Asignados[Cpto Llamada], "SERVICE CALL") -> 0 | M10: =COUNTIFS(Asignados[Tec Asignado], Técnicos!$B$10, Asignados[Cpto Llamada], "<>SERVICE CALL") -> 1 | N10: =COUNTIFS(Asignados[Tec Asignado], Técnicos!$B$12, Asignados[Cpto Llamada], "SERVICE CALL") -> 0 | O10: =COUNTIFS(Asignados[Tec Asignado], Técnicos!$B$12, Asignados[Cpto Llamada], "<>SERVICE CALL") -> 1
C11: =SUM(C10:D10) -> 6 | E11: =SUM(E10:F10) -> 0 | G11: =SUM(G10:H10) -> 0 | L11: =SUM(L10:M10) -> 1 | N11: =SUM(N10:O10) -> 1
A13: Sur | G13: SC | H13: =(A16+C16+E16+G16)/$A$22 -> 0.1875 | J13: Contratistas | P13: SC | Q13: =(J16+L16+N16+P16)/$A$22 -> 0
C14: #VALUE! | E14: #VALUE! | J14: #VALUE! | L14: #VALUE! | N14: #VALUE!
C15: SC | D15: MP | E15: SC | F15: MP | J15: SC | K15: MP | L15: SC | M15: MP | N15: SC | O15: MP
C16: =COUNTIFS(Asignados[Tec Asignado],Técnicos!$B$3, Asignados[Cpto Llamada], "SERVICE CALL") -> 0 | D16: =COUNTIFS(Asignados[Tec Asignado], Técnicos!$B$3, Asignados[Cpto Llamada], "<>SERVICE CALL") -> 3 | E16: =COUNTIFS(Asignados[Tec Asignado], Técnicos!$B$5, Asignados[Cpto Llamada], "SERVICE CALL") -> 3 | F16: =COUNTIFS(Asignados[Tec Asignado], Técnicos!$B$5, Asignados[Cpto Llamada], "<>SERVICE CALL") -> 0 | J16: =COUNTIFS(Asignados[Tec Asignado],Técnicos!$B$19, Asignados[Cpto Llamada], "SERVICE CALL") -> 0 | K16: =COUNTIFS(Asignados[Tec Asignado], Técnicos!$B$19, Asignados[Cpto Llamada], "<>SERVICE CALL") -> 0 | L16: =COUNTIFS(Asignados[Tec Asignado],Técnicos!$B$18, Asignados[Cpto Llamada], "SERVICE CALL") -> 0 | M16: =COUNTIFS(Asignados[Tec Asignado], Técnicos!$B$18, Asignados[Cpto Llamada], "<>SERVICE CALL") -> 0 | N16: =COUNTIFS(Asignados[Tec Asignado], Técnicos!$B$17, Asignados[Cpto Llamada], "SERVICE CALL") -> 0 | O16: =COUNTIFS(Asignados[Tec Asignado], Técnicos!$B$17, Asignados[Cpto Llamada], "<>SERVICE CALL") -> 1
C17: =SUM(C16:D16) -> 3 | E17: =SUM(E16:F16) -> 3 | J17: =SUM(J16:K16) -> 0 | L17: =SUM(L16:M16) -> 0 | N17: =SUM(N16:O16) -> 1
A22: =COUNTIFS(Asignados[Cpto Llamada], "SERVICE CALL") -> 16

Sheet Técnicos
A1: Foto | B1: Nombre Flow | C1: Zona Local
A2: #VALUE! | B2: Garcia, Alejandro Javier | C2: Oeste
A3: #VALUE! | B3: Gonzalez Cabrera, Antonio | C3: Sur
A4: #VALUE! | B4: Pavon, Diego Emanuel | C4: Centro
A5: #VALUE! | B5: Godoy, Diego | C5: Sur
A6: #VALUE! | B6: Buratti, Fabian | C6: Atlántica
A7: #VALUE! | B7: Vicente, Francisco Ariel | C7: Centro
A8: #VALUE! | B8: Martos, Jose Angel | C8: Oeste
A9: #VALUE! | B9: Montiel, Juan Fernando | C9: Atlántica
A10: #VALUE! | B10: Hernandez, Marcos Alberto | C10: La Pampa
A11: #VALUE! | B11: Aldayturriaga, Martin | C11: Oeste
A12: #VALUE! | B12: Allende, Martin Leandro | C12: La Pampa
A13: #VALUE! | B13: Rodriguez, Mateo Joaquin | C13: Centro
... A22: #VALUE! | B22: Lazzaro, Leonardo | C22: Suroeste

Sheet Suspendidos Total
A1: PEDIDO | B1: CLIENTE | C1: ATM | D1: TECNICO ZONA | E1: TECNICO ASISTIO | F1: MARCA FIN | G1: OBSERVACIONES CONTROL | H1: PROBLEMA ENCONTRADO | I1: CONCEPTO LLAMADA | J1: ZONA LOCAL | K1: Fabricante | L1: MPCR | M1: ID
A2: 101162560 | B2: AEROPUERTOS ARGENTINA 2000 SA | C2: 007089005070 | D2: Gonzalez Cabrera, Antonio | E2: Gonzalez Cabrera, Antonio | F2: 46083 | G2: [01/03/2026] Se realiza revisión del equipo, se realiza limpieza y calibración de sensores queda sin fallas. Se realizan varios depósitos con sobres y billetes , todos exitosos_x000D_ // se realiza bne, retira atasco, reinicio, deposito, operativo_x000D_ solicita asistencia por atascos reiterados en los ultimos dias | H2: SMC-Error Recontadora | I2: SC | J2: Sur | K2: SNBC | L2: CTI90 SNBC | M2: AEROPUERTOS ARGENTINA 2000 SA 007089005070
A3: 101156445 | B3: SAIEP | C3: 004677004570 | D3: Corti Victor | E3: Corti Victor | F3: 46082 | G3: [28/02/2026] mantenimiento | H3: SMC-Mantenimiento Preventivo | I3: MTM | J3: Contratistas | K3: SNBC | L3: CTI90 SNBC | M3: SAIEP 004677004570
A4: 101156676 | B4: GMRA S.A (Samsung) | C4: 010377007470 | D4: Corti Victor | E4: Corti Victor | F4: 46082 | G4: [28/02/2026] mantenimiento | H4: SMC-Mantenimiento Preventivo | I4: MTM | J4: Contratistas | K4: SNBC | L4: CTI90 SNBC | M4: GMRA S.A (Samsung) 010377007470
A5: 101156437 | B5: SAIEP | C5: 004677013670 | D5: Corti Victor | E5: Corti Victor | F5: 46082 | G5: [28/02/2026] mantenimiento | H5: SMC-Mantenimiento Preventivo | I5: MTM | J5: Contratistas | K5: CIMA | L5: CIMA | M5: SAIEP 004677013670
A6: 101156444 | B6: SAIEP | C6: 004677002970 | D6: Corti Victor | E6: Corti Victor | F6: 46082 | G6: [28/02/2026] mantenimiento | H6: SMC-Mantenimiento Preventivo | I6: MTM | J6: Contratistas | K6: SNBC | L6: CTI90 SNBC | M6: SAIEP 004677002970
A7: 101156717 | B7: CARREFOUR | C7: 006624018270 | D7: Corti Victor | E7: Corti Victor | F7: 46082 | G7: [28/02/2026] mantenimiento | H7: SMC-Mantenimiento Preventivo | I7: MTM | J7: Contratistas | K7: SNBC | L7: CTI90 SNBC | M7: CARREFOUR 006624018270
A8: 101155919 | B8: ACA | C8: 002359058270 | D8: Corti Victor | E8: Corti Victor | F8: 46082 | G8: [28/02/2026] mantenimiento | H8: SMC-Mantenimiento Preventivo | I8: MTM | J8: Contratistas | K8: CIMA | L8: CIMA | M8: ACA 002359058270
A9: 101162635 | B9: BASES SA | C9: 010757000270 | D9: Lazzaro, Leonardo | E9: Ibañez, Pablo Fernando | F9: 46082 | G9: [28/02/2026] se cambió impresora CTI UL // Se dio de alta el Requerimiento 101162635-0. | H9: Impresora de cliente | I9: SC | J9: Suroeste | K9: SNBC | L9: CTI UL | M9: BASES SA 010757000270
A10: 101162242 | B10: BAPRO | C10: 8745 | D10: Pavon, Diego Emanuel | E10: Pavon, Diego Emanuel | F10: 46081 | G10: [27/02/2026] Se realizo ajuste de cableado de EPP. Se realizo chequeo de máster key. Se realizaron pruebas en diagnóstico y produccion con funcionario sin presentar fallas. ATM OPERATIVO | H10: Aceptador de Billetes | I10: SC | J10: Centro | K10: GRG | L10: GRG H34 | M10: BAPRO 8745
A11: 101156855 | B11: CENCOSUD S.A | C11: 008681061870 | D11: Montiel, Juan Fernando | E11: Montiel, Juan Fernando | F11: 46081 | G11: [27/02/2026] se realiza mantenimiento preventivo en el equipo se realizaron pruebas correspondientes | H11: SMC-Mantenimiento Preventivo | I11: MTM | J11: Atlántica | K11: SNBC | L11: CTE2 SNBC | M11: CENCOSUD S.A 008681061870
A12: 101144390 | B12: BANCO NACION | C12: 10072 | D12: Chiriello, Pablo Javier | E12: Chiriello, Pablo Javier | F12: 46081 | G12: [27/02/2026] se realizó mantenimiento preventivo | H12: Mantenimiento ATM | I12: MTM | J12: Atlántica | K12: GRG Banking | L12: GRG H22 | M12: BANCO NACION 10072
A13: 101144878 | B13: BANCO NACION | C13: 4111 | D13: Buratti, Fabian | E13: Buratti, Fabian | F13: 46081 | G13: [27/02/2026] diagnóstico pruebas y preventivo ok | H13: Mantenimiento ATM | I13: MTM | J13: Atlántica | K13: GRG Banking | L13: GRG H34 | M13: BANCO NACION 4111
... A20: 101162344 | B20: BAPRO | C20: 11369 | D20: Buratti, Fabian | E20: Castaño, Matias | F20: 46081 | G20: [27/02/2026] se repara modulo de depósito | H20: Aceptador de Billetes | I20: SC | J20: Atlántica | K20: GRG | L20: GRG H34 | M20: BAPRO 11369
A21: 101162201 | B21: RELEVAMIENTOS CASH TODAY | C21: Relevamiento PATAGONIA | D21: Hernandez, Marcos Alberto | E21: Hernandez, Marcos Alberto | F21: 46081 | G21: [27/02/2026] Se realizo relevamiento por movimiento de equipo dentro de la sucursal._x000D_ Se envía informe del mismo. | H21: Relevamiento ATM | I21: SC | J21: La Pampa | M21: RELEVAMIENTOS CASH TODAY Relevamiento PATAGONIA
A22: 101146579 | B22: BAPRO | C22: 5886 | D22: Aldayturriaga, Martin | E22: Aldayturriaga, Martin | F22: 46081 | G22: [27/02/2026] Se realiza mantenimiento preventivo | H22: Mantenimiento ATM | I22: MTM | J22: Oeste | K22: GRG Banking | L22: GRG H22 | M22: BAPRO 5886
A23: 101162414 | B23: BAPRO | C23: 11214 | D23: Garcia, Alejandro Javier | E23: Garcia, Alejandro Javier | F23: 46081 | G23: [27/02/2026] Se suspende por pedido de parte (falla de motor de stacker) | H23: Dispensador | I23: SC | J23: Oeste | K23: GRG | L23: GRG H34 | M23: BAPRO 11214
A24: 101162329 | B24: BANCO NACION | C24: 5060 | D24: Godoy, Diego | E24: Godoy, Diego | F24: 46081 | G24: [27/02/2026] Tecla de función en monitor en mal estado y trabada. Se realizan pruebas. Falla persiste. Se suspende por repuesto | H24: Monitor cliente | I24: SC | J24: Sur | K24: Diebold Nixdorf | L24: OPTEVA | M24: BANCO NACION 5060
A25: 101156439 | B25: SAIEP | C25: 004677016970 | D25: Corti Victor | E25: Corti Victor | F25: 46081 | G25: [28/02/2026] mantenimiento | H25: SMC-Mantenimiento Preventivo | I25: MTM | J25: Contratistas | K25: CIMA | L25: CIMA | M25: SAIEP 004677016970
A26: 101162484 | B26: CARREFOUR | C26: 006624021970 | D26: Ibañez, Pablo Fernando | E26: Ibañez, Pablo Fernando | F26: 46081 | G26: [28/02/2026] se actualizo billetes de 1000 // Se necesita asistencia de un tecnico, ya que la calibracion de los billetes solo se puede hacer desde el menu de la glory. Horario de 8 a 22. | H26: Software Configuración | I26: SC | J26: Suroeste | K26: GLORY | L26: GLORY P500 | M26: CARREFOUR 006624021970
A27: 101156382 | B27: SAIEP | C27: 004677025770 | D27: Ibañez, Pablo Fernando | E27: Ibañez, Pablo Fernando | F27: 46081 | G27: [28/02/2026] se realizo mantenimiento preventivo | H27: SMC-Mantenimiento Preventivo | I27: MTM | J27: Suroeste | K27: SNBC | L27: CTI90 SNBC | M27: SAIEP 004677025770
A28: 101156734 | B28: FRAVEGA | C28: 008383011870 | D28: Corti Victor | E28: Corti Victor | F28: 46081 | G28: [27/02/2026] mantenimiento | H28: SMC-Mantenimiento Preventivo | I28: MTM | J28: Contratistas | K28: SNBC | L28: CTI90 SNBC | M28: FRAVEGA 008383011870
A29: 101156733 | B29: FRAVEGA | C29: 008383006770 | D29: Ibañez, Pablo Fernando | E29: Ibañez, Pablo Fernando | F29: 46081 | G29: [27/02/2026] se realizo mantenimiento preventivo | H29: SMC-Mantenimiento Preventivo | I29: MTM | J29: Suroeste | K29: SNBC | L29: CTI90 SNBC | M29: FRAVEGA 008383006770
A30: 101156434 | B30: SAIEP | C30: 004677002870 | D30: Corti Victor | E30: Corti Victor | F30: 46081 | G30: [27/02/2026] mantenimiento | H30: SMC-Mantenimiento Preventivo | I30: MTM | J30: Contratistas | K30: CIMA | L30: CIMA | M30: SAIEP 004677002870
A31: 101162107 | B31: AEROPUERTOS DE NEUQUEN | C31: 009169000070 | D31: Lazzaro, Leonardo | E31: Ibañez, Pablo Fernando | F31: 46081 | G31: [27/02/2026] se cambió router y chips claro // [26/02/2026] se suspende por pedido de repuesto // Por favor verificar conectividad, no logramos conexión remota con el equipo pese a que el cliente reinició el router. | H31: SMC - Verificacion de conectividad | I31: SC | J31: Suroeste | K31: SNBC | L31: CTI90 SNBC | M31: AEROPUERTOS DE NEUQUEN 009169000070
A32: 101162471 | B32: DISTRIBUIDORA DEL VALLE | C32: 003841000070 | D32: Godoy, Diego | E32: Godoy, Diego | F32: 46081 | G32: [27/02/2026] Fuente de AIO quemada. Se cambió fuente de AIO. se realizó prueba de depósito de efectivo con cliente. Prueba EXITOSA. Equipo operativo y en servicio | H32: Fuente PC | I32: SC | J32: Sur | K32: Prosegur | L32: TAS | M32: DISTRIBUIDORA DEL VALLE 003841000070
A33: 101162463 | B33: BANCO LA PAMPA | C33: 24 | D33: Hernandez, Marcos Alberto | E33: Hernandez, Marcos Alberto | F33: 46081 | G33: [27/02/2026] Se realizo reparación de lectora de tarjetas._x000D_ Se realizo prueba en diagnostico sin presentar fallas._x000D_ Se realizo prueba en servicio junto al funcionario sin presentar fallas. | H33: Lectora de tarjetas | I33: SC | J33: La Pampa | K33: Diebold Nixdorf | L33: OPTEVA | M33: BANCO LA PAMPA 24
... A50: 101162137 | B50: BANCO CREDICOOP | C50: 808971 | D50: Buratti, Fabian | E50: Chiriello, Pablo Javier | F50: 46080 | G50: [26/02/2026] se acomodó, precintó y conectó cableado de lectora. pruebas de diagnóstico y de servicio ok | H50: Lectora de tarjetas | I50: SC | J50: Atlántica | K50: GRG | L50: GRG H34 | M50: BANCO CREDICOOP 808971
A51: 101162081 | B51: RELEVAMIENTOS CASH TODAY | C51: Relevamiento PATAGONIA | D51: Hernandez, Marcos Alberto | E51: Pavon, Diego Emanuel | F51: 46080 | G51: [27/02/2026] Se realizo relevamiento por desisntalacion de terminal. Se enviará correo con el informe detallado a la cadena de mails. | H51: Relevamiento ATM | I51: SC | J51: La Pampa | M51: RELEVAMIENTOS CASH TODAY Relevamiento PATAGONIA
A52: 101156817 | B52: CENCOSUD S.A | C52: 008681061770 | D52: Montiel, Juan Fernando | E52: Buratti, Fabian | F52: 46080 | G52: [26/02/2026] diagnóstico pruebas y preventivo ok | H52: SMC-Mantenimiento Preventivo | I52: MTM | J52: Atlántica | K52: SNBC | L52: CTE2 SNBC | M52: CENCOSUD S.A 008681061770
A53: 101162228 | B53: BAPRO | C53: 8648 | D53: Vicente, Francisco Ariel | E53: Vicente, Francisco Ariel | F53: 46080 | G53: [26/02/2026] se solicita repuesto. | H53: Dispensador | I53: SC | J53: Centro | K53: GRG Banking | L53: GRG H22 | M53: BAPRO 8648
A54: 101157002 | B54: FAST FOOD SUDAMERICANA S.A | C54: 008415011370 | D54: Montiel, Juan Fernando | E54: Montiel, Juan Fernando | F54: 46080 | G54: [27/02/2026] se realiza mantenimiento preventivo en el equipo se realizaron pruebas correspondientes | H54: SMC-Mantenimiento Preventivo | I54: MTM | J54: Atlántica | K54: SNBC | L54: CTI90 SNBC | M54: FAST FOOD SUDAMERICANA S.A 008415011370
A55: 101161784 | B55: CREDIGUIA | C55: 007563001570 | D55: Ibañez, Pablo Fernando | E55: Ibañez, Pablo Fernando | F55: 46080 | G55: [27/02/2026] se reparto sensores puerta tesoro // Caudales pasa la guardia para 26/2_x000D_ [25/02/2026] se suspende por que se requiere presencia de UB_x000D_ 8 // 101161784-0. | H55: SMC-Placa / Sensores / Percha | I55: SC | J55: Suroeste | K55: SNBC | L55: CTI UL | M55: CREDIGUIA 007563001570
A56: 101146090 | B56: BAPRO | C56: 4638 | D56: Vicente, Francisco Ariel | E56: Vicente, Francisco Ariel | F56: 46080 | G56: [27/02/2026] se realizó mantenimiento preventivo correspondiente | H56: Mantenimiento ATM | I56: MTM | J56: Centro | K56: GRG | L56: GRG H34 | M56: BAPRO 4638
A57: 101162244 | B57: BANCO LA PAMPA | C57: 77 | D57: Martos, Jose Angel | E57: Martos, Jose Angel | F57: 46080 | G57: [27/02/2026] limpieza y calibracion del modulo ena._x000D_ modulo probado en produccion junto al funcionario._x000D_ equipo operativo | H57: Aceptador de Billetes | I57: SC | J57: Oeste | K57: Diebold Nixdorf | L57: OPTEVA MI | M57: BANCO LA PAMPA 77
A58: 101161300 | B58: BAPRO | C58: 8604 | D58: Montiel, Juan Fernando | E58: Montiel, Juan Fernando | F58: 46080 | G58: [27/02/2026] se solucionó problema en modulo de depósito se realizaron pruebas correspondientes con funcionario // [24/02/2026] se suspende pedido por solicitud de repuestos | H58: Aceptador de Billetes | I58: SC | J58: Atlántica | K58: GRG | L58: GRG H34 | M58: BAPRO 8604
A59: 101162211 | B59: CARREFOUR | C59: 006624021970 | D59: Ibañez, Pablo Fernando | E59: Ruejas, Nelson | F59: 46080 | G59: [27/02/2026] reparacion de scrow y reseteo de memoria ram,pruebas ok. // el equipo se tilda constantemente lo que hace imposible poder realizar una verificacion remota sin tener que estar reiniciando todo el tiempo | H59: SMC-Billetes Atascados | I59: SC | J59: Suroeste | K59: GLORY | L59: GLORY P500 | M59: CARREFOUR 006624021970
A60: 101144842 | B60: BANCO NACION | C60: 4112 | D60: Chiriello, Pablo Javier | E60: Chiriello, Pablo Javier | F60: 46080 | G60: [27/02/2026] se realizó mantenimiento preventivo | H60: Mantenimiento ATM | I60: MTM | J60: Atlántica | K60: GRG | L60: GRG H34 | M60: BANCO NACION 4112
A61: 101146555 | B61: BAPRO | C61: 11163 | D61: Garcia, Alejandro Javier | E61: Garcia, Alejandro Javier | F61: 46080 | G61: [27/02/2026] Mantenimiento preventivo. Pruebas en servicio quedan a cargo de funcionario cuando pueda volver a cargar el ATM | H61: Mantenimiento ATM | I61: MTM | J61: Oeste | K61: GRG | L61: GRG H34 | M61: BAPRO 11163
A62: 101162228 | B62: BAPRO | C62: 8648 | D62: Vicente, Francisco Ariel | E62: Vicente, Francisco Ariel | F62: 46080 | G62: [27/02/2026] se soldó ficha de datos de modulo dispensador. modulo probado en producción con funcionario // [26/02/2026] se solicita repuesto. | H62: Dispensador | I62: SC | J62: Centro | K62: GRG Banking | L62: GRG H22 | M62: BAPRO 8648
A63: 101162145 | B63: BANCO NACION | C63: 10508 | D63: Ibañez, Pablo Fernando | E63: Ibañez, Pablo Fernando | F63: 46080 | G63: [27/02/2026] se cambió consumibles dispensador _x000D_ pruebas ok con funcionario | H63: Dispensador | I63: SC | J63: Suroeste | K63: Diebold Nixdorf | L63: OPTEVA MI | M63: BANCO NACION 10508
... A267: 101156414 | B267: SAIEP | C267: 004677006170 | D267: Foschi, Alejandro | E267: Foschi, Alejandro | F267: 46072 | G267: [19/02/2026] mantenimiento preventivo | H267: SMC-Mantenimiento Preventivo | I267: MTM | J267: Contratistas | K267: SNBC | L267: CTI90 SNBC | M267: SAIEP 004677006170
A268: 101156786 | B268: CENCOSUD S.A | C268: 008681016470 | D268: Ibañez, Pablo Fernando | E268: Ruejas, Nelson | F268: 46072 | G268: [19/02/2026] se suspende por no tener permiso de la entidad | I268: MTM | J268: Suroeste | K268: GLORY | L268: GLORY P500 | M268: CENCOSUD S.A 008681016470
A269: 101155892 | B269: ACA | C269: 002359060370 | D269: Ibañez, Pablo Fernando | E269: Ibañez, Pablo Fernando | F269: 46072 | G269: [19/02/2026] se realizó mantenimiento preventivo | H269: SMC-Mantenimiento Preventivo | I269: MTM | J269: Suroeste | K269: CIMA | L269: CIMA | M269: ACA 002359060370
A270: 101143251 | B270: BANCO LA PAMPA | C270: 30 | D270: Allende, Martin Leandro | E270: Allende, Martin Leandro | F270: 46072 | G270: [19/02/2026] Suspende por demora en ingreso y reprogramación de visita. | H270: Mantenimiento ATM | I270: MTM | J270: La Pampa | K270: Diebold Nixdorf | L270: OPTEVA | M270: BANCO LA PAMPA 30
A271: 101159576 | B271: BANCO LA PAMPA | C271: 87 | D271: Hernandez, Marcos Alberto | E271: Hernandez, Marcos Alberto | F271: 46072 | G271: [19/02/2026] Se reemplazo impresora de recibos._x000D_ Se realizaron pruebas en diagnostico sin presentar fallas._x000D_ Se realizaron pruebas em servicio sin presentar fallas. | H271: Impresora de cliente | I271: SC | J271: La Pampa | K271: DIEBOLD NIXDORF | L271: CS2070 | M271: BANCO LA PAMPA 87
A272: 101160385 | B272: FAVANET | C272: 004925003470 | D272: Pavon, Diego Emanuel | E272: Pavon, Diego Emanuel | F272: 46072 | G272: [19/02/2026] Se realizo conexion de MAE. Se suspende pedido por colocación de bolsa (disponibilidad de caudales) | H272: Instalacion | I272: INST | J272: Centro | K272: SNBC | L272: CTI UL | M272: FAVANET 004925003470
A273: 101160302 | B273: BANCO LA PAMPA | C273: 30 | D273: Allende, Martin Leandro | E273: Allende, Martin Leandro | F273: 46072 | G273: [19/02/2026] Suspende por pedido de parte (CardCage). | H273: Falla de Pc Card Cage | I273: SC | J273: La Pampa | K273: Diebold Nixdorf | L273: OPTEVA | M273: BANCO LA PAMPA 30
A274: 101157169 | B274: EMFACO S.A. | C274: 004395002070 | D274: Castaño, Matias | E274: Castaño, Matias | F274: 46072 | G274: [19/02/2026] se realiza mantenimiento preventivo | H274: SMC-Mantenimiento Preventivo | I274: MTM | J274: Atlántica | K274: CIMA | L274: CIMA | M274: EMFACO S.A. 004395002070
A275: 101160185 | B275: BANCO HIPOTECARIO | C275: 015TI0002 | D275: Buratti, Fabian | E275: Buratti, Fabian | F275: 46072 | G275: [19/02/2026] se realiza calibrado de sensores y se repara sensor de CI qué generaba fallas aleatorias. Pruebas en diagnostico con billetes de prueba ok. Tas ok // [18/02/2026] suspendo por pedido de repuesto DOR y error recurrente. | H275: Aceptador de Billetes | I275: SC | J275: Atlántica | K275: Diebold Nixdorf | L275: TAS MI | M275: BANCO HIPOTECARIO 015TI0002
A276: 101160208 | B276: BAPRO | C276: 8233 | D276: Chiriello, Pablo Javier | E276: Chiriello, Pablo Javier | F276: 46072 | G276: [19/02/2026] problema.con USB. se cambió de puerto y se calibró touch. Pruebas de diagnóstico y de servicio ok | H276: Touch Screen | I276: SC | J276: Atlántica | K276: GRG Banking | L276: GRG H22 | M276: BAPRO 8233
A277: 101156378 | B277: SAIEP | C277: 004677001570 | D277: Ibañez, Pablo Fernando | E277: Ruejas, Nelson | F277: 46072 | G277: [19/02/2026] realizacion del mantenimiento preventivo del 28/2 | H277: SMC-Mantenimiento Preventivo | I277: MTM | J277: Suroeste | K277: SNBC | L277: CTI90 SNBC | M277: SAIEP 004677001570
A278: 101160328 | B278: ACA | C278: 002359060370 | D278: Ibañez, Pablo Fernando | E278: Ibañez, Pablo Fernando | F278: 46072 | G278: [19/02/2026] se limpio y reguló sensores deposito // 101160328-0. | H278: SMC-Billetes Atascados | I278: SC | J278: Suroeste | K278: CIMA | L278: CIMA | M278: ACA 002359060370
A279: 101160340 | B279: BANCO CREDICOOP | C279: 813631 | D279: Aldayturriaga, Martin | E279: Aldayturriaga, Martin | F279: 46072 | G279: [19/02/2026] Se realiza cambio de una gaveta de $2.000 la misma se deja funcionando en el ATM, se verifica el correcto funcionamiento de todos los módulos del ATM, se realizaron pruebas en producción en presencia de funcionario | H279: Depósito de sobre | I279: SC | J279: Oeste | K279: Diebold Nixdorf | L279: OPTEVA MI | M279: BANCO CREDICOOP 813631
A280: 101145365 | B280: BANCO NACION | C280: 5067 | D280: Allende, Martin Leandro | E280: Allende, Martin Leandro | F280: 46071 | G280: [18/02/2026] Se realizó mantenimiento preventivo. Se realizaron pruebas en diagnóstico y producción sin fallas. // [15/01/2026] Suspende por falta de personal en sucursal. | H280: Mantenimiento ATM | I280: MTM | J280: La Pampa | K280: Diebold Nixdorf | L280: OPTEVA | M280: BANCO NACION 5067
... A318: 101159409 | B318: BAPRO | C318: 8288 | D318: Garcia, Alejandro Javier | E318: Hernandez, Marcos Alberto | F318: 46067 | G318: [13/02/2026] Se reemplazo escrow de modulo CAM._x000D_ Se realizaron pruebas en diagnostico sin presentar fallas._x000D_ Se realizaron pruebas en servicio junto al tesorero sin presentar fallas. | H318: Aceptador de Billetes | I318: SC | J318: Oeste | K318: GRG | L318: GRG H34 | M318: BAPRO 8288
A319: 101159533 | B319: RELEVAMIENTOS CASH TODAY | C319: Relevamiento PATAGONIA | D319: Hernandez, Marcos Alberto | E319: Pavon, Diego Emanuel | F319: 46067 | G319: [14/02/2026] Se realizo relevaliento de MAE. Se envio el mismo a la cadena de mail correspondiente | H319: Relevamiento ATM | I319: SC | J319: La Pampa | M319: RELEVAMIENTOS CASH TODAY Relevamiento PATAGONIA
A320: 101159531 | B320: CARREFOUR | C320: 006624018970 | D320: Allende, Martin Leandro | E320: Allende, Martin Leandro | F320: 46067 | G320: [14/02/2026] Al momento de la visita técnica no se detecta mal funcionamiento de la terminal. Se realiza depósito con encargada sin fallas. | H320: Sin Fallas | I320: SC | J320: La Pampa | K320: SNBC | L320: CTE2 SNBC | M320: CARREFOUR 006624018970
A321: 101159456 | B321: GOYAIKE S.A.A.C.I.Y.F | C321: 002214003670 | D321: Montiel, Juan Fernando | E321: Montiel, Juan Fernando | F321: 46067 | G321: [13/02/2026] se realiza instalación de imagen base y aplicativo se realizaron pruebas correspondientes con personal de monitoreo y depósito de prueba con denominaciones varias // Se intenta reinstalar SP y FW pero resulta imposible por mala conectividad y lentitud del equipo, el mismo ademas, se ecuentra desactualizado, se deriva a campo para actualizar a la ultima version de Aleph (4.34) // El cliente llama por le sale escrow trabado , nos conectamos remotamente, se abre le escrow , se reinicia prueba en depositar y queda en espere por favor, se le indica que se fije los compartimientos dice que no hay nada, que le pase un trapito húmedo, depósito y le sale error y se queda tildada, se deriva a monitoreo _x000D_ Tel:1131454404 | H321: SMC – Remasterización | I321: SC | J321: Atlántica | K321: SNBC | L321: CTI UL | M321: GOYAIKE S.A.A.C.I.Y.F 002214003670
A322: 101157580 | B322: BANCO CREDICOOP | C322: 812051 | D322: Pavon, Diego Emanuel | E322: Pavon, Diego Emanuel | F322: 46067 | G322: [13/02/2026] Se realizo cambio de CI. Se realizaron pruebas en diagnóstico y producción con funcionario sin presentar fallas. ATM OPERATIVO // [12/02/2026] Se suspende pedido por solicitud de repuesto. // [11/02/2026] Se realizo cambio de UDD de modulo de depositos ENA. Se realizaron pruebas en diagnóstico y persiste falla. Se suspende pedido por repuesto de CI. // [09/02/2026] Se suspende pedido por solicitud de repuesto EDD | H322: Dispensador | I322: SC | J322: Centro | K322: Diebold Nixdorf | L322: OPTEVA MI | M322: BANCO CREDICOOP 812051
A323: 101159275 | B323: CORREDORES VIALES S.A | C323: 010253004870 | D323: Martos, Jose Angel | E323: Martos, Jose Angel | F323: 46067 | G323: [13/02/2026] se masterizo equipo 1._x000D_ prueba de depositos con el operador ok._x000D_ Equipo operativo // [12/02/2026] se suspende pedido por repuestos // sin conexión | H323: Falla en Software | I323: SC | J323: Oeste | K323: SNBC | L323: CTI90 SNBC | M323: CORREDORES VIALES S.A 010253004870
A324: 101159514 | B324: SAIEP | C324: 004677005270 | D324: Vicente, Francisco Ariel | E324: Vicente, Francisco Ariel | F324: 46067 | G324: [13/02/2026] se ajustó gancia de sensor desde placa arduino y se realizó actualización de firmawere de dicha placa. modulo aceptador de efectivo probado | H324: SMC-Placa / Sensores / Percha | I324: SC | J324: Centro | K324: SNBC | L324: CTI90 SNBC | M324: SAIEP 004677005270
A325: 101156508 | B325: PLANTA MAR DEL PLATA | C325: 4997 | D325: Castaño, Matias | E325: Castaño, Matias | F325: 46067 | G325: [13/02/2026] se realiza mantenimiento preventivo | H325: SMC-Mantenimiento Preventivo | I325: MTM | J325: Atlántica | K325: CIMA | L325: CIMA | M325: PLANTA MAR DEL PLATA 4997
A326: 101146821 | B326: BAPRO | C326: 8288 | D326: Garcia, Alejandro Javier | E326: Hernandez, Marcos Alberto | F326: 46067 | G326: [13/02/2026] Se realizo M. preventivo primer semestre 2026. | H326: Mantenimiento ATM | I326: MTM | J326: Oeste | K326: GRG | L326: GRG H34 | M326: BAPRO 8288
A327: 101159403 | B327: EL TEHUELCHE SACICI | C327: 009455000870 | D327: Gonzalez Cabrera, Antonio | E327: Gonzalez Cabrera, Antonio | F327: 46067 | G327: [13/02/2026] Se calibra sensor de presencia de bolsa y se reemplaza latabolsa, queda sin. fallas.Se efectuan varios depósitos, todos exitosos. // Se coordina con caudales_x000D_ 101159403-0. | H327: SMC-Placa / Sensores / Percha | I327: SC | J327: Sur | K327: SNBC | L327: CTI90 SNBC | M327: EL TEHUELCHE SACICI 009455000870
A328: 101156446 | B328: SAIEP | C328: 004677005270 | D328: Vicente, Francisco Ariel | E328: Vicente, Francisco Ariel | F328: 46067 | G328: [13/02/2026] se realizó mantenimiento preventivo correspondiente | H328: SMC-Mantenimiento Preventivo | I328: MTM | J328: Centro | K328: SNBC | L328: CTI90 SNBC | M328: SAIEP 004677005270
A329: 101159115 | B329: BAPRO | C329: 11090 | D329: Buratti, Fabian | E329: Montiel, Juan Fernando | F329: 46066 | G329: [12/02/2026] se solucionó problema en modulo de depósito y cableado de monitor se realizaron pruebas correspondientes con funcionario | H329: Aceptador de Billetes | I329: SC | J329: Atlántica | K329: GRG | L329: GRG H34 | M329: BAPRO 11090
A330: 101159103 | B330: BANCO LA PAMPA | C330: 33 | D330: Allende, Martin Leandro | E330: Allende, Martin Leandro | F330: 46066 | G330: [12/02/2026] Se reemplazó stacker y picker de módulo 2. Se realizaron pruebas en diagnóstico sin fallas. | H330: Dispensador | I330: SC | J330: La Pampa | K330: Diebold Nixdorf | L330: OPTEVA | M330: BANCO LA PAMPA 33
A331: 101143254 | B331: BANCO LA PAMPA | C331: 33 | D331: Allende, Martin Leandro | E331: Allende, Martin Leandro | F331: 46066 | G331: [12/02/2026] Se realizó mantenimiento preventivo. Se realizaron pruebas en diagnóstico sin fallas. | H331: Mantenimiento ATM | I331: MTM | J331: La Pampa | K331: Diebold Nixdorf | L331: OPTEVA | M331: BANCO LA PAMPA 33
... A651: 101145487 | B651: BANCO NACION | C651: 10452 | D651: Garcia, Alejandro Javier | E651: Garcia, Alejandro Javier | F651: 46057 | G651: [04/02/2026] Mantenimiento preventivo. _x000D_ Cambio de take away módulo 4._x000D_ Pruebas en servicio junto a funcionario exitosas | H651: Mantenimiento ATM | I651: MTM | J651: Oeste | K651: Diebold Nixdorf | L651: OPTEVA | M651: BANCO NACION 10452
A652: 101155601 | B652: PROSEGUR - CRP | C652: MardelPlata-001 | D652: Chiriello, Pablo Javier | E652: Chiriello, Pablo Javier | F652: 46056 | G652: [02/02/2026] se ajusto cableado de monitor. pruebas ok // _x000D_ El equipo CRP que funciona en nuestro sector se encuentra fuera de servicio porque no está efectuando la selección de sectores al presionar la pantalla táctil_x000D_ Quedamos a la espera de v. instrucciones para la resolución del inconveniente | H652: Monitor cliente | I652: SC | J652: Atlántica | M652: PROSEGUR - CRP MardelPlata-001
A653: 101142856 | B653: GOYAIKE S.A.A.C.I.Y.F | C653: 002214003670 | D653: Montiel, Juan Fernando | E653: Montiel, Juan Fernando | F653: 46056 | G653: [02/02/2026] se realiza mantenimiento preventivo en el equipo se realizaron pruebas correspondientes // [06/01/2026] se suspende pedido por local cerrado | H653: SMC-Mantenimiento Preventivo | I653: MTM | J653: Atlántica | K653: SNBC | L653: CTI UL | M653: GOYAIKE S.A.A.C.I.Y.F 002214003670
A654: 101155593 | B654: BANCO NACION | C654: 7745 | D654: Garcia, Alejandro Javier | E654: Garcia, Alejandro Javier | F654: 46056 | G654: [02/02/2026] Se reinstaló software Multivendor con JAM 11.0.0 por estar TTU sin opciones y no responder ante reinicios._x000D_ Pruebas en servicio junto a funcionario exitosas | H654: Monitor cliente | I654: SC | J654: Oeste | K654: GRG Banking | L654: GRG H22 | M654: BANCO NACION 7745
A655: 101156098 | B655: BANCO CREDICOOP | C655: 811831 | D655: Chiriello, Pablo Javier | E655: Castaño, Matias | F655: 46056 | G655: [03/02/2026] se suspende por no estar presente tesorero para abrir el cajero. | H655: Dispensador | I655: SC | J655: Atlántica | K655: Diebold Nixdorf | L655: OPTEVA | M655: BANCO CREDICOOP 811831
A656: 101155563 | B656: BAPRO | C656: 8541 | D656: Aldayturriaga, Martin | E656: Aldayturriaga, Martin | F656: 46056 | G656: [02/02/2026] Se realiza cambio de la placa IOboard, se realizaron pruebas en servicio con personal de la empresa | H656: Aceptador de Billetes | I656: SC | J656: Oeste | K656: GRG | L656: GRG H34 | M656: BAPRO 8541
A657: 101155574 | B657: BAPRO | C657: 6682 | D657: Pavon, Diego Emanuel | E657: Vicente, Francisco Ariel | F657: 46056 | G657: [02/02/2026] se realizó revisión completa de modulo dispensador. se borraron y se volvieron a cargar los tipos de cada gaveta. no se puedo hacer prueba en producción con funcionario ya que el equipo va a ser cargado el dia de mañana. | H657: Dispensador | I657: SC | J657: Centro | K657: GRG | L657: GRG H34 | M657: BAPRO 6682
A658: 101155689 | B658: BAPRO | C658: 11153 | D658: Pavon, Diego Emanuel | E658: Vicente, Francisco Ariel | F658: 46056 | G658: [02/02/2026] se colocaron correas del módulo dispensador salidas. se realizó calibración del módulo completo. se realizó prueba en producción con funcionario | H658: Dispensador | I658: SC | J658: Centro | K658: GRG | L658: GRG H34 | M658: BAPRO 11153
A659: 101155547 | B659: SAIEP | C659: 004677020170 | D659: Hernandez, Marcos Alberto | E659: Allende, Martin Leandro | F659: 46056 | G659: [02/02/2026] Se reiniciaron módem, y router. Se verificó conectividad con Mesa de Ayuda. Conexión OK. // Sin conexion con la maquina. _x000D_ | H659: Comunicaciones | I659: SC | J659: La Pampa | K659: SNBC | L659: CTI90 SNBC | M659: SAIEP 004677020170
A660: 101146808 | B660: BAPRO | C660: 11087 | D660: Pavon, Diego Emanuel | E660: Vicente, Francisco Ariel | F660: 46056 | G660: [02/02/2026] se realizó mantenimiento preventivo correspondiente | H660: Mantenimiento ATM | I660: MTM | J660: Centro | K660: GRG | L660: GRG H34 | M660: BAPRO 11087
A661: 101151405 | B661: MAGNANELLI S.A | C661: 010833000070 | D661: Aldayturriaga, Martin | E661: Aldayturriaga, Martin | F661: 46056 | G661: [02/02/2026] Se realiza cambio de la IO board, se realizaron pruebas en servicio con personal de la empresa // [26/01/2026] Se suspende pedido por solicitud de repuesto | H661: SMC-Placa / Sensores / Percha | I661: AIEC | J661: Oeste | K661: SNBC | L661: CTI90 SNBC | M661: MAGNANELLI S.A 010833000070
A662: 101143364 | B662: BANCO LA PAMPA | C662: 97 | D662: Garcia, Alejandro Javier | E662: Garcia, Alejandro Javier | F662: 46056 | G662: [02/02/2026] Se suspende por pedido de parte | H662: Mantenimiento ATM | I662: MTM | J662: Oeste | K662: DIEBOLD NIXDORF | L662: CS2070 | M662: BANCO LA PAMPA 97
A663: 101155556 | B663: BANCO CREDICOOP | C663: 808971 | D663: Buratti, Fabian | E663: Chiriello, Pablo Javier | F663: 46056 | G663: [02/02/2026] se desarmó módulo y submódulos, realizando limpieza de los mismos. se hicieron pruebas de diagnóstico y de servicio ok | H663: Aceptador de Billetes | I663: SC | J663: Atlántica | K663: GRG | L663: GRG H34 | M663: BANCO CREDICOOP 808971
A664: 101141874 | B664: ACA | C664: 002359017571 | D664: Rodriguez, Mateo Joaquin | E664: Martos, Jose Angel | F664: 46056 | G664: [02/02/2026] Se realizo MP._x000D_ prueba de depositos con el operador ok._x000D_ Equipo operativo | H664: SMC-Mantenimiento Preventivo | I664: MTM | J664: Centro | K664: SNBC | L664: CTI UL | M664: ACA 002359017571
... A833: 101145586 | B833: BANCO NACION | C833: 10273 | D833: Pavon, Diego Emanuel | E833: Pavon, Diego Emanuel | F833: 46050 | G833: [28/01/2026] Se realizo cambio de kit de friccion modulo picker nro 4. Se realizo mantenimiento preventivo OK Se realizaron pruebas en diagnóstico y producción con funcionario sin presentar fallas. ATM OPERATIVO | H833: Mantenimiento ATM | I833: MTM | J833: Centro | K833: Diebold Nixdorf | L833: OPTEVA | M833: BANCO NACION 10273
A834: 101154175 | B834: RELEVAMIENTOS CASH TODAY | C834: Relevamiento PATAGONIA | D834: Hernandez, Marcos Alberto | E834: Castaño, Matias | F834: 46050 | G834: [28/01/2026] relevamiento | H834: Relevamiento ATM | I834: SC | J834: La Pampa | M834: RELEVAMIENTOS CASH TODAY Relevamiento PATAGONIA
A835: 101154150 | B835: BANCO NACION | C835: 6041 | D835: Allende, Martin Leandro | E835: Allende, Martin Leandro | F835: 46050 | G835: [28/01/2026] Se retiró llave trabada en cerradura, se arregló el mecanismo de apertura de la gaveta de depósitos, y se entregó al funcionario dos llaves de la cerradura. ATM sin fallas. | H835: Aceptador de Billetes | I835: SC | J835: La Pampa | K835: GRG | L835: GRG H34 | M835: BANCO NACION 6041
A836: 101154275 | B836: BANCO LA PAMPA | C836: 87 | D836: Hernandez, Marcos Alberto | E836: Hernandez, Marcos Alberto | F836: 46050 | G836: [28/01/2026] Se realizo reparación de lectora de tarjetas._x000D_ Se realizo prueba en servicio junto al funcionario sin presentar fallas. | H836: Lectora de tarjetas | I836: SC | J836: La Pampa | K836: DIEBOLD NIXDORF | L836: CS2070 | M836: BANCO LA PAMPA 87
A837: 101154241 | B837: BANCO CREDICOOP | C837: 825431 | D837: Lazzaro, Leonardo | E837: Lazzaro, Leonardo | F837: 46050 | G837: [28/01/2026] cambio de correa de presentador. limpieza en general. pruebas de dispensador realizadas en diagnostico | H837: Dispensador | I837: SC | J837: Suroeste | K837: Diebold Nixdorf | L837: OPTEVA | M837: BANCO CREDICOOP 825431
A838: 101153941 | B838: FAVANET | C838: 004925004170 | D838: Castaño, Matias | E838: Castaño, Matias | F838: 46050 | G838: [27/01/2026] se realiza correct de cabezal // se abre scrow, se retira atasco, pero al probarlo nuevamente atasca, se abre nuevamente, se retira el atasco, se hace otra prueba y vuelve a ttabar pero esta vez el equipo tambien se tilda | H838: SMC-Error Recontadora | I838: SC | J838: Atlántica | K838: SNBC | L838: CTI90 SNBC | M838: FAVANET 004925004170
A839: 101153702 | B839: SAIEP | C839: 004677023970 | D839: Gonzalez Cabrera, Antonio | E839: Gonzalez Cabrera, Antonio | F839: 46050 | G839: [27/01/2026] Se reemplaza SIM y se verifica conexion con Monitoreo , conexión exitosa. // [26/01/2026] Se verifica conectividad del router, intentos sin éxito. Se apaga y enciende router sigue sin comunicaciones. Se contacta con el especialista Ariel Vassena y después de varias pruebas se solicita reemplazar el router. // se guia al cliente para reiniciar el router y revisar conexiónes pero el error persiste. | H839: Comunicaciones | I839: SC | J839: Sur | K839: SNBC | L839: CTI UL | M839: SAIEP 004677023970
A840: 101142169 | B840: MAXICONSUMO | C840: 003781000870 | D840: Castaño, Matias | E840: Chiriello, Pablo Javier | F840: 46050 | G840: [27/01/2026] se realizó mantenimiento preventivo | H840: SMC-Mantenimiento Preventivo | I840: MTM | J840: Atlántica | K840: GLORY | L840: GLORY P500 | M840: MAXICONSUMO 003781000870
A841: 101143357 | B841: BANCO LA PAMPA | C841: 87 | D841: Hernandez, Marcos Alberto | E841: Hernandez, Marcos Alberto | F841: 46050 | G841: [27/01/2026] Se realizo M. preventivo primer semestre 2026 | H841: Mantenimiento ATM | I841: MTM | J841: La Pampa | K841: DIEBOLD NIXDORF | L841: CS2070 | M841: BANCO LA PAMPA 87
A842: 101141823 | B842: ACA | C842: 002359010870 | D842: Corti Victor | E842: Corti Victor | F842: 46050 | G842: [27/01/2026] mantenimiento | H842: SMC-Mantenimiento Preventivo | I842: MTM | J842: Contratistas | K842: CIMA | L842: CIMA | M842: ACA 002359010870
A843: 101154184 | B843: BANCO NACION | C843: 7881 | D843: Chiriello, Pablo Javier | E843: Chiriello, Pablo Javier | F843: 46050 | G843: [28/01/2026] sin diferencia. se equiparó con sobrante del día anterior. (no hay faltante) // SLA 1 de 5 | H843: Sin Fallas | I843: SC | J843: Atlántica | K843: GRG Banking | L843: GRG H22 | M843: BANCO NACION 7881
A844: 101141999 | B844: SAIEP | C844: 004677006670 | D844: Gonzalez Cabrera, Antonio | E844: Gonzalez Cabrera, Antonio | F844: 46050 | G844: [27/01/2026] Se realizó Mantenimiento Preventivo del equipo. Se efectuan varios depósitos, todos exitosos. | H844: SMC-Mantenimiento Preventivo | I844: MTM | J844: Sur | K844: CIMA | L844: CIMA | M844: SAIEP 004677006670
A845: 101142478 | B845: SUPERMERCADOS TOLEDO S.A | C845: 004312003870 | D845: Castaño, Matias | E845: Chiriello, Pablo Javier | F845: 46049 | G845: [26/01/2026] se realizó mantenimiento preventivo | H845: SMC-Mantenimiento Preventivo | I845: MTM | J845: Atlántica | K845: SNBC | L845: CTE2 SNBC | M845: SUPERMERCADOS TOLEDO S.A 004312003870
A846: 101142267 | B846: FAST FOOD SUDAMERICANA S.A | C846: 008415005770 | D846: Castaño, Matias | E846: Chiriello, Pablo Javier | F846: 46049 | G846: [26/01/2026] se realizó mantenimiento preventivo | H846: SMC-Mantenimiento Preventivo | I846: MTM | J846: Atlántica | K846: SNBC | L846: CTI90 SNBC | M846: FAST FOOD SUDAMERICANA S.A 008415005770
... A950: 101142013 | B950: SAIEP | C950: 004677003270 | D950: Ibañez, Pablo Fernando | E950: Ibañez, Pablo Fernando | F950: 46045 | G950: [22/01/2026] se realizó mantenimiento preventivo | H950: SMC-Mantenimiento Preventivo | I950: MTM | J950: Suroeste | K950: SNBC | L950: CTI90 SNBC | M950: SAIEP 004677003270
A951: 101152177 | B951: PROSEGUR - CRP | C951: Ushuaia-001 | D951: Corti Victor | E951: Corti Victor | F951: 46045 | G951: [22/01/2026] se revisa control de acceso, encendido y conectividad, se detiva a especialista Santiago Falcon que actializo version del sistema y se realizan pruebas de funcionamiento. | H951: Desconexion de equipo | I951: SC | J951: Contratistas | M951: PROSEGUR - CRP Ushuaia-001
A952: 101146767 | B952: BAPRO | C952: 4788 | D952: Martos, Jose Angel | E952: Martos, Jose Angel | F952: 46045 | G952: [23/01/2026] Se realizo MP._x000D_ modulo probado en produccion junto al funcionario._x000D_ equipo operativo | H952: Mantenimiento ATM | I952: MTM | J952: Oeste | K952: GRG Banking | L952: GRG H22 | M952: BAPRO 4788
...

Sheet Suspendidos
A2: PEDIDO | B2: CLIENTE | C2: ATM | D2: TECNICO ZONA | E2: TECNICO ASISTIO | F2: MARCA FIN | G2: OBSERVACIONES CONTROL | H2: PROBLEMA ENCONTRADO | I2: CONCEPTO LLAMADA | J2: ZONA LOCAL | K2: Fabricante | L2: MPCR | M2: ID
A3: 101162560 | B3: AEROPUERTOS ARGENTINA 2000 SA | C3: 007089005070 | D3: Gonzalez Cabrera, Antonio | E3: Gonzalez Cabrera, Antonio | F3: 46083 | G3: [01/03/2026] Se realiza revisión del equipo, se realiza limpieza y calibración de sensores queda sin fallas. Se realizan varios depósitos con sobres y billetes , todos exitosos_x000D_ // se realiza bne, retira atasco, reinicio, deposito, operativo_x000D_ solicita asistencia por atascos reiterados en los ultimos dias | H3: SMC-Error Recontadora | I3: SERVICE CALL | J3: Sur | K3: SNBC | L3: CTI90 SNBC | M3: =CONCATENATE(Suspendidos[[#This Row],[CLIENTE]]," ",Suspendidos[[#This Row],[ATM]]) -> AEROPUERTOS ARGENTINA 2000 SA 007089005070
A4: 101162635 | B4: BASES SA | C4: 010757000270 | D4: Lazzaro, Leonardo | E4: Ibañez, Pablo Fernando | F4: 46082 | G4: [28/02/2026] se cambió impresora CTI UL // Se dio de alta el Requerimiento 101162635-0. | H4: Impresora de cliente | I4: SERVICE CALL | J4: Suroeste | K4: SNBC | L4: CTI UL | M4: =CONCATENATE(Suspendidos[[#This Row],[CLIENTE]]," ",Suspendidos[[#This Row],[ATM]]) -> BASES SA 010757000270
A5: 101162484 | B5: CARREFOUR | C5: 006624021970 | D5: Ibañez, Pablo Fernando | E5: Ibañez, Pablo Fernando | F5: 46081 | G5: [28/02/2026] se actualizo billetes de 1000 // Se necesita asistencia de un tecnico, ya que la calibracion de los billetes solo se puede hacer desde el menu de la glory. Horario de 8 a 22. | H5: Software Configuración | I5: SERVICE CALL | J5: Suroeste | K5: GLORY | L5: GLORY P500 | M5: =CONCATENATE(Suspendidos[[#This Row],[CLIENTE]]," ",Suspendidos[[#This Row],[ATM]]) -> CARREFOUR 006624021970
A6: 101162107 | B6: AEROPUERTOS DE NEUQUEN | C6: 009169000070 | D6: Lazzaro, Leonardo | E6: Ibañez, Pablo Fernando | F6: 46081 | G6: [27/02/2026] se cambió router y chips claro // [26/02/2026] se suspende por pedido de repuesto // Por favor verificar conectividad, no logramos conexión remota con el equipo pese a que el cliente reinició el router. | H6: SMC - Verificacion de conectividad | I6: SERVICE CALL | J6: Suroeste | K6: SNBC | L6: CTI90 SNBC | M6: =CONCATENATE(Suspendidos[[#This Row],[CLIENTE]]," ",Suspendidos[[#This Row],[ATM]]) -> AEROPUERTOS DE NEUQUEN 009169000070
A7: 101162471 | B7: DISTRIBUIDORA DEL VALLE | C7: 003841000070 | D7: Godoy, Diego | E7: Godoy, Diego | F7: 46081 | G7: [27/02/2026] Fuente de AIO quemada. Se cambió fuente de AIO. se realizó prueba de depósito de efectivo con cliente. Prueba EXITOSA. Equipo operativo y en servicio | H7: Fuente PC | I7: SERVICE CALL | J7: Sur | K7: Prosegur | L7: TAS | M7: =CONCATENATE(Suspendidos[[#This Row],[CLIENTE]]," ",Suspendidos[[#This Row],[ATM]]) -> DISTRIBUIDORA DEL VALLE 003841000070
A8: 101162463 | B8: BANCO LA PAMPA | C8: 24 | D8: Hernandez, Marcos Alberto | E8: Hernandez, Marcos Alberto | F8: 46081 | G8: [27/02/2026] Se realizo reparación de lectora de tarjetas._x000D_ Se realizo prueba en diagnostico sin presentar fallas._x000D_ Se realizo prueba en servicio junto al funcionario sin presentar fallas. | H8: Lectora de tarjetas | I8: SERVICE CALL | J8: La Pampa | K8: Diebold Nixdorf | L8: OPTEVA | M8: =CONCATENATE(Suspendidos[[#This Row],[CLIENTE]]," ",Suspendidos[[#This Row],[ATM]]) -> BANCO LA PAMPA 24
A9: 101162445 | B9: SEPSA | C9: 002201149370 | D9: Castaño, Matias | E9: Castaño, Matias | F9: 46081 | G9: [27/02/2026] se repara impresora de cliente // 101162445-0. | H9: Impresora de cliente | I9: SERVICE CALL | J9: Atlántica | K9: SNBC | L9: CTI UL | M9: =CONCATENATE(Suspendidos[[#This Row],[CLIENTE]]," ",Suspendidos[[#This Row],[ATM]]) -> SEPSA 002201149370
A10: 101162414 | B10: BAPRO | C10: 11214 | D10: Garcia, Alejandro Javier | E10: Garcia, Alejandro Javier | F10: 46081 | G10: [27/02/2026] Se suspende por pedido de parte (falla de motor de stacker) | H10: Dispensador | I10: SERVICE CALL | J10: Oeste | K10: GRG | L10: GRG H34 | M10: =CONCATENATE(Suspendidos[[#This Row],[CLIENTE]]," ",Suspendidos[[#This Row],[ATM]]) -> BAPRO 11214
A11: 101162329 | B11: BANCO NACION | C11: 5060 | D11: Godoy, Diego | E11: Godoy, Diego | F11: 46081 | G11: [27/02/2026] Tecla de función en monitor en mal estado y trabada. Se realizan pruebas. Falla persiste. Se suspende por repuesto | H11: Monitor cliente | I11: SERVICE CALL | J11: Sur | K11: Diebold Nixdorf | L11: OPTEVA | M11: =CONCATENATE(Suspendidos[[#This Row],[CLIENTE]]," ",Suspendidos[[#This Row],[ATM]]) -> BANCO NACION 5060
A12: 101162201 | B12: RELEVAMIENTOS CASH TODAY | C12: Relevamiento PATAGONIA | D12: Hernandez, Marcos Alberto | E12: Hernandez, Marcos Alberto | F12: 46081 | G12: [27/02/2026] Se realizo relevamiento por movimiento de equipo dentro de la sucursal._x000D_ Se envía informe del mismo. | H12: Relevamiento ATM | I12: SERVICE CALL | J12: La Pampa | M12: =CONCATENATE(Suspendidos[[#This Row],[CLIENTE]]," ",Suspendidos[[#This Row],[ATM]]) -> RELEVAMIENTOS CASH TODAY Relevamiento PATAGONIA
A13: 101162242 | B13: BAPRO | C13: 8745 | D13: Pavon, Diego Emanuel | E13: Pavon, Diego Emanuel | F13: 46081 | G13: [27/02/2026] Se realizo ajuste de cableado de EPP. Se realizo chequeo de máster key. Se realizaron pruebas en diagnóstico y produccion con funcionario sin presentar fallas. ATM OPERATIVO | H13: Aceptador de Billetes | I13: SERVICE CALL | J13: Centro | K13: GRG | L13: GRG H34 | M13: =CONCATENATE(Suspendidos[[#This Row],[CLIENTE]]," ",Suspendidos[[#This Row],[ATM]]) -> BAPRO 8745
A14: 101162157 | B14: BANCO CREDICOOP | C14: 814621 | D14: Godoy, Diego | E14: Godoy, Diego | F14: 46081 | G14: [27/02/2026] Se suspende por pedido de repuesto. Por recomendación de sector Especialista se solicita Shutter. | H14: Dispensador | I14: SERVICE CALL | J14: Sur | K14: GRG Banking | L14: GRG H22 | M14: =CONCATENATE(Suspendidos[[#This Row],[CLIENTE]]," ",Suspendidos[[#This Row],[ATM]]) -> BANCO CREDICOOP 814621
A15: 101162344 | B15: BAPRO | C15: 11369 | D15: Buratti, Fabian | E15: Castaño, Matias | F15: 46081 | G15: [27/02/2026] se repara modulo de depósito | H15: Aceptador de Billetes | I15: SERVICE CALL | J15: Atlántica | K15: GRG | L15: GRG H34 | M15: =CONCATENATE(Suspendidos[[#This Row],[CLIENTE]]," ",Suspendidos[[#This Row],[ATM]]) -> BAPRO 11369
A16: 101162191 | B16: BANCO LA PAMPA | C16: 14101 | D16: Allende, Martin Leandro | E16: Hernandez, Marcos Alberto | F16: 46081 | G16: [27/02/2026] Se reemplazo escrow de CRM9250N_x000D_ Se eliminó atasco de billetes en sensor TP02._x000D_ Se realizaron pruebas de deposito y extraccion junto a clientes de la entidad sin presentar fallas. | H16: Dispensador | I16: SERVICE CALL | J16: La Pampa | K16: GRG | L16: GRG H68 | M16: =CONCATENATE(Suspendidos[[#This Row],[CLIENTE]]," ",Suspendidos[[#This Row],[ATM]]) -> BANCO LA PAMPA 14101
A17: 101161888 | B17: ACA | C17: 002359012671 | D17: Aldayturriaga, Martin | E17: Aldayturriaga, Martin | F17: 46081 | G17: [27/02/2026] Se realiza calibración del sensor de presencia de bolsa, se realizaron pruebas en producción con personal de la empresa // A coordinar con UB | H17: SMC-Placa / Sensores / Percha | I17: SERVICE CALL | J17: Oeste | K17: SNBC | L17: CTI UL | M17: =CONCATENATE(Suspendidos[[#This Row],[CLIENTE]]," ",Suspendidos[[#This Row],[ATM]]) -> ACA 002359012671
A18: 101161784 | B18: CREDIGUIA | C18: 007563001570 | D18: Ibañez, Pablo Fernando | E18: Ibañez, Pablo Fernando | F18: 46080 | G18: [27/02/2026] se reparto sensores puerta tesoro // Caudales pasa la guardia para 26/2_x000D_ [25/02/2026] se suspende por que se requiere presencia de UB_x000D_ 8 // 101161784-0. | H18: SMC-Placa / Sensores / Percha | I18: SERVICE CALL | J18: Suroeste | K18: SNBC | L18: CTI UL | M18: =CONCATENATE(Suspendidos[[#This Row],[CLIENTE]]," ",Suspendidos[[#This Row],[ATM]]) -> CREDIGUIA 007563001570
A19: 101162244 | B19: BANCO LA PAMPA | C19: 77 | D19: Martos, Jose Angel | E19: Martos, Jose Angel | F19: 46080 | G19: [27/02/2026] limpieza y calibracion del modulo ena._x000D_ modulo probado en produccion junto al funcionario._x000D_ equipo operativo | H19: Aceptador de Billetes | I19: SERVICE CALL | J19: Oeste | K19: Diebold Nixdorf | L19: OPTEVA MI | M19: =CONCATENATE(Suspendidos[[#This Row],[CLIENTE]]," ",Suspendidos[[#This Row],[ATM]]) -> BANCO LA PAMPA 77
A20: 101161300 | B20: BAPRO | C20: 8604 | D20: Montiel, Juan Fernando | E20: Montiel, Juan Fernando | F20: 46080 | G20: [27/02/2026] se solucionó problema en modulo de depósito se realizaron pruebas correspondientes con funcionario // [24/02/2026] se suspende pedido por solicitud de repuestos | H20: Aceptador de Billetes | I20: SERVICE CALL | J20: Atlántica | K20: GRG | L20: GRG H34 | M20: =CONCATENATE(Suspendidos[[#This Row],[CLIENTE]]," ",Suspendidos[[#This Row],[ATM]]) -> BAPRO 8604
A21: 101162211 | B21: CARREFOUR | C21: 006624021970 | D21: Ibañez, Pablo Fernando | E21: Ruejas, Nelson | F21: 46080 | G21: [27/02/2026] reparacion de scrow y reseteo de memoria ram,pruebas ok. // el equipo se tilda constantemente lo que hace imposible poder realizar una verificacion remota sin tener que estar reiniciando todo el tiempo | H21: SMC-Billetes Atascados | I21: SERVICE CALL | J21: Suroeste | K21: GLORY | L21: GLORY P500 | M21: =CONCATENATE(Suspendidos[[#This Row],[CLIENTE]]," ",Suspendidos[[#This Row],[ATM]]) -> CARREFOUR 006624021970
A22: 101162081 | B22: RELEVAMIENTOS CASH TODAY | C22: Relevamiento PATAGONIA | D22: Hernandez, Marcos Alberto | E22: Pavon, Diego Emanuel | F22: 46080 | G22: [27/02/2026] Se realizo relevamiento por desisntalacion de terminal. Se enviará correo con el informe detallado a la cadena de mails. | H22: Relevamiento ATM | I22: SERVICE CALL | J22: La Pampa | M22: =CONCATENATE(Suspendidos[[#This Row],[CLIENTE]]," ",Suspendidos[[#This Row],[ATM]]) -> RELEVAMIENTOS CASH TODAY Relevamiento PATAGONIA
A23: 101162228 | B23: BAPRO | C23: 8648 | D23: Vicente, Francisco Ariel | E23: Vicente, Francisco Ariel | F23: 46080 | G23: [27/02/2026] se soldó ficha de datos de modulo dispensador. modulo probado en producción con funcionario // [26/02/2026] se solicita repuesto. | H23: Dispensador | I23: SERVICE CALL | J23: Centro | K23: GRG Banking | L23: GRG H22 | M23: =CONCATENATE(Suspendidos[[#This Row],[CLIENTE]]," ",Suspendidos[[#This Row],[ATM]]) -> BAPRO 8648
A24: 101162145 | B24: BANCO NACION | C24: 10508 | D24: Ibañez, Pablo Fernando | E24: Ibañez, Pablo Fernando | F24: 46080 | G24: [27/02/2026] se cambió consumibles dispensador _x000D_ pruebas ok con funcionario | H24: Dispensador | I24: SERVICE CALL | J24: Suroeste | K24: Diebold Nixdorf | L24: OPTEVA MI | M24: =CONCATENATE(Suspendidos[[#This Row],[CLIENTE]]," ",Suspendidos[[#This Row],[ATM]]) -> BANCO NACION 10508
A25: 101161660 | B25: BAPRO | C25: 11347 | D25: Chiriello, Pablo Javier | E25: Chiriello, Pablo Javier | F25: 46080 | G25: [27/02/2026] se suspende por pedido de repuesto (monitor) // a coordinar con PDF | H25: Aceptador de Billetes | I25: SERVICE CALL | J25: Atlántica | K25: GRG Banking | L25: GRG H22 | M25: =CONCATENATE(Suspendidos[[#This Row],[CLIENTE]]," ",Suspendidos[[#This Row],[ATM]]) -> BAPRO 11347
A26: 101162228 | B26: BAPRO | C26: 8648 | D26: Vicente, Francisco Ariel | E26: Vicente, Francisco Ariel | F26: 46080 | G26: [26/02/2026] se solicita repuesto. | H26: Dispensador | I26: SERVICE CALL | J26: Centro | K26: GRG Banking | L26: GRG H22 | M26: =CONCATENATE(Suspendidos[[#This Row],[CLIENTE]]," ",Suspendidos[[#This Row],[ATM]]) -> BAPRO 8648
A27: 101162137 | B27: BANCO CREDICOOP | C27: 808971 | D27: Buratti, Fabian | E27: Chiriello, Pablo Javier | F27: 46080 | G27: [26/02/2026] se acomodó, precintó y conectó cableado de lectora. pruebas de diagnóstico y de servicio ok | H27: Lectora de tarjetas | I27: SERVICE CALL | J27: Atlántica | K27: GRG | L27: GRG H34 | M27: =CONCATENATE(Suspendidos[[#This Row],[CLIENTE]]," ",Suspendidos[[#This Row],[ATM]]) -> BANCO CREDICOOP 808971
A28: 101161770 | B28: CENCOSUD S.A | C28: 008681069470 | D28: Montiel, Juan Fernando | E28: Montiel, Juan Fernando | F28: 46080 | G28: [26/02/2026] se realiza relevamiento de equipo se limpia cabezal y se realizaron pruebas correspondientes | H28: Relevamiento ATM | I28: SERVICE CALL | J28: Atlántica | K28: SNBC | L28: CTE2 SNBC | M28: =CONCATENATE(Suspendidos[[#This Row],[CLIENTE]]," ",Suspendidos[[#This Row],[ATM]]) -> CENCOSUD S.A 008681069470
A29: 101161765 | B29: SAIEP | C29: 004677076970 | D29: Ibañez, Pablo Fernando | E29: Ruejas, Nelson | F29: 46080 | G29: [26/02/2026] verificacion de modulo cabezal,limpieza de rodillos calibracion de caida de billetes y ajuste de posicion de monitor,se realizaron pruebas de deposito,ok | H29: Modulo SNBC | I29: SERVICE CALL | J29: Suroeste | K29: SNBC | L29: CTE2 SNBC | M29: =CONCATENATE(Suspendidos[[#This Row],[CLIENTE]]," ",Suspendidos[[#This Row],[ATM]]) -> SAIEP 004677076970
A30: 101162134 | B30: BAPRO | C30: 8124 | D30: Chiriello, Pablo Javier | E30: Chiriello, Pablo Javier | F30: 46080 | G30: [26/02/2026] se reemplazó lectora. pruebas de diagnóstico y de servicio ok | H30: Lectora de tarjetas | I30: SERVICE CALL | J30: Atlántica | K30: GRG Banking | L30: GRG H22 | M30: =CONCATENATE(Suspendidos[[#This Row],[CLIENTE]]," ",Suspendidos[[#This Row],[ATM]]) -> BAPRO 8124
A31: 101162119 | B31: BAPRO | C31: 11125 | D31: Garcia, Alejandro Javier | E31: Martos, Jose Angel | F31: 46080 | G31: [26/02/2026] cambio de shutter._x000D_ modulo probado en produccion junto al funcionario._x000D_ Equipo operativo. | H31: Dispensador | I31: SERVICE CALL | J31: Oeste | K31: GRG | L31: GRG H34 | M31: =CONCATENATE(Suspendidos[[#This Row],[CLIENTE]]," ",Suspendidos[[#This Row],[ATM]]) -> BAPRO 11125
A32: 101162073 | B32: BANCO NACION | C32: 7913 | D32: Aldayturriaga, Martin | E32: Aldayturriaga, Martin | F32: 46080 | G32: [26/02/2026] Al momento de llegar el ATM se encontraba funcionando correctamente, se verificó el estado de los sensores, se realizó limpieza, se realizaron pruebas en producción en presencia de funcionario | H32: Dispensador | I32: SERVICE CALL | J32: Oeste | K32: GRG Banking | L32: GRG H22 | M32: =CONCATENATE(Suspendidos[[#This Row],[CLIENTE]]," ",Suspendidos[[#This Row],[ATM]]) -> BANCO NACION 7913
A33: 101161828 | B33: BAPRO | C33: 11214 | D33: Garcia, Alejandro Javier | E33: Garcia, Alejandro Javier | F33: 46080 | G33: [26/02/2026] Se acomodaron correas horizontales del presentador y del note feeder del módulo 1._x000D_ Pruebas en servicio junto a funcionario exitosas | H33: Dispensador | I33: SERVICE CALL | J33: Oeste | K33: GRG | L33: GRG H34 | M33: =CONCATENATE(Suspendidos[[#This Row],[CLIENTE]]," ",Suspendidos[[#This Row],[ATM]]) -> BAPRO 11214
A34: 101161275 | B34: BANCO NACION | C34: 7651 | D34: Montiel, Juan Fernando | E34: Montiel, Juan Fernando | F34: 46080 | G34: [26/02/2026] se realiza cambio de stacker por falla en R/T se realizaron pruebas correspondientes con funcionario // [24/02/2026] se suspende pedido por solicitud de repuestos | H34: Dispensador | I34: SERVICE CALL | J34: Atlántica | K34: DIEBOLD NIXDORF | L34: CS280 | M34: =CONCATENATE(Suspendidos[[#This Row],[CLIENTE]]," ",Suspendidos[[#This Row],[ATM]]) -> BANCO NACION 7651
... A155: 101159656 | B155: SAIEP | C155: 004677009870 | D155: Allende, Martin Leandro | E155: Allende, Martin Leandro | F155: 46068 | G155: [14/02/2026] Se remasterizo terminal a fin de actualizar software aplicativo Aleph. Se realizó mantenimiento preventivo ya que se encontraba con mucho polvillo. Se realizaron pruebas de depósitos con empleados de la Entidad sin fallas. // SE comunica porque no le están impactando los depósitos en el sistema, el ultimo que refleja es a las 14:11, se verifica en el jornal que tiene varios depósitos realizado despues de dicha hora. Realizar backup de los cashin se requiere actualizar aleph | H155: Software Configuración | I155: SERVICE CALL | J155: La Pampa | K155: SNBC | L155: CTE2 SNBC | M155: =CONCATENATE(Suspendidos[[#This Row],[CLIENTE]]," ",Suspendidos[[#This Row],[ATM]]) -> SAIEP 004677009870
A156: 101159533 | B156: RELEVAMIENTOS CASH TODAY | C156: Relevamiento PATAGONIA | D156: Hernandez, Marcos Alberto | E156: Pavon, Diego Emanuel | F156: 46067 | G156: [14/02/2026] Se realizo relevaliento de MAE. Se envio el mismo a la cadena de mail correspondiente | H156: Relevamiento ATM | I156: SERVICE CALL | J156: La Pampa | M156: =CONCATENATE(Suspendidos[[#This Row],[CLIENTE]]," ",Suspendidos[[#This Row],[ATM]]) -> RELEVAMIENTOS CASH TODAY Relevamiento PATAGONIA
A157: 101159531 | B157: CARREFOUR | C157: 006624018970 | D157: Allende, Martin Leandro | E157: Allende, Martin Leandro | F157: 46067 | G157: [14/02/2026] Al momento de la visita técnica no se detecta mal funcionamiento de la terminal. Se realiza depósito con encargada sin fallas. | H157: Sin Fallas | I157: SERVICE CALL | J157: La Pampa | K157: SNBC | L157: CTE2 SNBC | M157: =CONCATENATE(Suspendidos[[#This Row],[CLIENTE]]," ",Suspendidos[[#This Row],[ATM]]) -> CARREFOUR 006624018970
A158: 101159275 | B158: CORREDORES VIALES S.A | C158: 010253004870 | D158: Martos, Jose Angel | E158: Martos, Jose Angel | F158: 46067 | G158: [13/02/2026] se masterizo equipo 1._x000D_ prueba de depositos con el operador ok._x000D_ Equipo operativo // [12/02/2026] se suspende pedido por repuestos // sin conexión | H158: Falla en Software | I158: SERVICE CALL | J158: Oeste | K158: SNBC | L158: CTI90 SNBC | M158: =CONCATENATE(Suspendidos[[#This Row],[CLIENTE]]," ",Suspendidos[[#This Row],[ATM]]) -> CORREDORES VIALES S.A 010253004870
A159: 101159456 | B159: GOYAIKE S.A.A.C.I.Y.F | C159: 002214003670 | D159: Montiel, Juan Fernando | E159: Montiel, Juan Fernando | F159: 46067 | G159: [13/02/2026] se realiza instalación de imagen base y aplicativo se realizaron pruebas correspondientes con personal de monitoreo y depósito de prueba con denominaciones varias // Se intenta reinstalar SP y FW pero resulta imposible por mala conectividad y lentitud del equipo, el mismo ademas, se ecuentra desactualizado, se deriva a campo para actualizar a la ultima version de Aleph (4.34) // El cliente llama por le sale escrow trabado , nos conectamos remotamente, se abre le escrow , se reinicia prueba en depositar y queda en espere por favor, se le indica que se fije los compartimientos dice que no hay nada, que le pase un trapito húmedo, depósito y le sale error y se queda tildada, se deriva a monitoreo _x000D_ Tel:1131454404 | H159: SMC – Remasterización | I159: SERVICE CALL | J159: Atlántica | K159: SNBC | L159: CTI UL | M159: =CONCATENATE(Suspendidos[[#This Row],[CLIENTE]]," ",Suspendidos[[#This Row],[ATM]]) -> GOYAIKE S.A.A.C.I.Y.F 002214003670
A160: 101157580 | B160: BANCO CREDICOOP | C160: 812051 | D160: Pavon, Diego Emanuel | E160: Pavon, Diego Emanuel | F160: 46067 | G160: [13/02/2026] Se realizo cambio de CI. Se realizaron pruebas en diagnóstico y producción con funcionario sin presentar fallas. ATM OPERATIVO // [12/02/2026] Se suspende pedido por solicitud de repuesto. // [11/02/2026] Se realizo cambio de UDD de modulo de depositos ENA. Se realizaron pruebas en diagnóstico y persiste falla. Se suspende pedido por repuesto de CI. // [09/02/2026] Se suspende pedido por solicitud de repuesto EDD | H160: Dispensador | I160: SERVICE CALL | J160: Centro | K160: Diebold Nixdorf | L160: OPTEVA MI | M160: =CONCATENATE(Suspendidos[[#This Row],[CLIENTE]]," ",Suspendidos[[#This Row],[ATM]]) -> BANCO CREDICOOP 812051
A161: 101159514 | B161: SAIEP | C161: 004677005270 | D161: Vicente, Francisco Ariel | E161: Vicente, Francisco Ariel | F161: 46067 | G161: [13/02/2026] se ajustó gancia de sensor desde placa arduino y se realizó actualización de firmawere de dicha placa. modulo aceptador de efectivo probado | H161: SMC-Placa / Sensores / Percha | I161: SERVICE CALL | J161: Centro | K161: SNBC | L161: CTI90 SNBC | M161: =CONCATENATE(Suspendidos[[#This Row],[CLIENTE]]," ",Suspendidos[[#This Row],[ATM]]) -> SAIEP 004677005270
A162: 101159403 | B162: EL TEHUELCHE SACICI | C162: 009455000870 | D162: Gonzalez Cabrera, Antonio | E162: Gonzalez Cabrera, Antonio | F162: 46067 | G162: [13/02/2026] Se calibra sensor de presencia de bolsa y se reemplaza latabolsa, queda sin. fallas.Se efectuan varios depósitos, todos exitosos. // Se coordina con caudales_x000D_ 101159403-0. | H162: SMC-Placa / Sensores / Percha | I162: SERVICE CALL | J162: Sur | K162: SNBC | L162: CTI90 SNBC | M162: =CONCATENATE(Suspendidos[[#This Row],[CLIENTE]]," ",Suspendidos[[#This Row],[ATM]]) -> EL TEHUELCHE SACICI 009455000870
A163: 101159450 | B163: SAIEP | C163: 004677023070 | D163: Godoy, Diego | E163: Godoy, Diego | F163: 46067 | G163: [13/02/2026] al arribar a cliente equipo indica error bolsa ausente y bolsa llena. se retira lata bolsa y se revisa. lata bolsa operativa. se realiza prueba de depósito de efectivo con cliente. Prueba EXITOSA. Equipo operativo y en servicio // A coordinar con caudales | H163: P. Chapas/Cerraduras | I163: SERVICE CALL | J163: Sur | K163: SNBC | L163: CTI90 SNBC | M163: =CONCATENATE(Suspendidos[[#This Row],[CLIENTE]]," ",Suspendidos[[#This Row],[ATM]]) -> SAIEP 004677023070
A164: 101159409 | B164: BAPRO | C164: 8288 | D164: Garcia, Alejandro Javier | E164: Hernandez, Marcos Alberto | F164: 46067 | G164: [13/02/2026] Se reemplazo escrow de modulo CAM._x000D_ Se realizaron pruebas en diagnostico sin presentar fallas._x000D_ Se realizaron pruebas en servicio junto al tesorero sin presentar fallas. | H164: Aceptador de Billetes | I164: SERVICE CALL | J164: Oeste | K164: GRG | L164: GRG H34 | M164: =CONCATENATE(Suspendidos[[#This Row],[CLIENTE]]," ",Suspendidos[[#This Row],[ATM]]) -> BAPRO 8288
A165: 101159347 | B165: CORREDORES VIALES S.A | C165: 010253005770 | D165: Garcia, Alejandro Javier | E165: Allende, Martin Leandro | F165: 46067 | G165: [13/02/2026] Se realizó mantenimiento preventivo. Se realizó depósito en producción con supervisor sin fallas. // cliente solicita asistencia ya que comenta que la validadora está muy sucia y se traba constantemente | H165: SMC-Mantenimiento Preventivo | I165: SERVICE CALL | J165: Oeste | K165: SNBC | L165: CTI UL | M165: =CONCATENATE(Suspendidos[[#This Row],[CLIENTE]]," ",Suspendidos[[#This Row],[ATM]]) -> CORREDORES VIALES S.A 010253005770
A166: 101157812 | B166: SAIEP | C166: 004677022570 | D166: Vicente, Francisco Ariel | E166: Vicente, Francisco Ariel | F166: 46067 | G166: [13/02/2026] se realizó cambio de cabezal por varios atascos. modulo aceptador de efectivo probado en producción con funcionario // cliente solicita asistencia ya que comenta que se traba constantemente la validadora al ingresar billetes y que la observa muy sucia a pesar de limpiarla con frecuencia._x000D_ Fernando, 2934531376_x000D_ Horario de tienda: 7 a 22hs | H166: Modulo SNBC | I166: SERVICE CALL | J166: Centro | K166: SNBC | L166: CTI UL | M166: =CONCATENATE(Suspendidos[[#This Row],[CLIENTE]]," ",Suspendidos[[#This Row],[ATM]]) -> SAIEP 004677022570
A167: 101159161 | B167: BANCO CREDICOOP | C167: 814361 | D167: Pavon, Diego Emanuel | E167: Pavon, Diego Emanuel | F167: 46067 | G167: [13/02/2026] Se cambio de placa de dispensador. Se actualizo firmware de la misma. Se realizaron pruebas en diagnostico y produccion con funcionario sin presentar fallas. ATM OPERATIVO. | H167: Dispensador | I167: SERVICE CALL | J167: Centro | K167: GRG Banking | L167: GRG H22 | M167: =CONCATENATE(Suspendidos[[#This Row],[CLIENTE]]," ",Suspendidos[[#This Row],[ATM]]) -> BANCO CREDICOOP 814361
A168: 101159423 | B168: BAPRO | C168: 3149 | D168: Aldayturriaga, Martin | E168: Aldayturriaga, Martin | F168: 46067 | G168: [13/02/2026] Se resuelve problemas con el head del módulo de depósitos, se realizó limpieza, se realizaron pruebas en producción en presencia de funcionario | H168: Aceptador de Billetes | I168: SERVICE CALL | J168: Oeste | K168: GRG | L168: GRG H34 | M168: =CONCATENATE(Suspendidos[[#This Row],[CLIENTE]]," ",Suspendidos[[#This Row],[ATM]]) -> BAPRO 3149
... A329: 101155593 | B329: BANCO NACION | C329: 7745 | D329: Garcia, Alejandro Javier | E329: Garcia, Alejandro Javier | F329: 46056 | G329: [02/02/2026] Se reinstaló software Multivendor con JAM 11.0.0 por estar TTU sin opciones y no responder ante reinicios._x000D_ Pruebas en servicio junto a funcionario exitosas | H329: Monitor cliente | I329: SERVICE CALL | J329: Oeste | K329: GRG Banking | L329: GRG H22 | M329: =CONCATENATE(Suspendidos[[#This Row],[CLIENTE]]," ",Suspendidos[[#This Row],[ATM]]) -> BANCO NACION 7745
A330: 101155601 | B330: PROSEGUR - CRP | C330: MardelPlata-001 | D330: Chiriello, Pablo Javier | E330: Chiriello, Pablo Javier | F330: 46056 | G330: [02/02/2026] se ajusto cableado de monitor. pruebas ok // _x000D_ El equipo CRP que funciona en nuestro sector se encuentra fuera de servicio porque no está efectuando la selección de sectores al presionar la pantalla táctil_x000D_ Quedamos a la espera de v. instrucciones para la resolución del inconveniente | H330: Monitor cliente | I330: SERVICE CALL | J330: Atlántica | M330: =CONCATENATE(Suspendidos[[#This Row],[CLIENTE]]," ",Suspendidos[[#This Row],[ATM]]) -> PROSEGUR - CRP MardelPlata-001
A331: 101155574 | B331: BAPRO | C331: 6682 | D331: Pavon, Diego Emanuel | E331: Vicente, Francisco Ariel | F331: 46056 | G331: [02/02/2026] se realizó revisión completa de modulo dispensador. se borraron y se volvieron a cargar los tipos de cada gaveta. no se puedo hacer prueba en producción con funcionario ya que el equipo va a ser cargado el dia de mañana. | H331: Dispensador | I331: SERVICE CALL | J331: Centro | K331: GRG | L331: GRG H34 | M331: =CONCATENATE(Suspendidos[[#This Row],[CLIENTE]]," ",Suspendidos[[#This Row],[ATM]]) -> BAPRO 6682
A332: 101155547 | B332: SAIEP | C332: 004677020170 | D332: Hernandez, Marcos Alberto | E332: Allende, Martin Leandro | F332: 46056 | G332: [02/02/2026] Se reiniciaron módem, y router. Se verificó conectividad con Mesa de Ayuda. Conexión OK. // Sin conexion con la maquina. _x000D_ | H332: Comunicaciones | I332: SERVICE CALL | J332: La Pampa | K332: SNBC | L332: CTI90 SNBC | M332: =CONCATENATE(Suspendidos[[#This Row],[CLIENTE]]," ",Suspendidos[[#This Row],[ATM]]) -> SAIEP 004677020170
A333: 101155047 | B333: BANCO HIPOTECARIO | C333: 015TI0002 | D333: Buratti, Fabian | E333: Castaño, Matias | F333: 46056 | G333: [02/02/2026] se suspende por no contar con autorización de ingreso. | H333: Aceptador de Billetes | I333: SERVICE CALL | J333: Atlántica | K333: Diebold Nixdorf | L333: TAS MI | M333: =CONCATENATE(Suspendidos[[#This Row],[CLIENTE]]," ",Suspendidos[[#This Row],[ATM]]) -> BANCO HIPOTECARIO 015TI0002
A334: 101155556 | B334: BANCO CREDICOOP | C334: 808971 | D334: Buratti, Fabian | E334: Chiriello, Pablo Javier | F334: 46056 | G334: [02/02/2026] se desarmó módulo y submódulos, realizando limpieza de los mismos. se hicieron pruebas de diagnóstico y de servicio ok | H334: Aceptador de Billetes | I334: SERVICE CALL | J334: Atlántica | K334: GRG | L334: GRG H34 | M334: =CONCATENATE(Suspendidos[[#This Row],[CLIENTE]]," ",Suspendidos[[#This Row],[ATM]]) -> BANCO CREDICOOP 808971
A335: 101155082 | B335: BAPRO | C335: 4671 | D335: Montiel, Juan Fernando | E335: Montiel, Juan Fernando | F335: 46056 | G335: [02/02/2026] se solucionó problema en lector de tarjetas no leía chips . se realizaron pruebas correspondientes con funcionario | H335: Lectora de tarjetas | I335: SERVICE CALL | J335: Atlántica | K335: GRG | L335: GRG H34 | M335: =CONCATENATE(Suspendidos[[#This Row],[CLIENTE]]," ",Suspendidos[[#This Row],[ATM]]) -> BAPRO 4671
A336: 101155562 | B336: TARJETA NARANJA | C336: 001035211870 | D336: Gonzalez Cabrera, Antonio | E336: Gonzalez Cabrera, Antonio | F336: 46056 | G336: [02/02/2026] Se configura Booteo de la BIOS enicializa Windows. Se efectuan varios depósitos, todos exitosos. // El cliente llama por que la mae está en negro, no pudios conectarnos, remotamente, se le pide que reinicie, sigue pantalla en negro, el cliente solicita técnico, | H336: Software Configuración | I336: SERVICE CALL | J336: Sur | K336: Prosegur | L336: TAS | M336: =CONCATENATE(Suspendidos[[#This Row],[CLIENTE]]," ",Suspendidos[[#This Row],[ATM]]) -> TARJETA NARANJA 001035211870
A337: 101154989 | B337: BANCO CREDICOOP | C337: 808231 | D337: Gonzalez Cabrera, Antonio | E337: Gonzalez Cabrera, Antonio | F337: 46055 | G337: [02/02/2026] Se suspende pedido por sucursal por no poder abrir el tesoro del ATM debido a que los funcionarios que poseen la segunda clave no se encontraban en sucursal , se coordina para mañana a las 8:30. | H337: Gaveta | I337: GAVETAS | J337: Sur | K337: Diebold Nixdorf | L337: OPTEVA MI | M337: =CONCATENATE(Suspendidos[[#This Row],[CLIENTE]]," ",Suspendidos[[#This Row],[ATM]]) -> BANCO CREDICOOP 808231
A338: 101155081 | B338: BAPRO | C338: 11087 | D338: Pavon, Diego Emanuel | E338: Vicente, Francisco Ariel | F338: 46055 | G338: [02/02/2026] se retiró objeto extraño de modulo aceptador de billetes. se limpik y calibró modulo completo. modulo aceptador de billetes probado en producción con funcionario | H338: Aceptador de Billetes | I338: SERVICE CALL | J338: Centro | K338: GRG | L338: GRG H34 | M338: =CONCATENATE(Suspendidos[[#This Row],[CLIENTE]]," ",Suspendidos[[#This Row],[ATM]]) -> BAPRO 11087
A339: 101155063 | B339: BANCO CREDICOOP | C339: 808271 | D339: Gonzalez Cabrera, Antonio | E339: Gonzalez Cabrera, Antonio | F339: 46055 | G339: [02/02/2026] Se suspende pedido por sucursal por no poder abrir el tesoro del ATM debido a que los funcionarios que poseen la segunda clave no se encontraban en sucursal , se coordina para mañana a las 8:30. | H339: Dispensador | I339: SERVICE CALL | J339: Sur | K339: Diebold Nixdorf | L339: OPTEVA | M339: =CONCATENATE(Suspendidos[[#This Row],[CLIENTE]]," ",Suspendidos[[#This Row],[ATM]]) -> BANCO CREDICOOP 808271
A340: 101155079 | B340: BAPRO | C340: 11364 | D340: Buratti, Fabian | E340: Chiriello, Pablo Javier | F340: 46055 | G340: [02/02/2026] se ajusto diverter que estaba flojo y fallaba intermitentemente. pruebas de diagnóstico y de servicio ok. | H340: Dispensador | I340: SERVICE CALL | J340: Atlántica | K340: GRG Banking | L340: GRG H22 | M340: =CONCATENATE(Suspendidos[[#This Row],[CLIENTE]]," ",Suspendidos[[#This Row],[ATM]]) -> BAPRO 11364
A341: 101155481 | B341: GMRA S.A (Samsung) | C341: 010377004370 | D341: Ibañez, Pablo Fernando | E341: Lazzaro, Leonardo | F341: 46055 | G341: [02/02/2026] equipo 100% operativo al momento de la visita y con conectividad | H341: Sin Fallas | I341: SERVICE CALL | J341: Suroeste | K341: CIMA | L341: CIMA | M341: =CONCATENATE(Suspendidos[[#This Row],[CLIENTE]]," ",Suspendidos[[#This Row],[ATM]]) -> GMRA S.A (Samsung) 010377004370
A342: 101155027 | B342: BANCO NACION | C342: 9022 | D342: Chiriello, Pablo Javier | E342: Chiriello, Pablo Javier | F342: 46055 | G342: [02/02/2026] se realizó carga y quedó ok. pruebas de diagnóstico y de servicio ok. (sin sellos por extrabancario) | H342: Dispensador | I342: SERVICE CALL | J342: Atlántica | K342: Diebold Nixdorf | L342: OPTEVA | M342: =CONCATENATE(Suspendidos[[#This Row],[CLIENTE]]," ",Suspendidos[[#This Row],[ATM]]) -> BANCO NACION 9022
... A376: 101154150 | B376: BANCO NACION | C376: 6041 | D376: Allende, Martin Leandro | E376: Allende, Martin Leandro | F376: 46050 | G376: [28/01/2026] Se retiró llave trabada en cerradura, se arregló el mecanismo de apertura de la gaveta de depósitos, y se entregó al funcionario dos llaves de la cerradura. ATM sin fallas. | H376: Aceptador de Billetes | I376: SERVICE CALL | J376: La Pampa | K376: GRG | L376: GRG H34 | M376: =CONCATENATE(Suspendidos[[#This Row],[CLIENTE]]," ",Suspendidos[[#This Row],[ATM]]) -> BANCO NACION 6041
A377: 101154175 | B377: RELEVAMIENTOS CASH TODAY | C377: Relevamiento PATAGONIA | D377: Hernandez, Marcos Alberto | E377: Castaño, Matias | F377: 46050 | G377: [28/01/2026] relevamiento | H377: Relevamiento ATM | I377: SERVICE CALL | J377: La Pampa | M377: =CONCATENATE(Suspendidos[[#This Row],[CLIENTE]]," ",Suspendidos[[#This Row],[ATM]]) -> RELEVAMIENTOS CASH TODAY Relevamiento PATAGONIA
A378: 101154241 | B378: BANCO CREDICOOP | C378: 825431 | D378: Lazzaro, Leonardo | E378: Lazzaro, Leonardo | F378: 46050 | G378: [28/01/2026] cambio de correa de presentador. limpieza en general. pruebas de dispensador realizadas en diagnostico | H378: Dispensador | I378: SERVICE CALL | J378: Suroeste | K378: Diebold Nixdorf | L378: OPTEVA | M378: =CONCATENATE(Suspendidos[[#This Row],[CLIENTE]]," ",Suspendidos[[#This Row],[ATM]]) -> BANCO CREDICOOP 825431
A379: 101154275 | B379: BANCO LA PAMPA | C379: 87 | D379: Hernandez, Marcos Alberto | E379: Hernandez, Marcos Alberto | F379: 46050 | G379: [28/01/2026] Se realizo reparación de lectora de tarjetas._x000D_ Se realizo prueba en servicio junto al funcionario sin presentar fallas. | H379: Lectora de tarjetas | I379: SERVICE CALL | J379: La Pampa | K379: DIEBOLD NIXDORF | L379: CS2070 | M379: =CONCATENATE(Suspendidos[[#This Row],[CLIENTE]]," ",Suspendidos[[#This Row],[ATM]]) -> BANCO LA PAMPA 87
A380: 101154184 | B380: BANCO NACION | C380: 7881 | D380: Chiriello, Pablo Javier | E380: Chiriello, Pablo Javier | F380: 46050 | G380: [28/01/2026] sin diferencia. se equiparó con sobrante del día anterior. (no hay faltante) // SLA 1 de 5 | H380: Sin Fallas | I380: SERVICE CALL | J380: Atlántica | K380: GRG Banking | L380: GRG H22 | M380: =CONCATENATE(Suspendidos[[#This Row],[CLIENTE]]," ",Suspendidos[[#This Row],[ATM]]) -> BANCO NACION 7881
A381: 101153702 | B381: SAIEP | C381: 004677023970 | D381: Gonzalez Cabrera, Antonio | E381: Gonzalez Cabrera, Antonio | F381: 46050 | G381: [27/01/2026] Se reemplaza SIM y se verifica conexion con Monitoreo , conexión exitosa. // [26/01/2026] Se verifica conectividad del router, intentos sin éxito. Se apaga y enciende router sigue sin comunicaciones. Se contacta con el especialista Ariel Vassena y después de varias pruebas se solicita reemplazar el router. // se guia al cliente para reiniciar el router y revisar conexiónes pero el error persiste. | H381: Comunicaciones | I381: SERVICE CALL | J381: Sur | K381: SNBC | L381: CTI UL | M381: =CONCATENATE(Suspendidos[[#This Row],[CLIENTE]]," ",Suspendidos[[#This Row],[ATM]]) -> SAIEP 004677023970
A382: 101153941 | B382: FAVANET | C382: 004925004170 | D382: Castaño, Matias | E382: Castaño, Matias | F382: 46050 | G382: [27/01/2026] se realiza correct de cabezal // se abre scrow, se retira atasco, pero al probarlo nuevamente atasca, se abre nuevamente, se retira el atasco, se hace otra prueba y vuelve a ttabar pero esta vez el equipo tambien se tilda | H382: SMC-Error Recontadora | I382: SERVICE CALL | J382: Atlántica | K382: SNBC | L382: CTI90 SNBC | M382: =CONCATENATE(Suspendidos[[#This Row],[CLIENTE]]," ",Suspendidos[[#This Row],[ATM]]) -> FAVANET 004925004170
A383: 101154095 | B383: M.G BAHIA SRL | C383: 006824000170 | D383: Pavon, Diego Emanuel | E383: Pavon, Diego Emanuel | F383: 46050 | G383: [27/01/2026] Se rompió base en 3D de sensor de presencia de bolsa. Se reparo en campo. Se realizaron pruebas en diagnóstico y producción con funcionario sin presentar fallas. MAE OPERARIVA // _x000D_ a coordinar con caudales_x000D_ Se dio de alta el Requerimiento 101154095-0._x000D_ | H383: SMC-Lata defectuosa | I383: SERVICE CALL | J383: Centro | K383: SNBC | L383: CTE2 SNBC | M383: =CONCATENATE(Suspendidos[[#This Row],[CLIENTE]]," ",Suspendidos[[#This Row],[ATM]]) -> M.G BAHIA SRL 006824000170
A384: 101154140 | B384: SAIEP | C384: 004677005170 | D384: Vicente, Francisco Ariel | E384: Vicente, Francisco Ariel | F384: 46050 | G384: [27/01/2026] se realizó cambio de panel de cerradura intergard. ya que el anterior contaba con falla en mecanismo. equipo cerrado y probado en producción con funcionario // se coordinacon caudales | H384: P. Chapas/Cerraduras | I384: SERVICE CALL | J384: Centro | K384: SNBC | L384: CTI UL | M384: =CONCATENATE(Suspendidos[[#This Row],[CLIENTE]]," ",Suspendidos[[#This Row],[ATM]]) -> SAIEP 004677005170
A385: 101154180 | B385: CENCOSUD S.A | C385: 008681010270 | D385: Gonzalez Cabrera, Antonio | E385: Gonzalez Cabrera, Antonio | F385: 46050 | G385: [27/01/2026] Se realiza revisión de impresora , presenta falla aleatoria en Guillotina, se reemplaza impresora , queda sin falla .Se realizan varias operaciones de impresión, todas exitosas. // erro de impresión se intenta que quede operativa pero el cliente retira el atasco imprime, pero al realizar re impresión se genera el atasco nuevamente | H385: Impresora de cliente | I385: SERVICE CALL | J385: Sur | K385: SNBC | L385: CTE2 SNBC | M385: =CONCATENATE(Suspendidos[[#This Row],[CLIENTE]]," ",Suspendidos[[#This Row],[ATM]]) -> CENCOSUD S.A 008681010270
A386: 101154092 | B386: BAPRO | C386: 11411 | D386: Martos, Jose Angel | E386: Martos, Jose Angel | F386: 46050 | G386: [27/01/2026] actualizacion de template 5.0._x000D_ modulo probado en produccion junto al funcionario._x000D_ Equipo operativo. | H386: Software Configuración | I386: SERVICE CALL | J386: Oeste | K386: GRG | L386: GRG H34 | M386: =CONCATENATE(Suspendidos[[#This Row],[CLIENTE]]," ",Suspendidos[[#This Row],[ATM]]) -> BAPRO 11411
A387: 101154094 | B387: BAPRO | C387: 11209 | D387: Aldayturriaga, Martin | E387: Aldayturriaga, Martin | F387: 46050 | G387: [27/01/2026] Al momento de llegar el ATM se encontraba funcionando correctamente, el tesorero me indica que no hizo el pedido y que e ATM funciona correctamente | H387: Sin Fallas | I387: SERVICE CALL | J387: Oeste | K387: GRG | L387: GRG H34 | M387: =CONCATENATE(Suspendidos[[#This Row],[CLIENTE]]," ",Suspendidos[[#This Row],[ATM]]) -> BAPRO 11209
A388: 101154115 | B388: BANCO LA PAMPA | C388: 163 | D388: Allende, Martin Leandro | E388: Allende, Martin Leandro | F388: 46050 | G388: [27/01/2026] Se destrabó tarjeta de crédito. Se reemplazó lectora de tarjetas. Se realizaron pruebas en diagnóstico y producción sin fallas // se solicita UB | H388: Aceptador de Billetes | I388: SERVICE CALL | J388: La Pampa | K388: Diebold Nixdorf | L388: OPTEVA | M388: =CONCATENATE(Suspendidos[[#This Row],[CLIENTE]]," ",Suspendidos[[#This Row],[ATM]]) -> BANCO LA PAMPA 163
A389: 101154068 | B389: BAPRO | C389: 6616 | D389: Buratti, Fabian | E389: Chiriello, Pablo Javier | F389: 46050 | G389: [27/01/2026] se reemplazó shutter. pruebas de diagnóstico y de servicio ok | H389: Dispensador | I389: SERVICE CALL | J389: Atlántica | K389: GRG Banking | L389: GRG H22 | M389: =CONCATENATE(Suspendidos[[#This Row],[CLIENTE]]," ",Suspendidos[[#This Row],[ATM]]) -> BAPRO 6616
... A439: 101153194 | B439: SAIEP | C439: 004677002870 | D439: Corti Victor | E439: Corti Victor | F439: 46045 | G439: [22/01/2026] se elimina atasco. se controla equipo y sensores. se prueba con el cliente . ok // El cliente se contacta por que la mae quedó fuera de servicio, se reinicia, y vuelve sigue igual , se le consulta si esta todo enchufado dice nosotros no queremos tocar nada, sigue fuera de servicio se deriva a técnico. | H439: SMC-Billetes Atascados | I439: SERVICE CALL | J439: Contratistas | K439: CIMA | L439: CIMA | M439: =CONCATENATE(Suspendidos[[#This Row],[CLIENTE]]," ",Suspendidos[[#This Row],[ATM]]) -> SAIEP 004677002870
A440: 101152177 | B440: PROSEGUR - CRP | C440: Ushuaia-001 | D440: Corti Victor | E440: Corti Victor | F440: 46045 | G440: [22/01/2026] se revisa control de acceso, encendido y conectividad, se detiva a especialista Santiago Falcon que actializo version del sistema y se realizan pruebas de funcionamiento. | H440: Desconexion de equipo | I440: SERVICE CALL | J440: Contratistas | M440: =CONCATENATE(Suspendidos[[#This Row],[CLIENTE]]," ",Suspendidos[[#This Row],[ATM]]) -> PROSEGUR - CRP Ushuaia-001
A441: 101153174 | B441: BAPRO | C441: 3149 | D441: Aldayturriaga, Martin | E441: Aldayturriaga, Martin | F441: 46045 | G441: [22/01/2026] Se desarmo el módulo de depósitos y se realizó limpieza, se realizaron pruebas en producción en presencia de funcionario | H441: Aceptador de Billetes | I441: SERVICE CALL | J441: Oeste | K441: GRG | L441: GRG H34 | M441: =CONCATENATE(Suspendidos[[#This Row],[CLIENTE]]," ",Suspendidos[[#This Row],[ATM]]) -> BAPRO 3149
A442: 101153144 | B442: BAPRO | C442: 11413 | D442: Buratti, Fabian | E442: Ruejas, Nelson | F442: 46045 | G442: [22/01/2026] reparacion de dispenser ,pruebas ok | H442: Dispensador | I442: SERVICE CALL | J442: Atlántica | K442: GRG | L442: GRG H34 | M442: =CONCATENATE(Suspendidos[[#This Row],[CLIENTE]]," ",Suspendidos[[#This Row],[ATM]]) -> BAPRO 11413
A443: 101152357 | B443: ACA | C443: 002359016170 | D443: Montiel, Juan Fernando | E443: Montiel, Juan Fernando | F443: 46045 | G443: [22/01/2026] se realiza cambio de pantalla se realizaron pruebas correspondientes // [20/01/2026] se suspende pedido por solicitud de repuestos // cliente indica que se le rompio la pantalla y no funciona el tactil en la parte superior | H443: Monitor cliente | I443: SERVICE CALL | J443: Atlántica | K443: CIMA | L443: CIMA | M443: =CONCATENATE(Suspendidos[[#This Row],[CLIENTE]]," ",Suspendidos[[#This Row],[ATM]]) -> ACA 002359016170
A444: 101152900 | B444: COOPERATIVA OBRERA LIMITADA DE CONSUMO BAHIA BLANCA | C444: 002472004370 | D444: Pavon, Diego Emanuel | E444: Pavon, Diego Emanuel | F444: 46045 | G444: [22/01/2026] Se realizo remasterizacion. No se pudo realizar el respaldo de las carpetas ya que no se tenía acceso a Windows. Se realizaron pruebas en diagnóstico y producción con funcionario sin presentar fallas. // Se deriva a tecnico, OCS caido y no permite hacer el desbloqueo. | H444: Instalacion | I444: SERVICE CALL | J444: Centro | K444: SNBC | L444: CTE2 SNBC | M444: =CONCATENATE(Suspendidos[[#This Row],[CLIENTE]]," ",Suspendidos[[#This Row],[ATM]]) -> COOPERATIVA OBRERA LIMITADA DE CONSUMO BAHIA BLANCA 002472004370
A445: 101153121 | B445: BANCO LA PAMPA | C445: 148 | D445: Garcia, Alejandro Javier | E445: Garcia, Alejandro Javier | F445: 46045 | G445: [22/01/2026] Se suspende por pedido de parte (stacker) | H445: Dispensador | I445: SERVICE CALL | J445: Oeste | K445: DIEBOLD NIXDORF | L445: CS2070 | M445: =CONCATENATE(Suspendidos[[#This Row],[CLIENTE]]," ",Suspendidos[[#This Row],[ATM]]) -> BANCO LA PAMPA 148
A446: 101152657 | B446: VALLARTA S.A | C446: 002121000570 | D446: Castaño, Matias | E446: Castaño, Matias | F446: 46045 | G446: [22/01/2026] se repara cabezal snbc // [21/01/2026] suspende por pedido de parte | H446: SMC-Error Recontadora | I446: SERVICE CALL | J446: Atlántica | K446: SNBC | L446: CTI90 SNBC | M446: =CONCATENATE(Suspendidos[[#This Row],[CLIENTE]]," ",Suspendidos[[#This Row],[ATM]]) -> VALLARTA S.A 002121000570
A447: 101152923 | B447: BANCO NACION | C447: 4191 | D447: Buratti, Fabian | E447: Chiriello, Pablo Javier | F447: 46045 | G447: [22/01/2026] se calibró sensor de tickness. pruebas de diagnóstico y de servicio ok junto a funcionario | H447: Dispensador | I447: SERVICE CALL | J447: Atlántica | K447: GRG | L447: GRG H34 | M447: =CONCATENATE(Suspendidos[[#This Row],[CLIENTE]]," ",Suspendidos[[#This Row],[ATM]]) -> BANCO NACION 4191
A448: 101153039 | B448: BAPRO | C448: 8541 | D448: Aldayturriaga, Martin | E448: Aldayturriaga, Martin | F448: 46045 | G448: [22/01/2026] Se resuelve problemas con el dispensador de dinero y el módulo de depósitos, se realizó limpieza, se realizaron pruebas en producción en presencia de funcionario | H448: Dispensador | I448: SERVICE CALL | J448: Oeste | K448: GRG | L448: GRG H34 | M448: =CONCATENATE(Suspendidos[[#This Row],[CLIENTE]]," ",Suspendidos[[#This Row],[ATM]]) -> BAPRO 8541
A449: 101152864 | B449: BANCO LA PAMPA | C449: 11 | D449: Allende, Martin Leandro | E449: Hernandez, Marcos Alberto | F449: 46045 | G449: [22/01/2026] Se reemplazaron consumibles de los 4 módulos._x000D_ Se realizo limpieza general del modulo dispensador._x000D_ Se realizaron diversas pruebas em diagnostico sin presentar fallas._x000D_ Se realizaron extracciones en servicio pagando de todas las denominaciones sin presentar fallas. // caudales asiste mañana. | H449: Dispensador | I449: SERVICE CALL | J449: La Pampa | K449: Diebold Nixdorf | L449: OPTEVA | M449: =CONCATENATE(Suspendidos[[#This Row],[CLIENTE]]," ",Suspendidos[[#This Row],[ATM]]) -> BANCO LA PAMPA 11
A450: 101153016 | B450: BAPRO | C450: 6562 | D450: Buratti, Fabian | E450: Ruejas, Nelson | F450: 46045 | G450: [22/01/2026] revision de atm, se comunico con link para verificar falla,se esta actualizando jam luego de masterizacion,se quedo hasta balanceo para seguimiento de conexion.todo ok | H450: Software Configuración | I450: SERVICE CALL | J450: Atlántica | K450: GRG Banking | L450: GRG H22 | M450: =CONCATENATE(Suspendidos[[#This Row],[CLIENTE]]," ",Suspendidos[[#This Row],[ATM]]) -> BAPRO 6562
